Workbook

Sheet 配色及公式
A1: 二元配色 | B1: #FF3C3C | C1: #070707
B2: #FE827E | C2: #82B9DF
A4: 三元配色 | B4: #4E86BD | C4: #F7913E | D4: #5AAA5B
B5: #D22229 | C5: #3A5A8A | D5: #80A6B7
A7: 四元配色 | B7: #2A527A | C7: #43B396 | D7: #E54E72 | E7: #F3C36B
B8: #6B5B95 | C8: #D64161 | D8: #92A8D1 | E8: #88B04B | G8: #6B5B95 | H8: #D64161 | I8: #92A8D1 | J8: #88B04B
A10: 五元配色 | B10: #03579A | C10: #F9C011 | D10: #F3774B | E10: #60C6C9 | F10: #505A6E | G10: {=Easy获取单元格填充颜色值HEX(B10)} -> #NAME?
A11: 六元配色 | B11: #CBB57C | C11: #5CB8CD | D11: #4879B9 | E11: #55AD76 | F11: #C5575A | G11: #7673B5
A12: 自定义配色
B13: C00000 | C13: 333333 | D13: 444758 | E13: 554455 | F13: 555544 | G13: 445544 | H13: 9CD2A4 | I13: FAA61A | J13: B53B6D | K13: 3EBAE9 | L13: F5F5F5
A14: `=INDEX(INDIRECT("'"&$B2&"'!F2:Q2"),MATCH(9.99999999999999E+307,INDIRECT("'"&$B2&"'!F2:Q2")))
A15: `=MATCH("4月",C2:N2,0) `取列序号
A16: `=INDIRECT("'"&$B2&"'!D2")
A17: `=MID(REPLACE(CELL("filename"),1,FIND("[",CELL("filename")),""),7,1)
A19: [【2025年1月】经营数据.xlsx]年度计划
A20: =CELL("filename",A20) -> C:\Users\Administrator\Desktop\2026年4月分析\[【2026年4月】经营数据 - 空.xlsx]配色及公式
A21: =MID(CELL("filename",A1),FIND("]",CELL("filename",A1))+1,30)&"2024年数据" -> 配色及公式2024年数据
A23: `_ * #,##0.00_ ;[红色]_ * -#,##0.00_ ;_ * "-"??_ ;_ @_
A24: `_ * #,##0.00%_ ;[红色]_ * -#,##0.00%_ ;_ * "-"??_ ;_ @_

Sheet 年度计划
A1: 类别 | B1: 序号 | C1: 指标 | D1: 年度计划 | E1: 北京中言 | F1: 大连凯丹 | G1: 福建钱隆 | H1: 春夏秋冬 | I1: 重庆宜新 | J1: 伯豪瑞廷 | K1: 重庆瑞尔 | L1: 盛唐融信 | M1: 君康经纪 | O1: 第5版预算
A2: 经营指标 | B2: 1 | C2: 营业收入 | D2: =SUM(E2:M2) -> 27810.978 | E2: 8093.1731 | F2: 620.83163 | G2: 6392.8 | H2: 1494.8762 | I2: 709.51636 | J2: 7640.86 | K2: 1454.9973 | L2: 755.36194 | M2: 648.56173
B3: 2 | C3: EBITDA/GOP/扣非利润 | D3: =SUM(E3:M3) -> 12461.674 | E3: 3056.2075 | F3: 259.97843 | G3: 4789.05 | H3: 903.57 | I3: 190.72038 | J3: 3208.89 | K3: -55.516737 | L3: 127.81801 | M3: -19.043753
B4: 3 | C4: 经营活动净现金流 | D4: =SUM(E4:M4) -> 7797.3282 | E4: 112.83542 | F4: 296.47159 | G4: 4232.71 | H4: 664.10036 | I4: 259.62622 | J4: 2140.79 | K4: -178.55007 | L4: 91.154908 | M4: 178.18975
A5: 财务指标 | B5: 4 | C5: 经营支出小计 | D5: =SUM(E5:M5) -> 11893.252 | E5: 2263.9656 | F5: 188.23 | G5: 823.59 | H5: 835.1 | I5: 268.66369 | J5: 4751.02 | K5: 1518.434 | L5: 653.17324 | M5: 591.07578
B6: 4.1 | C6: 固定费用 | D6: =SUM(E6:M6) -> 6663.4234 | E6: 637.27558 | F6: 149.04 | G6: 750.54 | H6: 795.9 | I6: 89.223688 | J6: 2813.65 | K6: 793.4447 | L6: 268.70086 | M6: 365.6486
B7: 4.1.1 | C7: 人力费用 | D7: =SUM(E7:M7) -> 4472.174 | E7: 484.75 | F7: 89.52 | G7: 295.69 | H7: 298.77 | I7: 56.812 | J7: 2148.46 | K7: 700.56 | L7: 195.0858 | M7: 202.52624
B8: 4.1.2 | C8: 日常费用 | D8: =SUM(E8:M8) -> 2191.2494 | E8: 152.52558 | F8: 59.52 | G8: 454.85 | H8: 497.13 | I8: 32.411688 | J8: 665.19 | K8: 92.8847 | L8: 73.615064 | M8: 163.12237
B9: 4.2 | C9: 变动费用 | D9: =SUM(E9:M9) -> 5229.8288 | E9: 1626.69 | F9: 39.19 | G9: 73.05 | H9: 39.2 | I9: 179.44 | J9: 1937.37 | K9: 724.9893 | L9: 384.47237 | M9: 225.42717
B10: 4.2.1 | C10: 经营变动费用 | D10: =SUM(E10:M10) -> 2989.9257 | E10: 1626.69 | F10: 39.19 | G10: 73.05 | H10: 39.2 | I10: 179.44 | J10: 647.28 | K10: 225.42 | L10: 81.588744 | M10: 78.066998
B11: 4.2.2 | C11: 营业成本 | D11: =SUM(E11:M11) -> 2239.9031 | E11: 0 | F11: 0 | G11: 0 | H11: 0 | I11: 0 | J11: 1290.09 | K11: 499.5693 | L11: 302.88363 | M11: 147.36017
B12: 5 | C12: 资本性支出 | D12: =SUM(E12:M12) -> 1648.888 | E12: 842 | F12: 79.6 | G12: 226.85 | H12: 52 | I12: 0 | J12: 294.498 | K12: 153.94 | L12: 0 | M12: 0
A13: 业务指标 | B13: 6 | C13: 期末出租率/月均入住率 | E13: 0.65 | F13: 0.7171 | G13: 0.5715 | H13: 0.69 | I13: 0.5805 | J13: 0.8203 | K13: 0.71 | L13: 0 | M13: 0
B14: 7 | C14: 回款率 | E14: 0.95 | F14: 0.95 | G14: 0.95 | H14: 0.89 | I14: 0.95 | J14: 0.842 | K14: 0.98 | L14: 0 | M14: 0
B15: 8 | C15: OTA网络评价 | E15: 0 | F15: 0 | G15: 0 | H15: 0 | I15: 0 | J15: 4.7 | K15: 4.7 | L15: 0 | M15: 0
B16: 9 | C16: 规模保费 | D16: =SUM(E16:M16) -> 3652 | E16: 0 | F16: 0 | G16: 0 | H16: 0 | I16: 0 | J16: 0 | K16: 0 | L16: 862 | M16: 2790
B17: 10 | C17: 13月继续率
B18: 11 | C18: 25月继续率
A21: 二元配色 | B21: #FF3C3C | C21: #070707
B22: #FE827E | C22: #82B9DF
A24: 三元配色 | B24: #4E86BD | C24: #F7913E | D24: #5AAA5B | F24: #4CAF50
B25: #D22229 | C25: #3A5A8A | D25: #80A6B7 | F25: #F44336
A27: 四元配色 | B27: #2A527A | C27: #43B396 | D27: #E54E72
B28: #6B5B95 | C28: #D64161 | D28: #92A8D1 | E28: #88B04B | F28: #F3C36B | I28: #6B5B95 | J28: #D64161 | K28: #92A8D1 | L28: #88B04B
A30: 五元配色 | B30: #03579A | C30: #F9C011 | D30: #F3774B | E30: #60C6C9 | F30: #505A6E | G30: {=Easy获取单元格填充颜色值HEX(B30)} -> #NAME?
A31: 六元配色 | B31: #CBB57C | C31: #5CB8CD | D31: #4879B9 | E31: #55AD76 | F31: #C5575A | G31: #7673B5
A32: 自定义配色
B33: C00000 | C33: 333333 | D33: 444758 | E33: 554455 | F33: 555544 | G33: 445544 | H33: 9CD2A4 | I33: FAA61A | J33: B53B6D | K33: 3EBAE9 | L33: F5F5F5
A35: `=INDEX(INDIRECT("'"&$B2&"'!F2:Q2"),MATCH(9.99999999999999E+307,INDIRECT("'"&$B2&"'!F2:Q2")))
A36: `=MATCH("4月",C2:N2,0) `取列序号
A37: `=INDIRECT("'"&$B2&"'!D2")
A38: `=MID(REPLACE(CELL("filename"),1,FIND("[",CELL("filename")),""),7,1)
A39: `=GET.WORKBOOK(1)
A40: `=CELL("filename",A43)
A41: `=MID(CELL("filename",A1),FIND("]",CELL("filename",A1))+1,30)
A42: `=SHEETSNAME()
A43: `_ * #,##0.00_ ;[红色]_ * -#,##0.00_ ;_ * "-"??_ ;_ @_
A44: `_ * #,##0.00%_ ;[红色]_ * -#,##0.00%_ ;_ * "-"??_ ;_ @_
A45: `=INDIRECT("'.\\经营报表\\["&SHEETSNAME(A1)&".xlsx]指标统计'!$G$4:$R$20")
A46: `=INDIRECT("G2:"&CELL("address",INDEX(G2:R2,0,MATCH(填写页!$A$1,G1:R1,0))))
... A55: `=IF(COLUMN()-3>MATCH(填写页!$A$1,$C$69:$N$69,0),NA(),IF(D$71<>0,IFERROR((D$71-C$71)/ABS(C$71),NA()),NA()))

Sheet 分解计划
A1: 2026年 营收分解 | B1: 合计 | C1: 1月 | D1: 2月 | E1: 3月 | F1: 4月 | G1: 5月 | H1: 6月 | I1: 7月 | J1: 8月 | K1: 9月 | L1: 10月 | M1: 11月 | N1: 12月 | O1: 一季度 | P1: 二季度 | Q1: 三季度 | R1: 四季度 | S1: 核对 | T1: 第5版预算
A2: 北京中言 | B2: =SUM(C2:N2) -> 8093.1731 | C2: 732.94 | D2: 699.13 | E2: 669.14 | F2: 674.14 | G2: 653.32 | H2: 658.05 | I2: 667.56052 | J2: 672.56052 | K2: 695.58052 | L2: 658.28052 | M2: 637.90052 | N2: 674.57052 | O2: =SUM(C2:E2) -> 2101.21 | P2: =SUM(F2:H2) -> 1985.51 | Q2: =SUM(I2:K2) -> 2035.7016 | R2: =SUM(L2:N2) -> 1970.7516
A3: 大连凯丹 | B3: =SUM(C3:N3) -> 620.83163 | C3: 51.249258 | D3: 52.248496 | E3: 52.748496 | F3: 53.066638 | G3: 53.925322 | H3: 53.95222 | I3: 54.005277 | J3: 48.769356 | K3: 49.289356 | L3: 49.740978 | M3: 50.363847 | N3: 51.472387 | O3: =SUM(C3:E3) -> 156.24625 | P3: =SUM(F3:H3) -> 160.94418 | Q3: =SUM(I3:K3) -> 152.06399 | R3: =SUM(L3:N3) -> 151.57721
A4: 福建钱隆 | B4: =SUM(C4:N4) -> 6392.8 | C4: 518.42 | D4: 511.28 | E4: 515.08 | F4: 522.17 | G4: 527.6 | H4: 556.15 | I4: 539.7 | J4: 540.24 | K4: 538.77 | L4: 544.29 | M4: 536.67 | N4: 542.43 | O4: =SUM(C4:E4) -> 1544.78 | P4: =SUM(F4:H4) -> 1605.92 | Q4: =SUM(I4:K4) -> 1618.71 | R4: =SUM(L4:N4) -> 1623.39
A5: 春夏秋冬 | B5: =SUM(C5:N5) -> 1494.8762 | C5: 111.47143 | D5: 104.85143 | E5: 119.39143 | F5: 121.31143 | G5: 123.64143 | H5: 125.65143 | I5: 129.10143 | J5: 132.81905 | K5: 131.57 | L5: 130.40905 | M5: 131.89905 | N5: 132.75905 | O5: =SUM(C5:E5) -> 335.71429 | P5: =SUM(F5:H5) -> 370.60429 | Q5: =SUM(I5:K5) -> 393.49048 | R5: =SUM(L5:N5) -> 395.06714
A6: 重庆宜新 | B6: =SUM(C6:N6) -> 709.51636 | C6: 35.676006 | D6: 30.697235 | E6: 30.811079 | F6: 47.091121 | G6: 58.274533 | H6: 61.525358 | I6: 71.727659 | J6: 74.003394 | K6: 78.465234 | L6: 73.825582 | M6: 73.709577 | N6: 73.709577 | O6: =SUM(C6:E6) -> 97.184321 | P6: =SUM(F6:H6) -> 166.89101 | Q6: =SUM(I6:K6) -> 224.19629 | R6: =SUM(L6:N6) -> 221.24474
A7: 伯豪瑞廷 | B7: =SUM(C7:N7) -> 7640.86 | C7: 627.4 | D7: 501.26 | E7: 568.4 | F7: 621.71 | G7: 648.43 | H7: 636.67 | I7: 738.6 | J7: 710.2 | K7: 631.86 | L7: 656.96 | M7: 655.88 | N7: 643.49 | O7: =SUM(C7:E7) -> 1697.06 | P7: =SUM(F7:H7) -> 1906.81 | Q7: =SUM(I7:K7) -> 2080.66 | R7: =SUM(L7:N7) -> 1956.33
A8: 重庆瑞尔 | B8: =SUM(C8:N8) -> 1454.9973 | C8: 88.748745 | D8: 89.805349 | E8: 102.23931 | F8: 112.08082 | G8: 133.30063 | H8: 123.26235 | I8: 132.82422 | J8: 133.56007 | K8: 134.93425 | L8: 140.8478 | M8: 134.68742 | N8: 128.70629 | O8: =SUM(C8:E8) -> 280.7934 | P8: =SUM(F8:H8) -> 368.64381 | Q8: =SUM(I8:K8) -> 401.31853 | R8: =SUM(L8:N8) -> 404.24152
A9: 盛唐融信 | B9: =SUM(C9:N9) -> 0 | O9: =SUM(C9:E9) -> 0 | P9: =SUM(F9:H9) -> 0 | Q9: =SUM(I9:K9) -> 0 | R9: =SUM(L9:N9) -> 0
A10: 君康经纪 | B10: =SUM(C10:N10) -> 0 | O10: =SUM(C10:E10) -> 0 | P10: =SUM(F10:H10) -> 0 | Q10: =SUM(I10:K10) -> 0 | R10: =SUM(L10:N10) -> 0
A11: 合计 | B11: =SUM(C11:N11) -> 26407.055 | C11: =SUM(C2:C10) -> 2165.9054 | D11: =SUM(D2:D10) -> 1989.2725 | E11: =SUM(E2:E10) -> 2057.8103 | F11: =SUM(F2:F10) -> 2151.57 | G11: =SUM(G2:G10) -> 2198.4919 | H11: =SUM(H2:H10) -> 2215.2614 | I11: =SUM(I2:I10) -> 2333.5191 | J11: =SUM(J2:J10) -> 2312.1524 | ... R11: =SUM(R2:R10) -> 6722.6022

Sheet 总指标历史分期
A1: 项目 | B1: 项目-202512经营报告 | C1: 年度目标 | D1: 实际达成 | E1: 达成率 | F1: 1月 | G1: 2月 | H1: 3月 | I1: 4月 | J1: 5月 | K1: 6月 | L1: 7月 | M1: 8月 | N1: 9月 | O1: 10月 | P1: 11月 | Q1: 12月
A2: 经营指标 | B2: 营业收入 | C2: 30558.062 | D2: 28181.139 | E2: 0.9222162 | F2: 2407.5807 | G2: 2189.195 | H2: 2310.296 | I2: 2291.0697 | J2: 2312.9612 | K2: 2286.3054 | L2: 2408.0989 | M2: 2398.079 | N2: 2344.1448 | O2: 2403.0649 | P2: 2379.5125 | Q2: 2450.8312
B3: EBITDA/GOP/扣非利润 | C3: 12286.122 | D3: 12945.723 | E3: 1.0536866 | F3: 1207.5316 | G3: 1140.6831 | H3: 1195.0011 | I3: 1077.0275 | J3: 1159.866 | K3: 1143.683 | L3: 1318.2138 | M3: 1180.8945 | N3: 1066.4392 | O3: 1135.0602 | P3: 756.76946 | Q3: 564.55314
B4: 经营活动净现金流 | C4: 12438.211 | D4: 11696.941 | E4: 0.9404038 | F4: 910.68824 | G4: 426.68439 | H4: 2503.3549 | I4: -643.42971 | J4: 811.07116 | K4: 1448.6863 | L4: 3107.3865 | M4: 1343.9718 | N4: 897.2792 | O4: -1020.102 | P4: 1316.0834 | Q4: 595.26667
A5: 财务指标 | B5: 经营支出小计 | C5: 13186.324 | D5: 10699.74 | E5: 0.81142701 | F5: 839.33311 | G5: 696.26559 | H5: 756.11704 | I5: 698.07918 | J5: 806.97896 | K5: 790.02021 | L5: 727.13364 | M5: 864.44935 | N5: 948.92149 | O5: 749.51749 | P5: 1280.7353 | Q5: 1542.1882
B6: 固定费用 | C6: 6611.5022 | D6: 5911.963 | E6: 0.8941936 | F6: 476.38421 | G6: 446.53047 | H6: 459.45352 | I6: 438.68413 | J6: 523.7582 | K6: 495.49687 | L6: 437.09994 | M6: 440.82381 | N6: 460.40832 | O6: 468.11105 | P6: 546.94898 | Q6: 718.26347
B7: 人力费用 | C7: 4635.4091 | D7: 4540.5084 | E7: 0.979527 | F7: 408.94515 | G7: 373.05775 | H7: 369.35821 | I7: 368.11845 | J7: 399.65464 | K7: 366.26882 | L7: 368.46255 | M7: 360.74311 | N7: 379.80615 | O7: 373.57493 | P7: 408.779 | Q7: 363.73966
B8: 日常费用 | C8: 1976.0931 | D8: 1371.4546 | E8: 0.69402326 | F8: 67.439062 | G8: 73.472721 | H8: 90.095305 | I8: 70.565688 | J8: 124.10356 | K8: 129.22805 | L8: 68.63739 | M8: 80.080708 | N8: 80.602175 | O8: 94.53612 | P8: 138.16998 | Q8: 354.52382
B9: 变动费用 | C9: 6574.8319 | D9: 4787.7766 | E9: 0.72819756 | F9: 362.94889 | G9: 249.73512 | H9: 296.66352 | I9: 259.39504 | J9: 283.22076 | K9: 294.52335 | L9: 290.0337 | M9: 423.62554 | N9: 488.51317 | O9: 281.40644 | P9: 733.78629 | Q9: 823.92473
B10: 经营变动费用 | C10: 4138.3189 | D10: 3025.1471 | E10: 0.7310087 | F10: 121.8173 | G10: 111.90372 | H10: 162.00137 | I10: 146.16795 | J10: 143.66212 | K10: 162.74821 | L10: 130.03204 | M10: 249.80461 | N10: 373.26523 | O10: 135.69596 | P10: 616.47767 | Q10: 671.57098
B11: 营业成本 | C11: 2436.5029 | D11: 1762.6294 | E11: 0.72342593 | F11: 241.1316 | G11: 137.8314 | H11: 134.66215 | I11: 113.22709 | J11: 139.55864 | K11: 131.77514 | L11: 160.00167 | M11: 173.82094 | N11: 115.24794 | O11: 145.71048 | P11: 117.30862 | Q11: 152.35375
B12: 资本性支出 | C12: 1801.88 | D12: 515.90854 | E12: 0.28631682 | F12: 2.460841 | G12: 3.909588 | H12: 6.26 | I12: 5.13 | J12: 44.092211 | K12: 26.56 | L12: 32.23 | M12: 5.485002 | N12: 130.23136 | O12: 3.54 | P12: 137.98 | Q12: 118.02954

Sheet 营收历史分体分期
A1: 公司 | B1: 合计 | C1: 1月 | D1: 2月 | E1: 3月 | F1: 4月 | G1: 5月 | H1: 6月 | I1: 7月 | J1: 8月 | K1: 9月 | L1: 10月 | M1: 11月 | N1: 12月
A2: 北京中言 | B2: =SUM(C2:N2) -> 8883.634 | C2: 729.33674 | D2: 719.88634 | E2: 723.07548 | F2: 660.43262 | G2: 664.38903 | H2: 648.15076 | I2: 706.88458 | J2: 750.77023 | K2: 760.98751 | L2: 753.24024 | M2: 811.20804 | N2: 955.27239
A3: 大连凯丹 | B3: =SUM(C3:N3) -> 744.72 | C3: 49.42 | D3: 74.06 | E3: 50.16 | F3: 79.52 | G3: 51.64 | H3: 63.78 | I3: 51.24 | J3: 52.15 | K3: 77.91 | L3: 69.29 | M3: 52.62 | N3: 72.93
A4: 福建钱隆 | B4: =SUM(C4:N4) -> 6811.2442 | C4: 572.83709 | D4: 565.30403 | E4: 575.66361 | F4: 577.57187 | G4: 580.97393 | H4: 593.9485 | I4: 552.75106 | J4: 564.04237 | K4: 577.22315 | L4: 533.70582 | M4: 555.61558 | N4: 561.60721
A5: 春夏秋冬 | B5: =SUM(C5:N5) -> 1372.83 | C5: 111.6 | D5: 120.92 | E5: 113.45 | F5: 120.32 | G5: 111.4 | H5: 106.45 | I5: 110.76 | J5: 103.39 | K5: 119.5 | L5: 126.5 | M5: 118.9 | N5: 109.64
A6: 重庆宜新 | B6: =SUM(C6:N6) -> 708.33923 | C6: 60.893351 | D6: 61.44702 | E6: 62.937243 | F6: 58.140368 | G6: 54.59992 | H6: 57.112126 | I6: 57.107671 | J6: 57.864961 | K6: 58.017674 | L6: 58.010279 | M6: 59.447189 | N6: 62.761423
A7: 伯豪瑞廷 | B7: =SUM(C7:N7) -> 7549.28 | C7: 638.59 | D7: 508.88 | E7: 583.66 | F7: 632.44 | G7: 669.89 | H7: 654.76 | I7: 751.06 | J7: 672.56 | K7: 585.23 | L7: 673.95 | M7: 623.86 | N7: 554.4
A8: 重庆瑞尔 | B8: =SUM(C8:N8) -> 1317.0211 | C8: 122.07055 | D8: 81.181808 | E8: 97.998313 | F8: 102.57482 | G8: 114.97763 | H8: 96.161043 | I8: 113.34614 | J8: 129.57156 | K8: 113.18523 | L8: 138.98558 | M8: 123.14268 | N8: 83.825761
A9: 盛唐融信 | B9: =SUM(C9:N9) -> 585.65702 | C9: 106.32089 | D9: 42.534918 | E9: 75.209191 | F9: 32.272233 | G9: 43.14 | H9: 47.282986 | I9: 52.31881 | J9: 40.126594 | K9: 41.531773 | L9: 32.941035 | M9: 27.427461 | N9: 44.551139
A10: 君康经纪 | B10: =SUM(C10:N10) -> 208.41382 | C10: 16.512047 | D10: 14.980842 | E10: 28.14216 | F10: 27.797814 | G10: 21.950714 | H10: 18.660004 | I10: 12.630675 | J10: 27.603272 | K10: 10.559486 | L10: 16.441937 | M10: 7.291591 | N10: 5.843275
A11: 小计 | B11: =SUM(B2:B10) -> 28181.139 | C11: =SUM(C2:C10) -> 2407.5807 | D11: =SUM(D2:D10) -> 2189.195 | E11: =SUM(E2:E10) -> 2310.296 | F11: =SUM(F2:F10) -> 2291.0697 | G11: =SUM(G2:G10) -> 2312.9612 | H11: =SUM(H2:H10) -> 2286.3054 | I11: =SUM(I2:I10) -> 2408.0989 | ... N11: =SUM(N2:N10) -> 2450.8312

Sheet Sheet2
A1: 65535 | B1: 65535 | C1: 65535 | D1: 65535 | E1: 65535 | F1: 65535 | G1: 65535 | H1: 65535 | I1: 65535

Sheet Sheet1
A1: -1.#QNAN | B1: -1.#QNAN | C1: -1.#QNAN | D1: -1.#QNAN | E1: -1.#QNAN | F1: -1.#QNAN | G1: -1.#QNAN | H1: -1.#QNAN | I1: -1.#QNAN

Sheet 管理建议
A1: 序号 | B1: 名称
A2: 1
A3: 2
A4: 3
A5: 4
A6: 5
A7: 6
A8: 7
A9: 8
A10: 9
A11: 10
A12: 11
A13: 12
... A18: 17

Sheet 填写页
A1: =A2&A3 | C1: 公司 | E1: 序号 | F1: 指标
A2: 4 | C2: 北京中言 | E2: 1 | F2: 营业收入
A3: 月 | C3: 大连凯丹 | E3: 2 | F3: EBITDA/GOP/扣非利润
A4: 2026 | C4: 福建钱隆 | E4: 3 | F4: 经营活动净现金流
A5: 年 | C5: 春夏秋冬 | E5: 4 | F5: 经营支出小计
C6: 重庆宜新 | E6: 4.1 | F6: 固定费用
A7: 序时进度 | C7: 伯豪瑞廷 | E7: 4.1.1 | F7: 人力费用
A8: =A2/12 | C8: 重庆瑞尔 | E8: 4.1.2 | F8: 日常费用
C9: 盛唐融信 | E9: 4.2 | F9: 变动费用
C10: 君康经纪 | E10: 4.2.1 | F10: 经营变动费用
E11: 4.2.2 | F11: 营业成本
E12: 5 | F12: 资本性支出
E13: 6 | F13: 期末出租率/月均入住率
E14: 7 | F14: 回款率
E15: 8 | F15: OTA网络评价
E16: 9 | F16: 规模保费
E17: 10 | F17: 13月继续率
E18: 11 | F18: 25月继续率

Sheet 整体
A1: 类别 | B1: 序号 | C1: 指标 | D1: 年度目标 | E1: 实际达成 | F1: 达成率 | G1: 1月 | H1: 2月 | I1: 3月 | J1: 4月 | K1: 5月 | L1: 6月 | M1: 7月 | N1: 8月 | O1: 9月 | P1: 10月 | Q1: 11月 | R1: 12月 | S1: 同比变化 | T1: ="上年"&填写页!A1&"累计" -> 上年4月累计
A2: 经营指标 | B2: 1 | C2: 营业收入 | D2: =SUM(北京中言:君康经纪!D2) -> 27810.978 | E2: =SUM(北京中言:君康经纪!E2) -> 6293.5502 | F2: =IFERROR(MAX(1+(E2-D2)/ABS(D2),0),) -> 0.22629733 | G2: =IF(VALUE(SUBSTITUTE(G$1,"月",""))<=填写页!$A$2,SUM(北京中言:君康经纪!G2),0) -> 2008.2177 | H2: =IF(VALUE(SUBSTITUTE(H$1,"月",""))<=填写页!$A$2,SUM(北京中言:君康经纪!H2),0) -> 1773.7489 | I2: =IF(VALUE(SUBSTITUTE(I$1,"月",""))<=填写页!$A$2,SUM(北京中言:君康经纪!I2),0) -> 2511.5836 | J2: =IF(VALUE(SUBSTITUTE(J$1,"月",""))<=填写页!$A$2,SUM(北京中言:君康经纪!J2),0) -> 0 | K2: =IF(VALUE(SUBSTITUTE(K$1,"月",""))<=填写页!$A$2,SUM(北京中言:君康经纪!K2),0) -> 0 | L2: =IF(VALUE(SUBSTITUTE(L$1,"月",""))<=填写页!$A$2,SUM(北京中言:君康经纪!L2),0) -> 0 | M2: =IF(VALUE(SUBSTITUTE(M$1,"月",""))<=填写页!$A$2,SUM(北京中言:君康经纪!M2),0) -> 0 | N2: =IF(VALUE(SUBSTITUTE(N$1,"月",""))<=填写页!$A$2,SUM(北京中言:君康经纪!N2),0) -> 0 | ... R2: =IF(VALUE(SUBSTITUTE(R$1,"月",""))<=填写页!$A$2,SUM(北京中言:君康经纪!R2),0) -> 0 | S2: =IFERROR(E2/T2-1,) -> -0.31578022 | T2: =SUM(INDEX(总指标历史分期!$F2:$Q2,1,1):INDEX(总指标历史分期!$F2:$Q2,1,MATCH(填写页!$A$1,总指标历史分期!$F$1:$Q$1,0))) -> 9198.1413
B3: 2 | C3: EBITDA/GOP/扣非利润 | D3: =SUM(北京中言:君康经纪!D3) -> 12461.674 | E3: =SUM(北京中言:君康经纪!E3) -> 3304.0421 | F3: =IFERROR(MAX(1+(E3-D3)/ABS(D3),0),) -> 0.2651363 | G3: =IF(VALUE(SUBSTITUTE(G$1,"月",""))<=填写页!$A$2,SUM(北京中言:君康经纪!G3),0) -> 957.60657 | H3: =IF(VALUE(SUBSTITUTE(H$1,"月",""))<=填写页!$A$2,SUM(北京中言:君康经纪!H3),0) -> 796.55666 | I3: =IF(VALUE(SUBSTITUTE(I$1,"月",""))<=填写页!$A$2,SUM(北京中言:君康经纪!I3),0) -> 1549.8789 | J3: =IF(VALUE(SUBSTITUTE(J$1,"月",""))<=填写页!$A$2,SUM(北京中言:君康经纪!J3),0) -> 0 | K3: =IF(VALUE(SUBSTITUTE(K$1,"月",""))<=填写页!$A$2,SUM(北京中言:君康经纪!K3),0) -> 0 | L3: =IF(VALUE(SUBSTITUTE(L$1,"月",""))<=填写页!$A$2,SUM(北京中言:君康经纪!L3),0) -> 0 | M3: =IF(VALUE(SUBSTITUTE(M$1,"月",""))<=填写页!$A$2,SUM(北京中言:君康经纪!M3),0) -> 0 | N3: =IF(VALUE(SUBSTITUTE(N$1,"月",""))<=填写页!$A$2,SUM(北京中言:君康经纪!N3),0) -> 0 | ... R3: =IF(VALUE(SUBSTITUTE(R$1,"月",""))<=填写页!$A$2,SUM(北京中言:君康经纪!R3),0) -> 0 | S3: =IFERROR(E3/T3-1,) -> -0.28487704 | T3: =SUM(INDEX(总指标历史分期!$F3:$Q3,1,1):INDEX(总指标历史分期!$F3:$Q3,1,MATCH(填写页!$A$1,总指标历史分期!$F$1:$Q$1,0))) -> 4620.2433
B4: 3 | C4: 经营活动净现金流 | D4: =SUM(北京中言:君康经纪!D4) -> 7797.3282 | E4: =SUM(北京中言:君康经纪!E4) -> 2565.3342 | F4: =IFERROR(MAX(1+(E4-D4)/ABS(D4),0),) -> 0.32900169 | G4: =IF(VALUE(SUBSTITUTE(G$1,"月",""))<=填写页!$A$2,SUM(北京中言:君康经纪!G4),0) -> 661.08085 | H4: =IF(VALUE(SUBSTITUTE(H$1,"月",""))<=填写页!$A$2,SUM(北京中言:君康经纪!H4),0) -> 1290.5356 | I4: =IF(VALUE(SUBSTITUTE(I$1,"月",""))<=填写页!$A$2,SUM(北京中言:君康经纪!I4),0) -> 613.71771 | J4: =IF(VALUE(SUBSTITUTE(J$1,"月",""))<=填写页!$A$2,SUM(北京中言:君康经纪!J4),0) -> 0 | K4: =IF(VALUE(SUBSTITUTE(K$1,"月",""))<=填写页!$A$2,SUM(北京中言:君康经纪!K4),0) -> 0 | L4: =IF(VALUE(SUBSTITUTE(L$1,"月",""))<=填写页!$A$2,SUM(北京中言:君康经纪!L4),0) -> 0 | M4: =IF(VALUE(SUBSTITUTE(M$1,"月",""))<=填写页!$A$2,SUM(北京中言:君康经纪!M4),0) -> 0 | N4: =IF(VALUE(SUBSTITUTE(N$1,"月",""))<=填写页!$A$2,SUM(北京中言:君康经纪!N4),0) -> 0 | ... R4: =IF(VALUE(SUBSTITUTE(R$1,"月",""))<=填写页!$A$2,SUM(北京中言:君康经纪!R4),0) -> 0 | S4: =IFERROR(E4/T4-1,) -> -0.19765556 | T4: =SUM(INDEX(总指标历史分期!$F4:$Q4,1,1):INDEX(总指标历史分期!$F4:$Q4,1,MATCH(填写页!$A$1,总指标历史分期!$F$1:$Q$1,0))) -> 3197.2979
A5: 财务指标 | B5: 4 | C5: 经营支出小计 | D5: =SUM(北京中言:君康经纪!D5) -> 11893.252 | E5: =SUM(北京中言:君康经纪!E5) -> 1956.3181 | F5: =IFERROR(MAX(1+(E5-D5)/ABS(D5),0),) -> 0.16448975 | G5: =IF(VALUE(SUBSTITUTE(G$1,"月",""))<=填写页!$A$2,SUM(北京中言:君康经纪!G5),0) -> 693.53794 | H5: =IF(VALUE(SUBSTITUTE(H$1,"月",""))<=填写页!$A$2,SUM(北京中言:君康经纪!H5),0) -> 618.83413 | I5: =IF(VALUE(SUBSTITUTE(I$1,"月",""))<=填写页!$A$2,SUM(北京中言:君康经纪!I5),0) -> 643.94602 | J5: =IF(VALUE(SUBSTITUTE(J$1,"月",""))<=填写页!$A$2,SUM(北京中言:君康经纪!J5),0) -> 0 | K5: =IF(VALUE(SUBSTITUTE(K$1,"月",""))<=填写页!$A$2,SUM(北京中言:君康经纪!K5),0) -> 0 | L5: =IF(VALUE(SUBSTITUTE(L$1,"月",""))<=填写页!$A$2,SUM(北京中言:君康经纪!L5),0) -> 0 | M5: =IF(VALUE(SUBSTITUTE(M$1,"月",""))<=填写页!$A$2,SUM(北京中言:君康经纪!M5),0) -> 0 | N5: =IF(VALUE(SUBSTITUTE(N$1,"月",""))<=填写页!$A$2,SUM(北京中言:君康经纪!N5),0) -> 0 | ... R5: =IF(VALUE(SUBSTITUTE(R$1,"月",""))<=填写页!$A$2,SUM(北京中言:君康经纪!R5),0) -> 0 | S5: =IFERROR(E5/T5-1,) -> -0.34566813 | T5: =SUM(INDEX(总指标历史分期!$F5:$Q5,1,1):INDEX(总指标历史分期!$F5:$Q5,1,MATCH(填写页!$A$1,总指标历史分期!$F$1:$Q$1,0))) -> 2989.7949
B6: 4.1 | C6: 固定费用 | D6: =SUM(北京中言:君康经纪!D6) -> 6663.4234 | E6: =SUM(北京中言:君康经纪!E6) -> 1242.6731 | F6: =IFERROR(MAX(1+(E6-D6)/ABS(D6),0),) -> 0.18649169 | G6: =IF(VALUE(SUBSTITUTE(G$1,"月",""))<=填写页!$A$2,SUM(北京中言:君康经纪!G6),0) -> 435.90698 | H6: =IF(VALUE(SUBSTITUTE(H$1,"月",""))<=填写页!$A$2,SUM(北京中言:君康经纪!H6),0) -> 408.36292 | I6: =IF(VALUE(SUBSTITUTE(I$1,"月",""))<=填写页!$A$2,SUM(北京中言:君康经纪!I6),0) -> 398.40323 | J6: =IF(VALUE(SUBSTITUTE(J$1,"月",""))<=填写页!$A$2,SUM(北京中言:君康经纪!J6),0) -> 0 | K6: =IF(VALUE(SUBSTITUTE(K$1,"月",""))<=填写页!$A$2,SUM(北京中言:君康经纪!K6),0) -> 0 | L6: =IF(VALUE(SUBSTITUTE(L$1,"月",""))<=填写页!$A$2,SUM(北京中言:君康经纪!L6),0) -> 0 | M6: =IF(VALUE(SUBSTITUTE(M$1,"月",""))<=填写页!$A$2,SUM(北京中言:君康经纪!M6),0) -> 0 | N6: =IF(VALUE(SUBSTITUTE(N$1,"月",""))<=填写页!$A$2,SUM(北京中言:君康经纪!N6),0) -> 0 | ... R6: =IF(VALUE(SUBSTITUTE(R$1,"月",""))<=填写页!$A$2,SUM(北京中言:君康经纪!R6),0) -> 0
B7: 4.1.1 | C7: 人力费用 | D7: =SUM(北京中言:君康经纪!D7) -> 4472.174 | E7: =SUM(北京中言:君康经纪!E7) -> 1059.0341 | F7: =IFERROR(MAX(1+(E7-D7)/ABS(D7),0),) -> 0.23680521 | G7: =IF(VALUE(SUBSTITUTE(G$1,"月",""))<=填写页!$A$2,SUM(北京中言:君康经纪!G7),0) -> 368.59725 | H7: =IF(VALUE(SUBSTITUTE(H$1,"月",""))<=填写页!$A$2,SUM(北京中言:君康经纪!H7),0) -> 355.16541 | I7: =IF(VALUE(SUBSTITUTE(I$1,"月",""))<=填写页!$A$2,SUM(北京中言:君康经纪!I7),0) -> 335.27146 | J7: =IF(VALUE(SUBSTITUTE(J$1,"月",""))<=填写页!$A$2,SUM(北京中言:君康经纪!J7),0) -> 0 | K7: =IF(VALUE(SUBSTITUTE(K$1,"月",""))<=填写页!$A$2,SUM(北京中言:君康经纪!K7),0) -> 0 | L7: =IF(VALUE(SUBSTITUTE(L$1,"月",""))<=填写页!$A$2,SUM(北京中言:君康经纪!L7),0) -> 0 | M7: =IF(VALUE(SUBSTITUTE(M$1,"月",""))<=填写页!$A$2,SUM(北京中言:君康经纪!M7),0) -> 0 | N7: =IF(VALUE(SUBSTITUTE(N$1,"月",""))<=填写页!$A$2,SUM(北京中言:君康经纪!N7),0) -> 0 | ... R7: =IF(VALUE(SUBSTITUTE(R$1,"月",""))<=填写页!$A$2,SUM(北京中言:君康经纪!R7),0) -> 0
B8: 4.1.2 | C8: 日常费用 | D8: =SUM(北京中言:君康经纪!D8) -> 2191.2494 | E8: =SUM(北京中言:君康经纪!E8) -> 183.739 | F8: =IFERROR(MAX(1+(E8-D8)/ABS(D8),0),) -> 0.08385125 | G8: =IF(VALUE(SUBSTITUTE(G$1,"月",""))<=填写页!$A$2,SUM(北京中言:君康经纪!G8),0) -> 67.409728 | H8: =IF(VALUE(SUBSTITUTE(H$1,"月",""))<=填写页!$A$2,SUM(北京中言:君康经纪!H8),0) -> 53.197509 | I8: =IF(VALUE(SUBSTITUTE(I$1,"月",""))<=填写页!$A$2,SUM(北京中言:君康经纪!I8),0) -> 63.131765 | J8: =IF(VALUE(SUBSTITUTE(J$1,"月",""))<=填写页!$A$2,SUM(北京中言:君康经纪!J8),0) -> 0 | K8: =IF(VALUE(SUBSTITUTE(K$1,"月",""))<=填写页!$A$2,SUM(北京中言:君康经纪!K8),0) -> 0 | L8: =IF(VALUE(SUBSTITUTE(L$1,"月",""))<=填写页!$A$2,SUM(北京中言:君康经纪!L8),0) -> 0 | M8: =IF(VALUE(SUBSTITUTE(M$1,"月",""))<=填写页!$A$2,SUM(北京中言:君康经纪!M8),0) -> 0 | N8: =IF(VALUE(SUBSTITUTE(N$1,"月",""))<=填写页!$A$2,SUM(北京中言:君康经纪!N8),0) -> 0 | ... R8: =IF(VALUE(SUBSTITUTE(R$1,"月",""))<=填写页!$A$2,SUM(北京中言:君康经纪!R8),0) -> 0
B9: 4.2 | C9: 变动费用 | D9: =SUM(北京中言:君康经纪!D9) -> 5229.8288 | E9: =SUM(北京中言:君康经纪!E9) -> 713.64496 | F9: =IFERROR(MAX(1+(E9-D9)/ABS(D9),0),) -> 0.13645666 | G9: =IF(VALUE(SUBSTITUTE(G$1,"月",""))<=填写页!$A$2,SUM(北京中言:君康经纪!G9),0) -> 257.63097 | H9: =IF(VALUE(SUBSTITUTE(H$1,"月",""))<=填写页!$A$2,SUM(北京中言:君康经纪!H9),0) -> 210.47121 | I9: =IF(VALUE(SUBSTITUTE(I$1,"月",""))<=填写页!$A$2,SUM(北京中言:君康经纪!I9),0) -> 245.54279 | J9: =IF(VALUE(SUBSTITUTE(J$1,"月",""))<=填写页!$A$2,SUM(北京中言:君康经纪!J9),0) -> 0 | K9: =IF(VALUE(SUBSTITUTE(K$1,"月",""))<=填写页!$A$2,SUM(北京中言:君康经纪!K9),0) -> 0 | L9: =IF(VALUE(SUBSTITUTE(L$1,"月",""))<=填写页!$A$2,SUM(北京中言:君康经纪!L9),0) -> 0 | M9: =IF(VALUE(SUBSTITUTE(M$1,"月",""))<=填写页!$A$2,SUM(北京中言:君康经纪!M9),0) -> 0 | N9: =IF(VALUE(SUBSTITUTE(N$1,"月",""))<=填写页!$A$2,SUM(北京中言:君康经纪!N9),0) -> 0 | ... R9: =IF(VALUE(SUBSTITUTE(R$1,"月",""))<=填写页!$A$2,SUM(北京中言:君康经纪!R9),0) -> 0
B10: 4.2.1 | C10: 经营变动费用 | D10: =SUM(北京中言:君康经纪!D10) -> 2989.9257 | E10: =SUM(北京中言:君康经纪!E10) -> 325.83967 | F10: =IFERROR(MAX(1+(E10-D10)/ABS(D10),0),) -> 0.10897918 | G10: =IF(VALUE(SUBSTITUTE(G$1,"月",""))<=填写页!$A$2,SUM(北京中言:君康经纪!G10),0) -> 97.129076 | H10: =IF(VALUE(SUBSTITUTE(H$1,"月",""))<=填写页!$A$2,SUM(北京中言:君康经纪!H10),0) -> 83.805597 | I10: =IF(VALUE(SUBSTITUTE(I$1,"月",""))<=填写页!$A$2,SUM(北京中言:君康经纪!I10),0) -> 144.905 | J10: =IF(VALUE(SUBSTITUTE(J$1,"月",""))<=填写页!$A$2,SUM(北京中言:君康经纪!J10),0) -> 0 | K10: =IF(VALUE(SUBSTITUTE(K$1,"月",""))<=填写页!$A$2,SUM(北京中言:君康经纪!K10),0) -> 0 | L10: =IF(VALUE(SUBSTITUTE(L$1,"月",""))<=填写页!$A$2,SUM(北京中言:君康经纪!L10),0) -> 0 | M10: =IF(VALUE(SUBSTITUTE(M$1,"月",""))<=填写页!$A$2,SUM(北京中言:君康经纪!M10),0) -> 0 | N10: =IF(VALUE(SUBSTITUTE(N$1,"月",""))<=填写页!$A$2,SUM(北京中言:君康经纪!N10),0) -> 0 | ... R10: =IF(VALUE(SUBSTITUTE(R$1,"月",""))<=填写页!$A$2,SUM(北京中言:君康经纪!R10),0) -> 0
B11: 4.2.2 | C11: 营业成本 | D11: =SUM(北京中言:君康经纪!D11) -> 2239.9031 | E11: =SUM(北京中言:君康经纪!E11) -> 387.8053 | F11: =IFERROR(MAX(1+(E11-D11)/ABS(D11),0),) -> 0.17313485 | G11: =IF(VALUE(SUBSTITUTE(G$1,"月",""))<=填写页!$A$2,SUM(北京中言:君康经纪!G11),0) -> 160.50189 | H11: =IF(VALUE(SUBSTITUTE(H$1,"月",""))<=填写页!$A$2,SUM(北京中言:君康经纪!H11),0) -> 126.66561 | I11: =IF(VALUE(SUBSTITUTE(I$1,"月",""))<=填写页!$A$2,SUM(北京中言:君康经纪!I11),0) -> 100.6378 | J11: =IF(VALUE(SUBSTITUTE(J$1,"月",""))<=填写页!$A$2,SUM(北京中言:君康经纪!J11),0) -> 0 | K11: =IF(VALUE(SUBSTITUTE(K$1,"月",""))<=填写页!$A$2,SUM(北京中言:君康经纪!K11),0) -> 0 | L11: =IF(VALUE(SUBSTITUTE(L$1,"月",""))<=填写页!$A$2,SUM(北京中言:君康经纪!L11),0) -> 0 | M11: =IF(VALUE(SUBSTITUTE(M$1,"月",""))<=填写页!$A$2,SUM(北京中言:君康经纪!M11),0) -> 0 | N11: =IF(VALUE(SUBSTITUTE(N$1,"月",""))<=填写页!$A$2,SUM(北京中言:君康经纪!N11),0) -> 0 | ... R11: =IF(VALUE(SUBSTITUTE(R$1,"月",""))<=填写页!$A$2,SUM(北京中言:君康经纪!R11),0) -> 0
B12: 5 | C12: 资本性支出 | D12: =SUM(北京中言:君康经纪!D12) -> 1648.888 | E12: =SUM(北京中言:君康经纪!E12) -> 10.135942 | F12: =IFERROR(MAX(1+(E12-D12)/ABS(D12),0),) -> 0.0061471379 | G12: =IF(VALUE(SUBSTITUTE(G$1,"月",""))<=填写页!$A$2,SUM(北京中言:君康经纪!G12),0) -> 4.72 | H12: =IF(VALUE(SUBSTITUTE(H$1,"月",""))<=填写页!$A$2,SUM(北京中言:君康经纪!H12),0) -> 3.48 | I12: =IF(VALUE(SUBSTITUTE(I$1,"月",""))<=填写页!$A$2,SUM(北京中言:君康经纪!I12),0) -> 1.935942 | J12: =IF(VALUE(SUBSTITUTE(J$1,"月",""))<=填写页!$A$2,SUM(北京中言:君康经纪!J12),0) -> 0 | K12: =IF(VALUE(SUBSTITUTE(K$1,"月",""))<=填写页!$A$2,SUM(北京中言:君康经纪!K12),0) -> 0 | L12: =IF(VALUE(SUBSTITUTE(L$1,"月",""))<=填写页!$A$2,SUM(北京中言:君康经纪!L12),0) -> 0 | M12: =IF(VALUE(SUBSTITUTE(M$1,"月",""))<=填写页!$A$2,SUM(北京中言:君康经纪!M12),0) -> 0 | N12: =IF(VALUE(SUBSTITUTE(N$1,"月",""))<=填写页!$A$2,SUM(北京中言:君康经纪!N12),0) -> 0 | ... R12: =IF(VALUE(SUBSTITUTE(R$1,"月",""))<=填写页!$A$2,SUM(北京中言:君康经纪!R12),0) -> 0

Sheet 营收
A1: 序号 | B1: 公司 | C1: 当月达成 | D1: 累计达成 | E1: 当月计划 | F1: 累计计划 | G1: 年度计划 | H1: 当月达成率 | I1: 累计达成率 | J1: 年度达成率 | K1: 上年同期累计 | L1: 同比变化 | M1: 上月达成 | N1: 环比变化 | O1: 公司 | P1: 同比数值 | Q1: 同比比率
A2: 1 | B2: 北京中言 | C2: {=INDEX(INDIRECT("'"&$B2&"'!$G$2:$R$2"),0,MATCH(填写页!$A$1,INDIRECT("'"&$B2&"'!$G$1:$R$1"),0))} -> 0 | D2: {=INDIRECT("'"&$B2&"'!$E$2")} -> 2295.837 | E2: {=INDEX(分解计划!C2:N2,0,MATCH(填写页!$A$1,分解计划!$C$1:$N$1,0))} -> 674.14 | F2: =SUM(分解计划!$C2:INDEX(分解计划!C2:N2,0,MATCH(填写页!$A$1,分解计划!$C$1:$N$1,0))) -> 2775.35 | G2: {=INDIRECT("'"&$B2&"'!$D$2")} -> 8093.1731 | H2: =IFERROR(C2/E2,) -> 0 | I2: =IFERROR(D2/F2,) -> 0.82722432 | J2: =IFERROR(D2/G2,) -> 0.28367576 | K2: =SUM(营收历史分体分期!$C2:INDEX(营收历史分体分期!$C2:$M2,0,MATCH(填写页!$A$1,营收历史分体分期!$C$1:$M$1,0))) -> 2832.7312 | L2: =IFERROR(D2/K2-1,0) -> -0.18953234 | M2: 955.27239 | N2: =IFERROR($C2/$M2-1,) -> -1 | O2: 北京中言 | P2: =D2-K2 -> -536.89416 | Q2: =P2/K2 -> -0.18953234 | S2: `=INDEX(INDIRECT("'"&$B2&"'!$G$2:$R$2"),0,MATCH(填写页!$A$1,INDIRECT("'"&$B2&"'!$G$1:$R$1"))-1)
A3: 2 | B3: 大连凯丹 | C3: {=INDEX(INDIRECT("'"&$B3&"'!$G$2:$R$2"),0,MATCH(填写页!$A$1,INDIRECT("'"&$B3&"'!$G$1:$R$1"),0))} -> 0 | D3: {=INDIRECT("'"&$B3&"'!$E$2")} -> 157.69 | E3: {=INDEX(分解计划!C3:N3,0,MATCH(填写页!$A$1,分解计划!$C$1:$N$1,0))} -> 53.066638 | F3: =SUM(分解计划!$C3:INDEX(分解计划!C3:N3,0,MATCH(填写页!$A$1,分解计划!$C$1:$N$1,0))) -> 209.31289 | G3: {=INDIRECT("'"&$B3&"'!$D$2")} -> 620.83163 | H3: =IFERROR(C3/E3,) -> 0 | I3: =IFERROR(D3/F3,) -> 0.75336976 | J3: =IFERROR(D3/G3,) -> 0.25399801 | K3: =SUM(营收历史分体分期!$C3:INDEX(营收历史分体分期!$C3:$M3,0,MATCH(填写页!$A$1,营收历史分体分期!$C$1:$M$1,0))) -> 253.16 | L3: =IFERROR(D3/K3-1,0) -> -0.37711329 | M3: 72.93 | N3: =IFERROR($C3/$M3-1,) -> -1 | O3: 大连凯丹 | P3: =D3-K3 -> -95.47 | Q3: =P3/K3 -> -0.37711329
A4: 3 | B4: 福建钱隆 | C4: {=INDEX(INDIRECT("'"&$B4&"'!$G$2:$R$2"),0,MATCH(填写页!$A$1,INDIRECT("'"&$B4&"'!$G$1:$R$1"),0))} -> 0 | D4: {=INDIRECT("'"&$B4&"'!$E$2")} -> 1569.4094 | E4: {=INDEX(分解计划!C4:N4,0,MATCH(填写页!$A$1,分解计划!$C$1:$N$1,0))} -> 522.17 | F4: =SUM(分解计划!$C4:INDEX(分解计划!C4:N4,0,MATCH(填写页!$A$1,分解计划!$C$1:$N$1,0))) -> 2066.95 | G4: {=INDIRECT("'"&$B4&"'!$D$2")} -> 6392.8 | H4: =IFERROR(C4/E4,) -> 0 | I4: =IFERROR(D4/F4,) -> 0.75928755 | J4: =IFERROR(D4/G4,) -> 0.2454964 | K4: =SUM(营收历史分体分期!$C4:INDEX(营收历史分体分期!$C4:$M4,0,MATCH(填写页!$A$1,营收历史分体分期!$C$1:$M$1,0))) -> 2291.3766 | L4: =IFERROR(D4/K4-1,0) -> -0.31508012 | M4: 561.60721 | N4: =IFERROR($C4/$M4-1,) -> -1 | O4: 福建钱隆 | P4: =D4-K4 -> -721.9672 | Q4: =P4/K4 -> -0.31508012
A5: 4 | B5: 春夏秋冬 | C5: {=INDEX(INDIRECT("'"&$B5&"'!$G$2:$R$2"),0,MATCH(填写页!$A$1,INDIRECT("'"&$B5&"'!$G$1:$R$1"),0))} -> 0 | D5: {=INDIRECT("'"&$B5&"'!$E$2")} -> 310.7 | E5: {=INDEX(分解计划!C5:N5,0,MATCH(填写页!$A$1,分解计划!$C$1:$N$1,0))} -> 121.31143 | F5: =SUM(分解计划!$C5:INDEX(分解计划!C5:N5,0,MATCH(填写页!$A$1,分解计划!$C$1:$N$1,0))) -> 457.02571 | G5: {=INDIRECT("'"&$B5&"'!$D$2")} -> 1494.8762 | H5: =IFERROR(C5/E5,) -> 0 | I5: =IFERROR(D5/F5,) -> 0.67983046 | J5: =IFERROR(D5/G5,) -> 0.2078433 | K5: =SUM(营收历史分体分期!$C5:INDEX(营收历史分体分期!$C5:$M5,0,MATCH(填写页!$A$1,营收历史分体分期!$C$1:$M$1,0))) -> 466.29 | L5: =IFERROR(D5/K5-1,0) -> -0.33367647 | M5: 109.64 | N5: =IFERROR($C5/$M5-1,) -> -1 | O5: 春夏秋冬 | P5: =D5-K5 -> -155.59 | Q5: =P5/K5 -> -0.33367647
A6: 5 | B6: 重庆宜新 | C6: {=INDEX(INDIRECT("'"&$B6&"'!$G$2:$R$2"),0,MATCH(填写页!$A$1,INDIRECT("'"&$B6&"'!$G$1:$R$1"),0))} -> 0 | D6: {=INDIRECT("'"&$B6&"'!$E$2")} -> 130.57764 | E6: {=INDEX(分解计划!C6:N6,0,MATCH(填写页!$A$1,分解计划!$C$1:$N$1,0))} -> 47.091121 | F6: =SUM(分解计划!$C6:INDEX(分解计划!C6:N6,0,MATCH(填写页!$A$1,分解计划!$C$1:$N$1,0))) -> 144.27544 | G6: {=INDIRECT("'"&$B6&"'!$D$2")} -> 709.51636 | H6: =IFERROR(C6/E6,) -> 0 | I6: =IFERROR(D6/F6,) -> 0.90505802 | J6: =IFERROR(D6/G6,) -> 0.18403754 | K6: =SUM(营收历史分体分期!$C6:INDEX(营收历史分体分期!$C6:$M6,0,MATCH(填写页!$A$1,营收历史分体分期!$C$1:$M$1,0))) -> 243.41798 | L6: =IFERROR(D6/K6-1,0) -> -0.46356615 | M6: 62.761423 | N6: =IFERROR($C6/$M6-1,) -> -1 | O6: 重庆宜新 | P6: =D6-K6 -> -112.84034 | Q6: =P6/K6 -> -0.46356615
A7: 6 | B7: 伯豪瑞廷 | C7: {=INDEX(INDIRECT("'"&$B7&"'!$G$2:$R$2"),0,MATCH(填写页!$A$1,INDIRECT("'"&$B7&"'!$G$1:$R$1"),0))} -> 0 | D7: {=INDIRECT("'"&$B7&"'!$E$2")} -> 1487.36 | E7: {=INDEX(分解计划!C7:N7,0,MATCH(填写页!$A$1,分解计划!$C$1:$N$1,0))} -> 621.71 | F7: =SUM(分解计划!$C7:INDEX(分解计划!C7:N7,0,MATCH(填写页!$A$1,分解计划!$C$1:$N$1,0))) -> 2318.77 | G7: {=INDIRECT("'"&$B7&"'!$D$2")} -> 7640.86 | H7: =IFERROR(C7/E7,) -> 0 | I7: =IFERROR(D7/F7,) -> 0.64144352 | J7: =IFERROR(D7/G7,) -> 0.19465872 | K7: =SUM(营收历史分体分期!$C7:INDEX(营收历史分体分期!$C7:$M7,0,MATCH(填写页!$A$1,营收历史分体分期!$C$1:$M$1,0))) -> 2363.57 | L7: =IFERROR(D7/K7-1,0) -> -0.37071464 | M7: 554.4 | N7: =IFERROR($C7/$M7-1,) -> -1 | O7: 伯豪瑞廷 | P7: =D7-K7 -> -876.21 | Q7: =P7/K7 -> -0.37071464
A8: 7 | B8: 重庆瑞尔 | C8: {=INDEX(INDIRECT("'"&$B8&"'!$G$2:$R$2"),0,MATCH(填写页!$A$1,INDIRECT("'"&$B8&"'!$G$1:$R$1"),0))} -> 0 | D8: {=INDIRECT("'"&$B8&"'!$E$2")} -> 223.36091 | E8: {=INDEX(分解计划!C8:N8,0,MATCH(填写页!$A$1,分解计划!$C$1:$N$1,0))} -> 112.08082 | F8: =SUM(分解计划!$C8:INDEX(分解计划!C8:N8,0,MATCH(填写页!$A$1,分解计划!$C$1:$N$1,0))) -> 392.87423 | G8: {=INDIRECT("'"&$B8&"'!$D$2")} -> 1454.9973 | H8: =IFERROR(C8/E8,) -> 0 | I8: =IFERROR(D8/F8,) -> 0.56853033 | J8: =IFERROR(D8/G8,) -> 0.15351294 | K8: =SUM(营收历史分体分期!$C8:INDEX(营收历史分体分期!$C8:$M8,0,MATCH(填写页!$A$1,营收历史分体分期!$C$1:$M$1,0))) -> 403.82549 | L8: =IFERROR(D8/K8-1,0) -> -0.44688753 | M8: 83.825761 | N8: =IFERROR($C8/$M8-1,) -> -1 | O8: 重庆瑞尔 | P8: =D8-K8 -> -180.46457 | Q8: =P8/K8 -> -0.44688753
A9: 8 | B9: 盛唐融信 | C9: {=INDEX(INDIRECT("'"&$B9&"'!$G$2:$R$2"),0,MATCH(填写页!$A$1,INDIRECT("'"&$B9&"'!$G$1:$R$1"),0))} -> 0 | D9: {=INDIRECT("'"&$B9&"'!$E$2")} -> 83.977952 | E9: {=INDEX(分解计划!C9:N9,0,MATCH(填写页!$A$1,分解计划!$C$1:$N$1,0))} -> 0 | F9: =SUM(分解计划!$C9:INDEX(分解计划!C9:N9,0,MATCH(填写页!$A$1,分解计划!$C$1:$N$1,0))) -> 0 | G9: {=INDIRECT("'"&$B9&"'!$D$2")} -> 755.36194 | H9: =IFERROR(C9/E9,) -> 0 | I9: =IFERROR(D9/F9,) -> 0 | J9: =IFERROR(D9/G9,) -> 0.11117578 | K9: =SUM(营收历史分体分期!$C9:INDEX(营收历史分体分期!$C9:$M9,0,MATCH(填写页!$A$1,营收历史分体分期!$C$1:$M$1,0))) -> 256.33723 | L9: =IFERROR(D9/K9-1,0) -> -0.67239268 | M9: 44.551139 | N9: =IFERROR($C9/$M9-1,) -> -1 | O9: 盛唐融信 | P9: =D9-K9 -> -172.35927 | Q9: =P9/K9 -> -0.67239268
A10: 9 | B10: 君康经纪 | C10: {=INDEX(INDIRECT("'"&$B10&"'!$G$2:$R$2"),0,MATCH(填写页!$A$1,INDIRECT("'"&$B10&"'!$G$1:$R$1"),0))} -> 0 | D10: {=INDIRECT("'"&$B10&"'!$E$2")} -> 34.637326 | E10: {=INDEX(分解计划!C10:N10,0,MATCH(填写页!$A$1,分解计划!$C$1:$N$1,0))} -> 0 | F10: =SUM(分解计划!$C10:INDEX(分解计划!C10:N10,0,MATCH(填写页!$A$1,分解计划!$C$1:$N$1,0))) -> 0 | G10: {=INDIRECT("'"&$B10&"'!$D$2")} -> 648.56173 | H10: =IFERROR(C10/E10,) -> 0 | I10: =IFERROR(D10/F10,) -> 0 | J10: =IFERROR(D10/G10,) -> 0.053406367 | K10: =SUM(营收历史分体分期!$C10:INDEX(营收历史分体分期!$C10:$M10,0,MATCH(填写页!$A$1,营收历史分体分期!$C$1:$M$1,0))) -> 87.432863 | L10: =IFERROR(D10/K10-1,0) -> -0.60384088 | M10: 5.843275 | N10: =IFERROR($C10/$M10-1,) -> -1 | O10: 君康经纪 | P10: =D10-K10 -> -52.795537 | Q10: =P10/K10 -> -0.60384088
A11: 合计 | C11: =SUM(C2:C10) -> 0 | D11: =SUM(D2:D10) -> 6293.5502 | E11: =SUM(E2:E10) -> 2151.57 | F11: =SUM(F2:F10) -> 8364.5583 | G11: =SUM(G2:G10) -> 27810.978 | H11: =IFERROR(C11/E11,) -> 0 | I11: =IFERROR(D11/F11,) -> 0.75240677 | J11: =IFERROR(D11/G11,) -> 0.22629733 | K11: =SUM(营收历史分体分期!$C11:INDEX(营收历史分体分期!$C11:$M21,0,MATCH(填写页!$A$1,营收历史分体分期!$C$1:$M$1,0))) -> 9198.1413 | L11: =IFERROR(D11/K11-1,0) -> -0.31578022 | M11: =SUM(M2:M10) -> 2450.8312 | N11: =IFERROR($C11/M11-1,) -> -1
B29: 公司 | C29: 当月计划 | D29: 当月达成 | E29: 当月达成率
B30: 北京中言 | C30: {=E2:E10} -> 674.14 | D30: {=C2:C10} -> 0 | E30: =IFERROR(D30/C30,) -> 0
B31: 大连凯丹 | C31: 53.066638 | D31: 0 | E31: =IFERROR(D31/C31,) -> 0
B32: 福建钱隆 | C32: 522.17 | D32: 0 | E32: =IFERROR(D32/C32,) -> 0
B33: 春夏秋冬 | C33: 121.31143 | D33: 0 | E33: =IFERROR(D33/C33,) -> 0
B34: 重庆宜新 | C34: 47.091121 | D34: 0 | E34: =IFERROR(D34/C34,) -> 0
B35: 伯豪瑞廷 | C35: 621.71 | D35: 0 | E35: =IFERROR(D35/C35,) -> 0
B36: 重庆瑞尔 | C36: 112.08082 | D36: 0 | E36: =IFERROR(D36/C36,) -> 0
B37: 盛唐融信 | C37: 0 | D37: 0 | E37: =IFERROR(D37/C37,) -> 0
B38: 君康经纪 | C38: 0 | D38: 0 | E38: =IFERROR(D38/C38,) -> 0
C39: 当月计划 | D39: 当月达成 | E39: 当月达成率 | F39: 缺口
B40: 合计 | C40: =SUM(C30:C38) -> 2151.57 | D40: =SUM(D30:D38) -> 0 | E40: =IFERROR(D40/C40,) -> 0 | F40: =1-E40 -> 1
B42: 公司 | C42: 分解计划 | D42: 累计达成 | E42: 分解计划达成率
B43: 北京中言 | C43: {=F2:F10} -> 2775.35 | D43: {=D2:D10} -> 2295.837 | E43: =IFERROR(D43/C43,) -> 0.82722432
B44: 大连凯丹 | C44: 209.31289 | D44: 157.69 | E44: =IFERROR(D44/C44,) -> 0.75336976
B45: 福建钱隆 | C45: 2066.95 | D45: 1569.4094 | E45: =IFERROR(D45/C45,) -> 0.75928755
B46: 春夏秋冬 | C46: 457.02571 | D46: 310.7 | E46: =IFERROR(D46/C46,) -> 0.67983046
B47: 重庆宜新 | C47: 144.27544 | D47: 130.57764 | E47: =IFERROR(D47/C47,) -> 0.90505802
B48: 伯豪瑞廷 | C48: 2318.77 | D48: 1487.36 | E48: =IFERROR(D48/C48,) -> 0.64144352
B49: 重庆瑞尔 | C49: 392.87423 | D49: 223.36091 | E49: =IFERROR(D49/C49,) -> 0.56853033
B50: 盛唐融信 | C50: 0 | D50: 83.977952 | E50: =IFERROR(D50/C50,) -> 0
B51: 君康经纪 | C51: 0 | D51: 34.637326 | E51: =IFERROR(D51/C51,) -> 0
C52: 季度计划 | D52: 季度达成 | E52: 分解计划达成率 | F52: 缺口
B53: 合计 | C53: =SUM(C43:C51) -> 8364.5583 | D53: =SUM(D43:D51) -> 6293.5502 | E53: =IFERROR(D53/C53,) -> 0.75240677 | F53: =1-E53 -> 0.24759323
B55: 公司 | C55: 年度计划 | D55: 年度达成 | E55: 年度达成率
B56: 北京中言 | C56: {=G2:G10} -> 8093.1731 | D56: {=D2:D10} -> 2295.837 | E56: =IFERROR(D56/C56,) -> 0.28367576
B57: 大连凯丹 | C57: 620.83163 | D57: 157.69 | E57: =IFERROR(D57/C57,) -> 0.25399801
B58: 福建钱隆 | C58: 6392.8 | D58: 1569.4094 | E58: =IFERROR(D58/C58,) -> 0.2454964
B59: 春夏秋冬 | C59: 1494.8762 | D59: 310.7 | E59: =IFERROR(D59/C59,) -> 0.2078433
B60: 重庆宜新 | C60: 709.51636 | D60: 130.57764 | E60: =IFERROR(D60/C60,) -> 0.18403754
B61: 伯豪瑞廷 | C61: 7640.86 | D61: 1487.36 | E61: =IFERROR(D61/C61,) -> 0.19465872
B62: 重庆瑞尔 | C62: 1454.9973 | D62: 223.36091 | E62: =IFERROR(D62/C62,) -> 0.15351294
B63: 盛唐融信 | C63: 755.36194 | D63: 83.977952 | E63: =IFERROR(D63/C63,) -> 0.11117578
B64: 君康经纪 | C64: 648.56173 | D64: 34.637326 | E64: =IFERROR(D64/C64,) -> 0.053406367
C65: 年度计划 | D65: 年度达成 | E65: 年度达成率 | F65: 缺口
B66: 合计 | C66: =SUM(C56:C64) -> 27810.978 | D66: =SUM(D56:D64) -> 6293.5502 | E66: =IFERROR(D66/C66,) -> 0.22629733 | F66: =1-E66 -> 0.77370267
B69: 指标 | C69: 1月 | D69: 2月 | E69: 3月 | F69: 4月 | G69: 5月 | H69: 6月 | I69: 7月 | J69: 8月 | K69: 9月 | L69: 10月 | M69: 11月 | N69: 12月
B70: 2025营收 | C70: {=营收历史分体分期!B11:N11} -> 28181.139 | D70: 2407.5807 | E70: 2189.195 | F70: 2310.296 | G70: 2291.0697 | H70: 2312.9612 | I70: 2286.3054 | J70: 2408.0989 | K70: 2398.079 | L70: 2344.1448 | M70: 2403.0649 | N70: 2379.5125 | O70: 2450.8312
B71: 2026营收 | C71: {=整体!G2:INDEX(整体!G2:R2,0,MATCH(填写页!$A$1,整体!$G$1:$R$1,0))} -> 2008.2177 | D71: 1773.7489 | E71: 2511.5836 | F71: 0 | G71: #N/A | H71: #N/A | I71: #N/A | J71: #N/A | K71: #N/A
B72: 单月同比 | C72: =IF(COLUMN()-2>MATCH(填写页!$A$1,$C$69:$N$69,0),NA(),IF(C$71<>0,IFERROR((C$71-C$70)/ABS(C$70),NA()),NA())) -> -0.92873895 | D72: =IF(COLUMN()-2>MATCH(填写页!$A$1,$C$69:$N$69,0),NA(),IF(D$71<>0,IFERROR((D$71-D$70)/ABS(D$70),NA()),NA())) -> -0.26326501 | E72: =IF(COLUMN()-2>MATCH(填写页!$A$1,$C$69:$N$69,0),NA(),IF(E$71<>0,IFERROR((E$71-E$70)/ABS(E$70),NA()),NA())) -> 0.14726358 | F72: =IF(COLUMN()-2>MATCH(填写页!$A$1,$C$69:$N$69,0),NA(),IF(F$71<>0,IFERROR((F$71-F$70)/ABS(F$70),NA()),NA())) -> #N/A | G72: =IF(COLUMN()-2>MATCH(填写页!$A$1,$C$69:$N$69,0),NA(),IF(G$71<>0,IFERROR((G$71-G$70)/ABS(G$70),NA()),NA())) -> #N/A | H72: =IF(COLUMN()-2>MATCH(填写页!$A$1,$C$69:$N$69,0),NA(),IF(H$71<>0,IFERROR((H$71-H$70)/ABS(H$70),NA()),NA())) -> #N/A | I72: =IF(COLUMN()-2>MATCH(填写页!$A$1,$C$69:$N$69,0),NA(),IF(I$71<>0,IFERROR((I$71-I$70)/ABS(I$70),NA()),NA())) -> #N/A | J72: =IF(COLUMN()-2>MATCH(填写页!$A$1,$C$69:$N$69,0),NA(),IF(J$71<>0,IFERROR((J$71-J$70)/ABS(J$70),NA()),NA())) -> #N/A | ... N72: =IF(COLUMN()-2>MATCH(填写页!$A$1,$C$69:$N$69,0),NA(),IF(N$71<>0,IFERROR((N$71-N$70)/ABS(N$70),NA()),NA())) -> #N/A
B73: 环比 | D73: =IF(COLUMN()-3>MATCH(填写页!$A$1,$C$69:$N$69,0),NA(),IF(D$71<>0,IFERROR((D$71-C$71)/ABS(C$71),NA()),NA())) -> -0.11675466 | E73: =IF(COLUMN()-3>MATCH(填写页!$A$1,$C$69:$N$69,0),NA(),IF(E$71<>0,IFERROR((E$71-D$71)/ABS(D$71),NA()),NA())) -> 0.41597473 | F73: =IF(COLUMN()-3>MATCH(填写页!$A$1,$C$69:$N$69,0),NA(),IF(F$71<>0,IFERROR((F$71-E$71)/ABS(E$71),NA()),NA())) -> #N/A | G73: =IF(COLUMN()-3>MATCH(填写页!$A$1,$C$69:$N$69,0),NA(),IF(G$71<>0,IFERROR((G$71-F$71)/ABS(F$71),NA()),NA())) -> #N/A | H73: =IF(COLUMN()-3>MATCH(填写页!$A$1,$C$69:$N$69,0),NA(),IF(H$71<>0,IFERROR((H$71-G$71)/ABS(G$71),NA()),NA())) -> #N/A | I73: =IF(COLUMN()-3>MATCH(填写页!$A$1,$C$69:$N$69,0),NA(),IF(I$71<>0,IFERROR((I$71-H$71)/ABS(H$71),NA()),NA())) -> #N/A | J73: =IF(COLUMN()-3>MATCH(填写页!$A$1,$C$69:$N$69,0),NA(),IF(J$71<>0,IFERROR((J$71-I$71)/ABS(I$71),NA()),NA())) -> #N/A | K73: =IF(COLUMN()-3>MATCH(填写页!$A$1,$C$69:$N$69,0),NA(),IF(K$71<>0,IFERROR((K$71-J$71)/ABS(J$71),NA()),NA())) -> #N/A | ... N73: =IF(COLUMN()-3>MATCH(填写页!$A$1,$C$69:$N$69,0),NA(),IF(N$71<>0,IFERROR((N$71-M$71)/ABS(M$71),NA()),NA())) -> #N/A
B95: 上年同期 | C95: 2026年 | D95: 占比 | E95: 同比 | F95: 环比 | G95: 同比水平轴线 | H95: 环比水平轴线
A96: 1月 | B96: 2407.5807 | C96: =整体!G2 -> 2008.2177 | D96: =IF(C96<>0,C96/SUM($C$96:$C$107),NA()) -> 0.31909139 | E96: =IF(C96<>0,C96/B96-1,NA()) -> -0.1658773 | F96: =C96/B107-1 -> -0.1805973 | G96: 0 | H96: 0
A97: 2月 | B97: 2189.195 | C97: =整体!H2 -> 1773.7489 | D97: =IF(C97<>0,C97/SUM($C$96:$C$107),NA()) -> 0.28183598 | E97: =IF(C97<>0,C97/B97-1,NA()) -> -0.18977115 | F97: =IF(C97<>0,C97/C96-1,NA()) -> -0.11675466 | G97: 0 | H97: 0
A98: 3月 | B98: 2310.296 | C98: =整体!I2 -> 2511.5836 | D98: =IF(C98<>0,C98/SUM($C$96:$C$107),NA()) -> 0.39907263 | E98: =IF(C98<>0,C98/B98-1,NA()) -> 0.087126345 | F98: =IF(C98<>0,C98/C97-1,NA()) -> 0.41597473 | G98: 0 | H98: 0
A99: 4月 | B99: 2291.0697 | D99: =IF(C99<>0,C99/SUM($C$96:$C$107),NA()) -> #N/A | E99: =IF(C99<>0,C99/B99-1,NA()) -> #N/A | F99: =IF(C99<>0,C99/C98-1,NA()) -> #N/A | G99: 0 | H99: 0
A100: 5月 | B100: 2312.9612 | D100: =IF(C100<>0,C100/SUM($C$96:$C$107),NA()) -> #N/A | E100: =IF(C100<>0,C100/B100-1,NA()) -> #N/A | F100: =IF(C100<>0,C100/C99-1,NA()) -> #N/A | G100: 0 | H100: 0
A101: 6月 | B101: 2286.3054 | D101: =IF(C101<>0,C101/SUM($C$96:$C$107),NA()) -> #N/A | E101: =IF(C101<>0,C101/B101-1,NA()) -> #N/A | F101: =IF(C101<>0,C101/C100-1,NA()) -> #N/A | G101: 0 | H101: 0
A102: 7月 | B102: 2408.0989 | D102: =IF(C102<>0,C102/SUM($C$96:$C$107),NA()) -> #N/A | E102: =IF(C102<>0,C102/B102-1,NA()) -> #N/A | F102: =IF(C102<>0,C102/C101-1,NA()) -> #N/A | G102: 0 | H102: 0
A103: 8月 | B103: 2398.079 | D103: =IF(C103<>0,C103/SUM($C$96:$C$107),NA()) -> #N/A | E103: =IF(C103<>0,C103/B103-1,NA()) -> #N/A | F103: =IF(C103<>0,C103/C102-1,NA()) -> #N/A | G103: 0 | H103: 0
A104: 9月 | B104: 2344.1448 | D104: =IF(C104<>0,C104/SUM($C$96:$C$107),NA()) -> #N/A | E104: =IF(C104<>0,C104/B104-1,NA()) -> #N/A | F104: =IF(C104<>0,C104/C103-1,NA()) -> #N/A | G104: 0 | H104: 0
A105: 10月 | B105: 2403.0649 | D105: =IF(C105<>0,C105/SUM($C$96:$C$107),NA()) -> #N/A | E105: =IF(C105<>0,C105/B105-1,NA()) -> #N/A | F105: =IF(C105<>0,C105/C104-1,NA()) -> #N/A | G105: 0 | H105: 0
A106: 11月 | B106: 2379.5125 | D106: =IF(C106<>0,C106/SUM($C$96:$C$107),NA()) -> #N/A | E106: =IF(C106<>0,C106/B106-1,NA()) -> #N/A | F106: =IF(C106<>0,C106/C105-1,NA()) -> #N/A | G106: 0 | H106: 0
A107: 12月 | B107: 2450.8312 | D107: =IF(C107<>0,C107/SUM($C$96:$C$107),NA()) -> #N/A | E107: =IF(C107<>0,C107/B107-1,NA()) -> #N/A | F107: =IF(C107<>0,C107/C106-1,NA()) -> #N/A | G107: 0 | H107: 0

Sheet 商写类
A1: 类别 | B1: 项目 | C1: 北京中言 | D1: 大连凯丹 | E1: 福建钱隆 | F1: 春夏秋冬 | G1: 重庆宜新
A2: 整体情况 | B2: 期初面积 | C2: 47507.63 | D2: 13442.88 | E2: 57874.95 | F2: 31299.98 | G2: 39201.19
A3: 整体情况 | B3: 新增签约面积 | C3: 4588.16 | D3: 529.12 | E3: 3104.76 | F3: 2235.04 | G3: 302.1
A4: 整体情况 | B4: 平均租金 | C4: 0 | D4: 0 | E4: 0 | F4: 0 | G4: 0
A5: 整体情况 | B5: 本期退租面积 | C5: 3738.07 | D5: 218.59 | E5: 1178.17 | F5: 366.45 | G5: 1467.83
A6: 整体情况 | B6: 月末面积 | C6: 49589.16 | D6: 13753.41 | E6: 59801.54 | F6: 33168.57 | G6: 38035.46
A7: 合作渠道 | B7: 渠道带客 | C7: 61 | D7: 54 | E7: 21 | F7: 12 | G7: 7
A8: 合作渠道 | B8: 渠道成交 | C8: 2 | D8: 5 | E8: 1 | F8: 3 | G8: 0
A9: 合作渠道 | B9: 渠道签约面积 | C9: 2672.44 | D9: 529.12 | E9: 1436.22 | F9: 1507.2 | G9: 0
A10: 合作渠道 | B10: 成交周期 | C10: 0 | D10: 0 | E10: 0 | F10: 0 | G10: 0
A11: 合作渠道 | B11: 转化率 | C11: ==C8/C7 | D11: ==D8/D7 | E11: ==E8/E7 | F11: ==F8/F7 | G11: ==G8/G7
A12: 自有招商 | B12: 自营带客 | C12: 4 | D12: 0 | E12: 7 | F12: 11 | G12: 6
A13: 自有招商 | B13: 自营成交 | C13: 1 | D13: 0 | E13: 0 | F13: 2 | G13: 4
A14: 自有招商 | B14: 自营签约面积 | C14: 1000 | D14: 0 | E14: 0 | F14: 727.84 | G14: 302.1
A15: 自有招商 | B15: 成交周期 | C15: 0 | D15: 0 | E15: 0 | F15: 0 | G15: 0
A16: 自有招商 | B16: 转化率 | C16: ==C13/C12 | D16: ==D13/D12 | E16: ==E13/E12 | F16: ==F13/F12 | G16: ==G13/G12
A17: 续租情况 | B17: 到期面积 | C17: 0 | D17: 218.38 | E17: 7733.49 | F17: 405.07 | G17: 825.82
A18: 续租情况 | B18: 续签面积 | C18: 0 | D18: 57.66 | E18: 7249.51 | F18: 338.87 | G18: 675.7
B19: 最新出租率
B20: 续签率 | C20: =C18/C17 | D20: =D18/D17 | E20: =E18/E17 | F20: =F18/F17 | G20: =G18/G17

Sheet 酒店类
A1: 类别 | B1: 项目 | C1: 伯豪瑞廷 | D1: 重庆瑞尔 | E1: OTA网络评价 | F1: 伯豪瑞廷 | G1: 重庆瑞尔 | I1: 月均入住率 | J1: 伯豪瑞廷 | K1: 重庆瑞尔
A2: 营销活动 | B2: 投放数量 | C2: 4883 | D2: 1904 | E2: 1月 | F2: 4.68 | G2: 4.7 | I2: 1月 | J2: 0.6527 | K2: 0.41286389
A3: 营销活动 | B3: 受众数量 | C3: 35768 | D3: 60000 | E3: 2月 | F3: 4.67 | G3: 4.7 | I3: 2月 | J3: 0.5493 | K3: 0.31946864
A4: 营销活动 | B4: 成交数量 | C4: 8494 | D4: 2 | E4: 3月 | F4: 4.69 | G4: 4.7 | I4: 3月 | J4: 0.7096 | K4: 0.59343037
A5: 营销活动 | B5: 转化率 | C5: ==C4/C3 | D5: ==D4/D3 | E5: 4月 | F5: 4.67 | G5: 4.7 | I5: 4月 | J5: 0.877 | K5: 0.74512195
E6: 5月 | F6: =NA() | G6: =NA() | I6: 5月 | J6: =NA() | K6: =NA()
E7: 6月 | F7: =NA() | G7: =NA() | I7: 6月 | J7: =NA() | K7: =NA()
E8: 7月 | F8: =NA() | G8: =NA() | I8: 7月 | J8: =NA() | K8: =NA()
E9: 8月 | F9: =NA() | G9: =NA() | I9: 8月 | J9: =NA() | K9: =NA()
E10: 9月 | F10: =NA() | G10: =NA() | I10: 9月 | J10: =NA() | K10: =NA()
E11: 10月 | F11: =NA() | G11: =NA() | I11: 10月 | J11: =NA() | K11: =NA()
E12: 11月 | F12: =NA() | G12: =NA() | I12: 11月 | J12: =NA() | K12: =NA()
E13: 12月 | F13: =NA() | G13: =NA() | I13: 12月 | J13: =NA() | K13: =NA()

Sheet 保险类
A1: 类别 | B1: 项目 | C1: 盛唐融信 | D1: 君康经纪 | F1: 项目 | G1: 盛唐融信 | H1: 君康经纪
A2: 人力 | B2: 期初人力 | C2: 97 | D2: 35 | F2: 月末人力 | G2: =C6 | H2: =D6
B3: 当月入职 | C3: 2 | D3: 0 | F3: 开单人数 | G3: =C8 | H3: =D8
B4: 当月离职 | C4: 2 | D4: 0 | F4: 活动率 | G4: =C9 | H4: =D9
B5: 当月净增 | C5: 0 | D5: 0
B6: 月末人力 | C6: 97 | D6: 35 | F6: 项目 | G6: 盛唐融信 | H6: 君康经纪
B7: 平均人力 | C7: 96.75 | D7: 35 | F7: 承保新单规模保费 | G7: =C10 | H7: =D10
B8: 开单人数 | C8: 2 | D8: 6 | F8: 承保件数 | G8: =C16 | H8: =D16
B9: 活动率 | C9: ==C8/C7 | D9: ==D8/D7 | F9: 件均保费 | G9: =C17 | H9: =D17
A10: 产能 | B10: 承保新单规模保费 | C10: 7.3247 | D10: 102.05 | F10: 人均保费 | G10: =C18 | H10: =D18
B11: 承保期交规模保费 | C11: 7 | D11: 102.05
B12: 应收13月续期保费 | C12: 0 | D12: 7 | F12: 规模保费 | G12: 盛唐融信 | H12: 君康经纪
B13: 实收13月续期保费 | C13: 0 | D13: 7 | F13: 1月 | G13: 7.1105 | H13: 100
B14: 应收25月续期保费 | C14: 0 | D14: 36.1 | F14: 2月 | G14: 0 | H14: 0.51
B15: 实收25月续期保费 | C15: 0 | D15: 36.1 | F15: 3月 | G15: 0.2142 | H15: 1.34
B16: 承保件数 | C16: 8 | D16: 44 | F16: 4月 | G16: 0 | H16: 0.2
B17: 件均保费 | C17: ==C10/C16 | D17: ==D10/D16 | F17: 5月 | G17: =NA() | H17: =NA()
B18: 人均保费 | C18: ==C10/C6 | D18: ==D10/D6 | F18: 6月 | G18: =NA() | H18: =NA()
F19: 7月 | G19: =NA() | H19: =NA()
F20: 8月 | G20: =NA() | H20: =NA()
F21: 9月 | G21: =NA() | H21: =NA()
F22: 10月 | G22: =NA() | H22: =NA()
F23: 11月 | G23: =NA() | H23: =NA()
F24: 12月 | G24: =NA() | H24: =NA()

Sheet 北京中言
A1: 类别 | B1: 序号 | C1: 指标 | D1: 年度目标 | E1: 实际达成 | F1: 年度目标达成率 | G1: 1月 | H1: 2月 | I1: 3月 | J1: 4月 | K1: 5月 | L1: 6月 | M1: 7月 | N1: 8月 | O1: 9月 | P1: 10月 | Q1: 11月 | R1: 12月
A2: 经营指标 | B2: 1 | C2: 营业收入 | D2: {=INDEX(年度计划!E2:M18,,MATCH(填写页!C2,年度计划!E1:M1,0))} | E2: =SUM(G2:R2) | F2: =IFERROR(MAX(1+(E2-D2)/ABS(D2),0),) | G2: 580.60931 | H2: 567.20524 | I2: 1148.0225 | J2: 769.80497 | K2: 0 | L2: 0 | M2: 0 | N2: 0 | O2: 0 | P2: 0 | Q2: 0 | R2: 0
B3: 2 | C3: EBITDA | D3: 3056.2075 | E3: =SUM(G3:R3) | F3: =IFERROR(MAX(1+(E3-D3)/ABS(D3),0),) | G3: 309.20647 | H3: 296.73437 | I3: 885.00292 | J3: 493.44928
B4: 3 | C4: 经营活动净现金流 | D4: 112.83542 | E4: =SUM(G4:R4) | F4: =IFERROR(MAX(1+(E4-D4)/ABS(D4),0),) | G4: 85.643994 | H4: 883.277 | I4: -715.53544 | J4: 2348.8622
A5: 财务指标 | B5: 4 | C5: 经营支出 | D5: 2263.9656 | E5: =SUM(G5:R5) | F5: =IFERROR(MAX(1+(E5-D5)/ABS(D5),0),) | G5: 46.856168 | H5: 43.40538 | I5: 50.429416 | J5: 56.655602 | K5: 0 | L5: 0 | M5: 0 | N5: 0 | O5: 0 | P5: 0 | Q5: 0 | R5: 0
B6: 4.1 | C6: 固定费用 | D6: 637.27558 | E6: =SUM(G6:R6) | F6: =IFERROR(MAX(1+(E6-D6)/ABS(D6),0),) | G6: 32.585219 | H6: 39.025355 | I6: 37.531035 | J6: 37.76773 | K6: 0 | L6: 0 | M6: 0 | N6: 0 | O6: 0 | P6: 0 | Q6: 0 | R6: 0
B7: 4.1.1 | C7: 人力费用 | D7: 484.75 | E7: =SUM(G7:R7) | F7: =IFERROR(MAX(1+(E7-D7)/ABS(D7),0),) | G7: 32.253202 | H7: 36.318083 | I7: 35.989898 | J7: 36.802752 | K7: 0 | L7: 0 | M7: 0 | N7: 0 | O7: 0 | P7: 0 | Q7: 0 | R7: 0
B8: 4.1.2 | C8: 日常费用 | D8: 152.52558 | E8: =SUM(G8:R8) | F8: =IFERROR(MAX(1+(E8-D8)/ABS(D8),0),) | G8: 0.332017 | H8: 2.707272 | I8: 1.541137 | J8: 0.964978 | K8: 0 | L8: 0 | M8: 0 | N8: 0 | O8: 0 | P8: 0 | Q8: 0 | R8: 0
B9: 4.2 | C9: 变动费用 | D9: 1626.69 | E9: =SUM(G9:R9) | F9: =IFERROR(MAX(1+(E9-D9)/ABS(D9),0),) | G9: 14.270949 | H9: 4.380025 | I9: 12.898381 | J9: 18.887872 | K9: 0 | L9: 0 | M9: 0 | N9: 0 | O9: 0 | P9: 0 | Q9: 0 | R9: 0
B10: 4.2.1 | C10: 经营变动费用 | D10: 1626.69 | E10: =SUM(G10:R10) | F10: =IFERROR(MAX(1+(E10-D10)/ABS(D10),0),) | G10: 14.270949 | H10: 4.380025 | I10: 12.898381 | J10: 18.887872 | K10: 0 | L10: 0 | M10: 0 | N10: 0 | O10: 0 | P10: 0 | Q10: 0 | R10: 0
B11: 4.2.2 | C11: 营业成本 | D11: 0 | E11: =SUM(G11:R11) | F11: =IFERROR(MAX(1+(E11-D11)/ABS(D11),0),) | G11: 0 | H11: 0 | I11: 0 | J11: 0 | K11: 0 | L11: 0 | M11: 0 | N11: 0 | O11: 0 | P11: 0 | Q11: 0 | R11: 0
B12: 5 | C12: 资本性支出 | D12: 842 | E12: =SUM(G12:R12) | F12: =IFERROR(MAX(1+(E12-D12)/ABS(D12),0),) | G12: 0 | H12: 0 | I12: 1.935942 | J12: 0 | K12: 0 | L12: 0 | M12: 0 | N12: 0 | O12: 0 | P12: 0 | Q12: 0 | R12: 0
A13: 业务指标 | B13: 6 | C13: 期末出租率/月均入住率 | D13: 0.65 | E13: =AVERAGE(G13:R13) | F13: =IFERROR(MAX(1+(E13-D13)/ABS(D13),0),) | G13: 0.6413 | H13: 0.6413 | I13: 0.6774 | J13: 0.6694
B14: 7 | C14: 回款率 | D14: 0.95 | E14: =AVERAGE(G14:R14) | F14: =IFERROR(MAX(1+(E14-D14)/ABS(D14),0),) | G14: 0.8 | H14: 0.85 | I14: 0.96 | J14: 0.98
B15: 8 | C15: OTA网络评价 | D15: 0 | E15: =SUM(G15:R15) | F15: =IFERROR(MAX(1+(E15-D15)/ABS(D15),0),)
B16: 9 | C16: 规模保费 | D16: 0 | F16: =IFERROR(MAX(1+(E16-D16)/ABS(D16),0),)
B17: 10 | C17: 13月继续率 | D17: 0 | F17: =IFERROR(MAX(1+(E17-D17)/ABS(D17),0),)
B18: 11 | C18: 25月继续率 | D18: 0 | F18: =IFERROR(MAX(1+(E18-D18)/ABS(D18),0),)
C19: 2025年实际 | D19: 年度目标 | E19: 实际达成 | F19: 达成率 | G19: 1月 | H19: 2月 | I19: 3月 | J19: 4月 | K19: 5月 | L19: 6月 | M19: 7月 | N19: 8月 | O19: 9月 | P19: 10月 | Q19: 11月 | R19: 12月
C20: 营业收入 | D20: 9135.52 | E20: 8883.634 | F20: 0.97242784 | G20: 729.33674 | H20: 719.88634 | I20: 723.07548 | J20: 660.43262 | K20: 664.38903 | L20: 648.15076 | M20: 706.88458 | N20: 750.77023 | O20: 760.98751 | P20: 753.24024 | Q20: 811.20804 | R20: 955.27239
C21: EBITDA | D21: 2987 | E21: 4176.5883 | F21: 1.3982552 | G21: 467.60307 | H21: 458.16375 | I21: 455.05641 | J21: 373.68863 | K21: 383.64334 | L21: 380.24551 | M21: 435.28758 | N21: 340.11817 | O21: 282.65279 | P21: 458.20072 | Q21: -29.920605 | R21: 171.84894
C22: 经营活动净现金流 | D22: 4201.84 | E22: 5706.9127 | F22: 1.3581937 | G22: 519.67712 | H22: 75.853911 | I22: 1372.5291 | J22: -305.1153 | K22: 206.87521 | L22: 483.10408 | M22: 2770.4534 | N22: 444.81988 | O22: 55.640722 | P22: -339.28573 | Q22: 436.6169 | R22: -14.256541
C23: 经营支出小计 | D23: 2944.87 | E23: 2060.4383 | F23: 0.69967039 | G23: 46.543318 | H23: 46.899491 | I23: 53.197258 | J23: 61.114695 | K23: 61.169023 | L23: 44.000701 | M23: 46.583224 | N23: 173.56148 | O23: 267.83217 | P23: 67.458067 | Q23: 616.03897 | R23: 576.03994
C24: 固定费用 | D24: 740.8 | E24: 616.9797 | F24: 0.83285597 | G24: 42.784328 | H24: 41.427891 | I24: 41.138456 | J24: 55.460039 | K24: 51.775343 | L24: 37.9741 | M24: 37.255528 | N24: 42.148129 | O24: 49.19572 | P24: 37.067361 | Q24: 121.85546 | R24: 58.897352
C25: 人力费用 | D25: 528.61 | E25: 530.19663 | F25: 1.0030015 | G25: 42.32517 | H25: 41.387802 | I25: 40.402673 | J25: 54.232546 | K25: 43.613434 | L25: 36.302716 | M25: 36.36041 | N25: 36.974999 | O25: 43.456246 | P25: 35.424669 | Q25: 66.912655 | R25: 52.803311
C26: 日常费用 | D26: 212.19 | E26: 86.783071 | F26: 0.40898756 | G26: 0.459158 | H26: 0.040089 | I26: 0.735783 | J26: 1.227493 | K26: 8.161909 | L26: 1.671384 | M26: 0.895118 | N26: 5.17313 | O26: 5.739474 | P26: 1.642692 | Q26: 54.9428 | R26: 6.094041
C27: 变动费用 | D27: 2204.07 | E27: 1443.4586 | F27: 0.65490598 | G27: 3.75899 | H27: 5.4716 | I27: 12.058802 | J27: 5.654656 | K27: 9.39368 | L27: 6.026601 | M27: 9.327696 | N27: 131.41335 | O27: 218.63645 | P27: 30.390706 | Q27: 494.18351 | R27: 517.14259
C28: 经营变动费用 | D28: 2204.07 | E28: 1443.4586 | F28: 0.65490598 | G28: 3.75899 | H28: 5.4716 | I28: 12.058802 | J28: 5.654656 | K28: 9.39368 | L28: 6.026601 | M28: 9.327696 | N28: 131.41335 | O28: 218.63645 | P28: 30.390706 | Q28: 494.18351 | R28: 517.14259
C29: 营业成本 | D29: 0 | E29: 0 | F29: 0 | G29: 0 | H29: 0 | I29: 0 | J29: 0 | K29: 0 | L29: 0 | M29: 0 | N29: 0 | O29: 0 | P29: 0 | Q29: 0 | R29: 0
C30: 资本性支出 | D30: 1134 | E30: 353.64959 | F30: 0.31186031 | G30: 0 | H30: 2.929588 | I30: 3.66 | J30: 0 | K30: 36.25 | L30: 18.13 | M30: 26.51 | N30: 3.48 | O30: 121.39 | P30: 1.93 | Q30: 128.65 | R30: 10.72
C31: 期末出租率/月均入住率 | D31: 0.92 | E31: 0.57890833 | F31: 0.62924819 | G31: 0.57 | H31: 0.57 | I31: 0.5458 | J31: 0.5458 | K31: 0.5406 | L31: 0.5406 | M31: 0.5831 | N31: 0.5859 | O31: 0.5982 | P31: 0.6075 | Q31: 0.6141 | R31: 0.6453
C32: 回款率 | D32: 0.95 | E32: 0.79041667 | F32: 0.83201754 | G32: 0.9826 | H32: 0.19 | I32: 0.5178 | J32: 1 | K32: 0.9121 | L32: 0.9662 | M32: 1 | N32: 0.4163 | O32: 0.55 | P32: 1 | Q32: 0.95 | R32: 1
F33: 指标 | G33: 1月 | H33: 2月 | I33: 3月 | J33: 4月 | K33: 5月 | L33: 6月 | M33: 7月 | N33: 8月 | O33: 9月 | P33: 10月 | Q33: 11月 | R33: 12月
F34: 营业收入 | G34: {=IF(COLUMN(G2:R2)<=COLUMN(G2)+MATCH(填写页!$A$1,$G$1:$R$1,0)-1,G2:R2,NA())} | H34: 567.20524 | I34: 1148.0225 | J34: 0 | K34: #N/A | L34: #N/A | M34: #N/A | N34: #N/A | O34: #N/A | P34: #N/A | Q34: #N/A | R34: #N/A
F35: 同期营收 | G35: =G20 | H35: =H20 | I35: =I20 | J35: =J20 | K35: =K20 | L35: =L20 | M35: =M20 | N35: =N20 | ... R35: =R20
F36: 营收分解计划 | G36: =VLOOKUP(填写页!$C$2,分解计划!$A:$N,COLUMN()-4,FALSE) | H36: =VLOOKUP(填写页!$C$2,分解计划!$A:$N,COLUMN()-4,FALSE) | I36: =VLOOKUP(填写页!$C$2,分解计划!$A:$N,COLUMN()-4,FALSE) | J36: =VLOOKUP(填写页!$C$2,分解计划!$A:$N,COLUMN()-4,FALSE) | K36: =VLOOKUP(填写页!$C$2,分解计划!$A:$N,COLUMN()-4,FALSE) | L36: =VLOOKUP(填写页!$C$2,分解计划!$A:$N,COLUMN()-4,FALSE) | M36: =VLOOKUP(填写页!$C$2,分解计划!$A:$N,COLUMN()-4,FALSE) | N36: =VLOOKUP(填写页!$C$2,分解计划!$A:$N,COLUMN()-4,FALSE) | ... R36: =VLOOKUP(填写页!$C$2,分解计划!$A:$N,COLUMN()-4,FALSE)
F39: 指标 | G39: 1月 | H39: 2月 | I39: 3月 | J39: 4月 | K39: 5月 | L39: 6月 | M39: 7月 | N39: 8月 | O39: 9月 | P39: 10月 | Q39: 11月 | R39: 12月
F40: 营业收入 | G40: {=IF(COLUMN(G2:R2)<=COLUMN(G2)+MATCH(填写页!$A$1,$G$1:$R$1,0)-1,G2:R2,NA())} | H40: 567.20524 | I40: 1148.0225 | J40: 0 | K40: #N/A | L40: #N/A | M40: #N/A | N40: #N/A | O40: #N/A | P40: #N/A | Q40: #N/A | R40: #N/A
F41: EBITDA | G41: {=IF(COLUMN(G3:R3)<=COLUMN(G3)+MATCH(填写页!$A$1,$G$1:$R$1,0)-1,G3:R3,NA())} | H41: 296.73437 | I41: 885.00292 | J41: 0 | K41: #N/A | L41: #N/A | M41: #N/A | N41: #N/A | O41: #N/A | P41: #N/A | Q41: #N/A | R41: #N/A
F42: 经营活动净现金流 | G42: {=IF(COLUMN(G4:R4)<=COLUMN(G4)+MATCH(填写页!$A$1,$G$1:$R$1,0)-1,G4:R4,NA())} | H42: 883.277 | I42: -715.53544 | J42: 0 | K42: #N/A | L42: #N/A | M42: #N/A | N42: #N/A | O42: #N/A | P42: #N/A | Q42: #N/A | R42: #N/A
F43: 经营支出小计 | G43: {=IF(COLUMN(G5:R5)<=COLUMN(G5)+MATCH(填写页!$A$1,$G$1:$R$1,0)-1,G5:R5,NA())} | H43: 43.40538 | I43: 50.429416 | J43: 0 | K43: #N/A | L43: #N/A | M43: #N/A | N43: #N/A | O43: #N/A | P43: #N/A | Q43: #N/A | R43: #N/A

Sheet 大连凯丹
A1: 类别 | B1: 序号 | C1: 指标 | D1: 年度目标 | E1: 实际达成 | F1: 年度目标达成率 | G1: 1月 | H1: 2月 | I1: 3月 | J1: 4月 | K1: 5月 | L1: 6月 | M1: 7月 | N1: 8月 | O1: 9月 | P1: 10月 | Q1: 11月 | R1: 12月
A2: 经营指标 | B2: 1 | C2: 营业收入 | D2: {=INDEX(年度计划!E2:M18,,MATCH(填写页!C3,年度计划!E1:M1,0))} | E2: =SUM(G2:R2) | F2: =IFERROR(MAX(1+(E2-D2)/ABS(D2),0),) | G2: 51.84 | H2: 52.73 | I2: 53.12 | J2: 63.87
B3: 2 | C3: EBITDA | D3: 259.97843 | E3: =SUM(G3:R3) | F3: =IFERROR(MAX(1+(E3-D3)/ABS(D3),0),) | G3: 27.46 | H3: 29.79 | I3: 26.62 | J3: 37.16
B4: 3 | C4: 经营活动净现金流 | D4: 296.47159 | E4: =SUM(G4:R4) | F4: =IFERROR(MAX(1+(E4-D4)/ABS(D4),0),) | G4: 142.94 | H4: 51.65 | I4: 63.12 | J4: 4.81
A5: 财务指标 | B5: 4 | C5: 经营支出 | D5: 188.23 | E5: =SUM(G5:R5) | F5: =IFERROR(MAX(1+(E5-D5)/ABS(D5),0),) | G5: 10.86 | H5: 8.8 | I5: 10.79 | J5: 12.44 | K5: 0 | L5: 0 | M5: 0 | N5: 0 | O5: 0 | P5: 0 | Q5: 0 | R5: 0
B6: 4.1 | C6: 固定费用 | D6: 149.04 | E6: =SUM(G6:R6) | F6: =IFERROR(MAX(1+(E6-D6)/ABS(D6),0),) | G6: 8.74 | H6: 8.8 | I6: 9.22 | J6: 12.36 | K6: 0 | L6: 0 | M6: 0 | N6: 0 | O6: 0 | P6: 0 | Q6: 0 | R6: 0
B7: 4.1.1 | C7: 人力费用 | D7: 89.52 | E7: =SUM(G7:R7) | F7: =IFERROR(MAX(1+(E7-D7)/ABS(D7),0),) | G7: 6.35 | H7: 6.34 | I7: 6.4 | J7: 6.37 | K7: 0 | L7: 0 | M7: 0 | N7: 0 | O7: 0 | P7: 0 | Q7: 0 | R7: 0
B8: 4.1.2 | C8: 日常费用 | D8: 59.52 | E8: =SUM(G8:R8) | F8: =IFERROR(MAX(1+(E8-D8)/ABS(D8),0),) | G8: 2.49 | H8: 2.46 | I8: 2.82 | J8: 5.99 | K8: 0 | L8: 0 | M8: 0 | N8: 0 | O8: 0 | P8: 0 | Q8: 0 | R8: 0
B9: 4.2 | C9: 变动费用 | D9: 39.19 | E9: =SUM(G9:R9) | F9: =IFERROR(MAX(1+(E9-D9)/ABS(D9),0),) | G9: 2.12 | H9: 0 | I9: 1.57 | J9: 0.08 | K9: 0 | L9: 0 | M9: 0 | N9: 0 | O9: 0 | P9: 0 | Q9: 0 | R9: 0
B10: 4.2.1 | C10: 经营变动费用 | D10: 39.19 | E10: =SUM(G10:R10) | F10: =IFERROR(MAX(1+(E10-D10)/ABS(D10),0),) | G10: 2.12 | H10: 0 | I10: 1.57 | J10: 0.08 | K10: 0 | L10: 0 | M10: 0 | N10: 0 | O10: 0 | P10: 0 | Q10: 0 | R10: 0
B11: 4.2.2 | C11: 营业成本 | D11: 0 | E11: =SUM(G11:R11) | F11: =IFERROR(MAX(1+(E11-D11)/ABS(D11),0),) | G11: 0 | H11: 0 | I11: 0 | J11: 0 | K11: 0 | L11: 0 | M11: 0 | N11: 0 | O11: 0 | P11: 0 | Q11: 0 | R11: 0
B12: 5 | C12: 资本性支出 | D12: 79.6 | E12: =SUM(G12:R12) | F12: =IFERROR(MAX(1+(E12-D12)/ABS(D12),0),) | G12: 4.72 | H12: 3.48 | I12: 0 | J12: 0 | K12: 0 | L12: 0 | M12: 0 | N12: 0 | O12: 0 | P12: 0 | Q12: 0 | R12: 0
A13: 业务指标 | B13: 6 | C13: 期末出租率/月均入住率 | D13: 0.7171 | E13: =AVERAGE(G13:R13) | F13: =IFERROR(MAX(1+(E13-D13)/ABS(D13),0),) | G13: 0.715 | H13: 0.7308 | I13: 0.742 | J13: 0.7335
B14: 7 | C14: 回款率 | D14: 0.95 | E14: =AVERAGE(G14:R14) | F14: =IFERROR(MAX(1+(E14-D14)/ABS(D14),0),) | G14: 1 | H14: 0.6565 | I14: 0.8889 | J14: 1
B15: 8 | C15: OTA网络评价 | D15: 0 | E15: =SUM(G15:R15) | F15: =IFERROR(MAX(1+(E15-D15)/ABS(D15),0),)
B16: 9 | C16: 规模保费 | D16: 0 | F16: =IFERROR(MAX(1+(E16-D16)/ABS(D16),0),)
B17: 10 | C17: 13月继续率 | D17: 0 | F17: =IFERROR(MAX(1+(E17-D17)/ABS(D17),0),)
B18: 11 | C18: 25月继续率 | D18: 0 | F18: =IFERROR(MAX(1+(E18-D18)/ABS(D18),0),)
C19: 2025年实际 | D19: 年度目标 | E19: 实际达成 | F19: 达成率 | G19: 1月 | H19: 2月 | I19: 3月 | J19: 4月 | K19: 5月 | L19: 6月 | M19: 7月 | N19: 8月 | O19: 9月 | P19: 10月 | Q19: 11月 | R19: 12月
C20: 营业收入 | D20: 598.72 | E20: 744.72 | F20: 1.2438536 | G20: 49.42 | H20: 74.06 | I20: 50.16 | J20: 79.52 | K20: 51.64 | L20: 63.78 | M20: 51.24 | N20: 52.15 | O20: 77.91 | P20: 69.29 | Q20: 52.62 | R20: 72.93
C21: EBITDA | D21: 162.63 | E21: 400.88 | F21: 2.4649819 | G21: 17.57 | H21: 52 | I21: 26.04 | J21: 50.35 | K21: 11.92 | L21: 36.83 | M21: 24.38 | N21: 26.88 | O21: 52.72 | P21: 39.72 | Q21: 19.18 | R21: 43.29
C22: 经营活动净现金流 | D22: 22.54 | E22: 217.62 | F22: 9.6548358 | G22: -52.47 | H22: 42.33 | I22: 12.42 | J22: 11.66 | K22: 5.24 | L22: 85.36 | M22: 18.41 | N22: 50 | O22: -0.36 | P22: -24.21 | Q22: 56.09 | R22: 13.15
C23: 经营支出小计 | D23: 252.2 | E23: 164.24 | F23: 0.65122918 | G23: 13.97 | H23: 8.34 | I23: 7.15 | J23: 14.58 | K23: 25.08 | L23: 12.55 | M23: 11.96 | N23: 10.44 | O23: 10.74 | P23: 15.02 | Q23: 19.2 | R23: 15.21
C24: 固定费用 | D24: 165.66 | E24: 146.41 | F24: 0.88379814 | G24: 8.25 | H24: 10.69 | I24: 9.94 | J24: 13.65 | K24: 20.05 | L24: 8.52 | M24: 11.87 | N24: 8.33 | O24: 9.34 | P24: 14.76 | Q24: 17.89 | R24: 13.12
C25: 人力费用 | D25: 91.92 | E25: 84.55 | F25: 0.91982158 | G25: 5.84 | H25: 5.98 | I25: 7.56 | J25: 6.06 | K25: 10.45 | L25: 6.14 | M25: 6.35 | N25: 6.41 | O25: 6.36 | P25: 6.44 | Q25: 10.56 | R25: 6.4
C26: 日常费用 | D26: 73.74 | E26: 61.86 | F26: 0.83889341 | G26: 2.41 | H26: 4.71 | I26: 2.38 | J26: 7.59 | K26: 9.6 | L26: 2.38 | M26: 5.52 | N26: 1.92 | O26: 2.98 | P26: 8.32 | Q26: 7.33 | R26: 6.72
C27: 变动费用 | D27: 86.54 | E27: 17.83 | F27: 0.20603189 | G27: 5.72 | H27: -2.35 | I27: -2.79 | J27: 0.93 | K27: 5.03 | L27: 4.03 | M27: 0.09 | N27: 2.11 | O27: 1.4 | P27: 0.26 | Q27: 1.31 | R27: 2.09
C28: 经营变动费用 | D28: 86.54 | E28: 17.83 | F28: 0.20603189 | G28: 5.72 | H28: -2.35 | I28: -2.79 | J28: 0.93 | K28: 5.03 | L28: 4.03 | M28: 0.09 | N28: 2.11 | O28: 1.4 | P28: 0.26 | Q28: 1.31 | R28: 2.09
C29: 营业成本 | D29: 0 | E29: 0 | F29: 0 | G29: 0 | H29: 0 | I29: 0 | J29: 0 | K29: 0 | L29: 0 | M29: 0 | N29: 0 | O29: 0 | P29: 0 | Q29: 0 | R29: 0
C30: 资本性支出 | D30: 46 | E30: 13.89 | F30: 0.30195652 | G30: 0 | H30: 0 | I30: 2.6 | J30: 0 | K30: 1 | L30: 0.8 | M30: 3.62 | N30: 0 | O30: 2.6 | P30: 1.09 | Q30: 0 | R30: 2.18
C31: 期末出租率/月均入住率 | D31: 0.76 | E31: 0.74615 | F31: 0.98177632 | G31: 0.7497 | H31: 0.7679 | I31: 0.7507 | J31: 0.7678 | K31: 0.7307 | L31: 0.7293 | M31: 0.7232 | N31: 0.7347 | O31: 0.7445 | P31: 0.7518 | Q31: 0.7487 | R31: 0.7548
C32: 回款率 | D32: 0.95 | E32: 0.69370833 | F32: 0.7302193 | G32: 0.929 | H32: 0.7172 | I32: 0.4798 | J32: 0.3038 | K32: 0.4446 | L32: 1 | M32: 1 | N32: 0.7272 | O32: 0.5699 | P32: 0.469 | Q32: 0.684 | R32: 1
F33: 指标 | G33: 1月 | H33: 2月 | I33: 3月 | J33: 4月 | K33: 5月 | L33: 6月 | M33: 7月 | N33: 8月 | O33: 9月 | P33: 10月 | Q33: 11月 | R33: 12月
F34: 营业收入 | G34: {=IF(COLUMN(G2:R2)<=COLUMN(G2)+MATCH(填写页!$A$1,$G$1:$R$1,0)-1,G2:R2,NA())} | H34: 52.73 | I34: 53.12 | J34: 0 | K34: #N/A | L34: #N/A | M34: #N/A | N34: #N/A | O34: #N/A | P34: #N/A | Q34: #N/A | R34: #N/A
F35: 同期营收 | G35: =G20 | H35: =H20 | I35: =I20 | J35: =J20 | K35: =K20 | L35: =L20 | M35: =M20 | N35: =N20 | ... R35: =R20
F36: 营收分解计划 | G36: =VLOOKUP(填写页!$C$3,分解计划!$A:$N,COLUMN()-4,FALSE) | H36: =VLOOKUP(填写页!$C$3,分解计划!$A:$N,COLUMN()-4,FALSE) | I36: =VLOOKUP(填写页!$C$3,分解计划!$A:$N,COLUMN()-4,FALSE) | J36: =VLOOKUP(填写页!$C$3,分解计划!$A:$N,COLUMN()-4,FALSE) | K36: =VLOOKUP(填写页!$C$3,分解计划!$A:$N,COLUMN()-4,FALSE) | L36: =VLOOKUP(填写页!$C$3,分解计划!$A:$N,COLUMN()-4,FALSE) | M36: =VLOOKUP(填写页!$C$3,分解计划!$A:$N,COLUMN()-4,FALSE) | N36: =VLOOKUP(填写页!$C$3,分解计划!$A:$N,COLUMN()-4,FALSE) | ... R36: =VLOOKUP(填写页!$C$3,分解计划!$A:$N,COLUMN()-4,FALSE)
F39: 指标 | G39: 1月 | H39: 2月 | I39: 3月 | J39: 4月 | K39: 5月 | L39: 6月 | M39: 7月 | N39: 8月 | O39: 9月 | P39: 10月 | Q39: 11月 | R39: 12月
F40: 营业收入 | G40: {=IF(COLUMN(G2:R2)<=COLUMN(G2)+MATCH(填写页!$A$1,$G$1:$R$1,0)-1,G2:R2,NA())} | H40: 52.73 | I40: 53.12 | J40: 0 | K40: #N/A | L40: #N/A | M40: #N/A | N40: #N/A | O40: #N/A | P40: #N/A | Q40: #N/A | R40: #N/A
F41: EBITDA | G41: {=IF(COLUMN(G3:R3)<=COLUMN(G3)+MATCH(填写页!$A$1,$G$1:$R$1,0)-1,G3:R3,NA())} | H41: 29.79 | I41: 26.62 | J41: 0 | K41: #N/A | L41: #N/A | M41: #N/A | N41: #N/A | O41: #N/A | P41: #N/A | Q41: #N/A | R41: #N/A
F42: 经营活动净现金流 | G42: {=IF(COLUMN(G4:R4)<=COLUMN(G4)+MATCH(填写页!$A$1,$G$1:$R$1,0)-1,G4:R4,NA())} | H42: 51.65 | I42: 63.12 | J42: 0 | K42: #N/A | L42: #N/A | M42: #N/A | N42: #N/A | O42: #N/A | P42: #N/A | Q42: #N/A | R42: #N/A
F43: 经营支出小计 | G43: {=IF(COLUMN(G5:R5)<=COLUMN(G5)+MATCH(填写页!$A$1,$G$1:$R$1,0)-1,G5:R5,NA())} | H43: 8.8 | I43: 10.79 | J43: 0 | K43: #N/A | L43: #N/A | M43: #N/A | N43: #N/A | O43: #N/A | P43: #N/A | Q43: #N/A | R43: #N/A

Sheet 福建钱隆
A1: 类别 | B1: 序号 | C1: 指标 | D1: 年度目标 | E1: 实际达成 | F1: 年度目标达成率 | G1: 1月 | H1: 2月 | I1: 3月 | J1: 4月 | K1: 5月 | L1: 6月 | M1: 7月 | N1: 8月 | O1: 9月 | P1: 10月 | Q1: 11月 | R1: 12月
A2: 经营指标 | B2: 1 | C2: 营业收入 | D2: {=INDEX(年度计划!E2:M18,,MATCH(填写页!C4,年度计划!E1:M1,0))} | E2: =SUM(G2:R2) | F2: =IFERROR(MAX(1+(E2-D2)/ABS(D2),0),) | G2: 519.18593 | H2: 532.97154 | I2: 517.25193 | J2: 925.59221 | K2: 0 | L2: 0 | M2: 0 | N2: 0 | O2: 0 | P2: 0 | Q2: 0 | R2: 0
B3: 2 | C3: EBITDA | D3: 4789.05 | E3: =SUM(G3:R3) | F3: =IFERROR(MAX(1+(E3-D3)/ABS(D3),0),) | G3: 390.20747 | H3: 411.25073 | I3: 392.54369 | J3: 544.20433 | K3: 0 | L3: 0 | M3: 0 | N3: 0 | O3: 0 | P3: 0 | Q3: 0 | R3: 0
B4: 3 | C4: 经营活动净现金流 | D4: 4232.71 | E4: =SUM(G4:R4) | F4: =IFERROR(MAX(1+(E4-D4)/ABS(D4),0),) | G4: 501.21573 | H4: 344.23802 | I4: 920.00434 | J4: 323.90208
A5: 财务指标 | B5: 4 | C5: 经营支出 | D5: 823.59 | E5: =SUM(G5:R5) | F5: =IFERROR(MAX(1+(E5-D5)/ABS(D5),0),) | G5: 36.843094 | H5: 30.590467 | I5: 37.133258 | J5: 293.51709 | K5: 0 | L5: 0 | M5: 0 | N5: 0 | O5: 0 | P5: 0 | Q5: 0 | R5: 0
B6: 4.1 | C6: 固定费用 | D6: 750.54 | E6: =SUM(G6:R6) | F6: =IFERROR(MAX(1+(E6-D6)/ABS(D6),0),) | G6: 35.522094 | H6: 26.958767 | I6: 27.930338 | J6: 293.04035 | K6: 0 | L6: 0 | M6: 0 | N6: 0 | O6: 0 | P6: 0 | Q6: 0 | R6: 0
B7: 4.1.1 | C7: 人力费用 | D7: 295.69 | E7: =SUM(G7:R7) | F7: =IFERROR(MAX(1+(E7-D7)/ABS(D7),0),) | G7: 22.264558 | H7: 22.38943 | I7: 22.990727 | J7: 21.718834 | K7: 0 | L7: 0 | M7: 0 | N7: 0 | O7: 0 | P7: 0 | Q7: 0 | R7: 0
B8: 4.1.2 | C8: 日常费用 | D8: 454.85 | E8: =SUM(G8:R8) | F8: =IFERROR(MAX(1+(E8-D8)/ABS(D8),0),) | G8: 13.257536 | H8: 4.569337 | I8: 4.939611 | J8: 271.32152 | K8: 0 | L8: 0 | M8: 0 | N8: 0 | O8: 0 | P8: 0 | Q8: 0 | R8: 0
B9: 4.2 | C9: 变动费用 | D9: 73.05 | E9: =SUM(G9:R9) | F9: =IFERROR(MAX(1+(E9-D9)/ABS(D9),0),) | G9: 1.321 | H9: 3.6317 | I9: 9.20292 | J9: 0.47674 | K9: 0 | L9: 0 | M9: 0 | N9: 0 | O9: 0 | P9: 0 | Q9: 0 | R9: 0
B10: 4.2.1 | C10: 经营变动费用 | D10: 73.05 | E10: =SUM(G10:R10) | F10: =IFERROR(MAX(1+(E10-D10)/ABS(D10),0),) | G10: 1.321 | H10: 3.6317 | I10: 9.20292 | J10: 0.47674 | K10: 0 | L10: 0 | M10: 0 | N10: 0 | O10: 0 | P10: 0 | Q10: 0 | R10: 0
B11: 4.2.2 | C11: 营业成本 | D11: 0 | E11: =SUM(G11:R11) | F11: =IFERROR(MAX(1+(E11-D11)/ABS(D11),0),) | G11: 0 | H11: 0 | I11: 0 | J11: 0 | K11: 0 | L11: 0 | M11: 0 | N11: 0 | O11: 0 | P11: 0 | Q11: 0 | R11: 0
B12: 5 | C12: 资本性支出 | D12: 226.85 | E12: =SUM(G12:R12) | F12: =IFERROR(MAX(1+(E12-D12)/ABS(D12),0),) | G12: 0 | H12: 0 | I12: 0 | J12: 0 | K12: 0 | L12: 0 | M12: 0 | N12: 0 | O12: 0 | P12: 0 | Q12: 0 | R12: 0
A13: 业务指标 | B13: 6 | C13: 期末出租率/月均入住率 | D13: 0.5715 | E13: =AVERAGE(G13:R13) | F13: =IFERROR(MAX(1+(E13-D13)/ABS(D13),0),) | G13: 0.55115714 | H13: 0.55115714 | I13: 0.56022555 | J13: 0.56950452
B14: 7 | C14: 回款率 | D14: 0.95 | E14: =AVERAGE(G14:R14) | F14: =IFERROR(MAX(1+(E14-D14)/ABS(D14),0),) | G14: 0.8144 | H14: 0.70045088 | I14: 0.95453013 | J14: 0.96088298
B15: 8 | C15: OTA网络评价 | D15: 0 | E15: =SUM(G15:R15) | F15: =IFERROR(MAX(1+(E15-D15)/ABS(D15),0),)
B16: 9 | C16: 规模保费 | D16: 0 | F16: =IFERROR(MAX(1+(E16-D16)/ABS(D16),0),)
B17: 10 | C17: 13月继续率 | D17: 0 | F17: =IFERROR(MAX(1+(E17-D17)/ABS(D17),0),)
B18: 11 | C18: 25月继续率 | D18: 0 | F18: =IFERROR(MAX(1+(E18-D18)/ABS(D18),0),)
C19: 2025年实际 | D19: 年度目标 | E19: 实际达成 | F19: 达成率 | G19: 1月 | H19: 2月 | I19: 3月 | J19: 4月 | K19: 5月 | L19: 6月 | M19: 7月 | N19: 8月 | O19: 9月 | P19: 10月 | Q19: 11月 | R19: 12月
C20: 营业收入 | D20: 6800.17 | E20: 6811.2442 | F20: 1.0016285 | G20: 572.83709 | H20: 565.30403 | I20: 575.66361 | J20: 577.57187 | K20: 580.97393 | L20: 593.9485 | M20: 552.75106 | N20: 564.04237 | O20: 577.22315 | P20: 533.70582 | Q20: 555.61558 | R20: 561.60721
C21: EBITDA | D21: 4860.39 | E21: 5267.6432 | F21: 1.0837902 | G21: 441.68231 | H21: 439.6966 | I21: 462.9364 | J21: 448.57399 | K21: 446.42831 | L21: 467.59224 | M21: 427.93674 | N21: 437.11006 | O21: 458.53609 | P21: 389.13405 | Q21: 431.92653 | R21: 416.08985
C22: 经营活动净现金流 | D22: 5217.67 | E22: 4693.5539 | F22: 0.89954979 | G22: 457.76636 | H22: 397.98981 | I22: 733.16704 | J22: 163.7616 | K22: 355.01737 | L22: 700.84506 | M22: 99.747329 | N22: 452.95395 | O22: 638.10657 | P22: -52.592844 | Q22: 385.60298 | R22: 361.18872
C23: 经营支出小计 | D23: 835.83 | E23: 444.8521 | F23: 0.53222796 | G23: 34.039785 | H23: 32.449705 | I23: 29.859678 | J23: 33.51014 | K23: 40.082846 | L23: 35.257505 | M23: 32.304781 | N23: 32.287317 | O23: 41.870843 | P23: 51.132129 | Q23: 32.889669 | R23: 49.1677
C24: 固定费用 | D24: 713.28 | E24: 404.10497 | F24: 0.56654465 | G24: 30.319785 | H24: 32.081757 | I24: 29.362925 | J24: 33.365873 | K24: 35.61717 | L24: 35.067279 | M24: 30.577788 | N24: 31.476407 | O24: 37.312898 | P24: 46.131029 | Q24: 31.516469 | R24: 31.275588
C25: 人力费用 | D25: 321.73 | E25: 310.90811 | F25: 0.96636343 | G25: 25.718935 | H25: 27.063107 | I25: 24.906654 | J25: 25.806351 | K25: 26.225601 | L25: 26.437012 | M25: 26.083735 | N25: 26.630161 | O25: 32.092224 | P25: 21.443787 | Q25: 26.174806 | R25: 22.325734
C26: 日常费用 | D26: 391.55 | E26: 93.196861 | F26: 0.23802033 | G26: 4.60085 | H26: 5.01865 | I26: 4.456271 | J26: 7.559522 | K26: 9.391569 | L26: 8.630267 | M26: 4.494053 | N26: 4.846246 | O26: 5.220674 | P26: 24.687242 | Q26: 5.341663 | R26: 8.949854
C27: 变动费用 | D27: 122.55 | E27: 40.74713 | F27: 0.33249392 | G27: 3.72 | H27: 0.367948 | I27: 0.496753 | J27: 0.144267 | K27: 4.465676 | L27: 0.190226 | M27: 1.726993 | N27: 0.81091 | O27: 4.557945 | P27: 5.0011 | Q27: 1.3732 | R27: 17.892112
C28: 经营变动费用 | D28: 122.55 | E28: 40.74713 | F28: 0.33249392 | G28: 3.72 | H28: 0.367948 | I28: 0.496753 | J28: 0.144267 | K28: 4.465676 | L28: 0.190226 | M28: 1.726993 | N28: 0.81091 | O28: 4.557945 | P28: 5.0011 | Q28: 1.3732 | R28: 17.892112
C29: 营业成本 | D29: 0 | E29: 0 | F29: 0 | G29: 0 | H29: 0 | I29: 0 | J29: 0 | K29: 0 | L29: 0 | M29: 0 | N29: 0 | O29: 0 | P29: 0 | Q29: 0 | R29: 0
C30: 资本性支出 | D30: 0 | E30: 0 | F30: 0 | G30: 0 | H30: 0 | I30: 0 | J30: 0 | K30: 0 | L30: 0 | M30: 0 | N30: 0 | O30: 0 | P30: 0 | Q30: 0 | R30: 0
C31: 期末出租率/月均入住率 | D31: 0.57 | E31: 0.55232666 | F31: 0.96899414 | G31: 0.56842335 | H31: 0.56842335 | I31: 0.56249856 | J31: 0.55766713 | K31: 0.55589952 | L31: 0.55530127 | M31: 0.54169513 | N31: 0.53872341 | O31: 0.54128754 | P31: 0.53189524 | Q31: 0.55494825 | R31: 0.55115714
C32: 回款率 | D32: 0.95 | E32: 0.96013686 | F32: 1.0106704 | G32: 0.86501547 | H32: 0.89646295 | I32: 0.93766619 | J32: 0.97223736 | K32: 0.97383766 | L32: 0.99156221 | M32: 0.98812524 | N32: 0.95085063 | O32: 0.98727063 | P32: 0.9843092 | Q32: 0.9866076 | R32: 0.98769722
F33: 指标 | G33: 1月 | H33: 2月 | I33: 3月 | J33: 4月 | K33: 5月 | L33: 6月 | M33: 7月 | N33: 8月 | O33: 9月 | P33: 10月 | Q33: 11月 | R33: 12月
F34: 营业收入 | G34: {=IF(COLUMN(G2:R2)<=COLUMN(G2)+MATCH(填写页!$A$1,$G$1:$R$1,0)-1,G2:R2,NA())} | H34: 532.97154 | I34: 517.25193 | J34: 0 | K34: #N/A | L34: #N/A | M34: #N/A | N34: #N/A | O34: #N/A | P34: #N/A | Q34: #N/A | R34: #N/A
F35: 同期营收 | G35: =G20 | H35: =H20 | I35: =I20 | J35: =J20 | K35: =K20 | L35: =L20 | M35: =M20 | N35: =N20 | ... R35: =R20
F36: 营收分解计划 | G36: =VLOOKUP(填写页!$C$4,分解计划!$A:$N,COLUMN()-4,FALSE) | H36: =VLOOKUP(填写页!$C$4,分解计划!$A:$N,COLUMN()-4,FALSE) | I36: =VLOOKUP(填写页!$C$4,分解计划!$A:$N,COLUMN()-4,FALSE) | J36: =VLOOKUP(填写页!$C$4,分解计划!$A:$N,COLUMN()-4,FALSE) | K36: =VLOOKUP(填写页!$C$4,分解计划!$A:$N,COLUMN()-4,FALSE) | L36: =VLOOKUP(填写页!$C$4,分解计划!$A:$N,COLUMN()-4,FALSE) | M36: =VLOOKUP(填写页!$C$4,分解计划!$A:$N,COLUMN()-4,FALSE) | N36: =VLOOKUP(填写页!$C$4,分解计划!$A:$N,COLUMN()-4,FALSE) | ... R36: =VLOOKUP(填写页!$C$4,分解计划!$A:$N,COLUMN()-4,FALSE)
F39: 指标 | G39: 1月 | H39: 2月 | I39: 3月 | J39: 4月 | K39: 5月 | L39: 6月 | M39: 7月 | N39: 8月 | O39: 9月 | P39: 10月 | Q39: 11月 | R39: 12月
F40: 营业收入 | G40: {=IF(COLUMN(G2:R2)<=COLUMN(G2)+MATCH(填写页!$A$1,$G$1:$R$1,0)-1,G2:R2,NA())} | H40: 532.97154 | I40: 517.25193 | J40: 0 | K40: #N/A | L40: #N/A | M40: #N/A | N40: #N/A | O40: #N/A | P40: #N/A | Q40: #N/A | R40: #N/A
F41: EBITDA | G41: {=IF(COLUMN(G3:R3)<=COLUMN(G3)+MATCH(填写页!$A$1,$G$1:$R$1,0)-1,G3:R3,NA())} | H41: 411.25073 | I41: 392.54369 | J41: 0 | K41: #N/A | L41: #N/A | M41: #N/A | N41: #N/A | O41: #N/A | P41: #N/A | Q41: #N/A | R41: #N/A
F42: 经营活动净现金流 | G42: {=IF(COLUMN(G4:R4)<=COLUMN(G4)+MATCH(填写页!$A$1,$G$1:$R$1,0)-1,G4:R4,NA())} | H42: 344.23802 | I42: 920.00434 | J42: 0 | K42: #N/A | L42: #N/A | M42: #N/A | N42: #N/A | O42: #N/A | P42: #N/A | Q42: #N/A | R42: #N/A
F43: 经营支出小计 | G43: {=IF(COLUMN(G5:R5)<=COLUMN(G5)+MATCH(填写页!$A$1,$G$1:$R$1,0)-1,G5:R5,NA())} | H43: 30.590467 | I43: 37.133258 | J43: 0 | K43: #N/A | L43: #N/A | M43: #N/A | N43: #N/A | O43: #N/A | P43: #N/A | Q43: #N/A | R43: #N/A

Sheet 春夏秋冬
A1: 类别 | B1: 序号 | C1: 指标 | D1: 年度目标 | E1: 实际达成 | F1: 年度目标达成率 | G1: 1月 | H1: 2月 | I1: 3月 | J1: 4月 | K1: 5月 | L1: 6月 | M1: 7月 | N1: 8月 | O1: 9月 | P1: 10月 | Q1: 11月 | R1: 12月
A2: 经营指标 | B2: 1 | C2: 营业收入 | D2: {=INDEX(年度计划!E2:M18,,MATCH(填写页!C5,年度计划!E1:M1,0))} | E2: =SUM(G2:R2) | F2: =IFERROR(MAX(1+(E2-D2)/ABS(D2),0),) | G2: 115.23 | H2: 97.66 | I2: 97.81 | J2: 102.53 | K2: 0 | L2: 0 | M2: 0 | N2: 0 | O2: 0 | P2: 0 | Q2: 0 | R2: 0 | S2: =D2-E2
B3: 2 | C3: EBITDA | D3: 903.57 | E3: =SUM(G3:R3) | F3: =IFERROR(MAX(1+(E3-D3)/ABS(D3),0),) | G3: 64.96 | H3: 47.55 | I3: 49.88 | J3: 46.19
B4: 3 | C4: 经营活动净现金流 | D4: 664.10036 | E4: =SUM(G4:R4) | F4: =IFERROR(MAX(1+(E4-D4)/ABS(D4),0),) | G4: -11.16 | H4: -8.45 | I4: 86.87 | J4: 21.83
A5: 财务指标 | B5: 4 | C5: 经营支出 | D5: 835.1 | E5: =SUM(G5:R5) | F5: =IFERROR(MAX(1+(E5-D5)/ABS(D5),0),) | G5: 25.4393 | H5: 25.42 | I5: 23.66 | J5: 30.88 | K5: 0 | L5: 0 | M5: 0 | N5: 0 | O5: 0 | P5: 0 | Q5: 0 | R5: 0
B6: 4.1 | C6: 固定费用 | D6: 795.9 | E6: =SUM(G6:R6) | F6: =IFERROR(MAX(1+(E6-D6)/ABS(D6),0),) | G6: 24.8893 | H6: 23.58 | I6: 23.66 | J6: 25.24 | K6: 0 | L6: 0 | M6: 0 | N6: 0 | O6: 0 | P6: 0 | Q6: 0 | R6: 0
B7: 4.1.1 | C7: 人力费用 | D7: 298.77 | E7: =SUM(G7:R7) | F7: =IFERROR(MAX(1+(E7-D7)/ABS(D7),0),) | G7: 24.89 | H7: 23.48 | I7: 23.55 | J7: 23.68 | K7: 0 | L7: 0 | M7: 0 | N7: 0 | O7: 0 | P7: 0 | Q7: 0 | R7: 0
B8: 4.1.2 | C8: 日常费用 | D8: 497.13 | E8: =SUM(G8:R8) | F8: =IFERROR(MAX(1+(E8-D8)/ABS(D8),0),) | G8: -0.0007 | H8: 0.1 | I8: 0.11 | J8: 1.56 | K8: 0 | L8: 0 | M8: 0 | N8: 0 | O8: 0 | P8: 0 | Q8: 0 | R8: 0
B9: 4.2 | C9: 变动费用 | D9: 39.2 | E9: =SUM(G9:R9) | F9: =IFERROR(MAX(1+(E9-D9)/ABS(D9),0),) | G9: 0.55 | H9: 1.84 | I9: 0 | J9: 5.64 | K9: 0 | L9: 0 | M9: 0 | N9: 0 | O9: 0 | P9: 0 | Q9: 0 | R9: 0
B10: 4.2.1 | C10: 经营变动费用 | D10: 39.2 | E10: =SUM(G10:R10) | F10: =IFERROR(MAX(1+(E10-D10)/ABS(D10),0),) | G10: 0.55 | H10: 1.84 | I10: 0 | J10: 5.64 | K10: 0 | L10: 0 | M10: 0 | N10: 0 | O10: 0 | P10: 0 | Q10: 0 | R10: 0
B11: 4.2.2 | C11: 营业成本 | D11: 0 | E11: =SUM(G11:R11) | F11: =IFERROR(MAX(1+(E11-D11)/ABS(D11),0),) | G11: 0 | H11: 0 | I11: 0 | J11: 0 | K11: 0 | L11: 0 | M11: 0 | N11: 0 | O11: 0 | P11: 0 | Q11: 0 | R11: 0
B12: 5 | C12: 资本性支出 | D12: 52 | E12: =SUM(G12:R12) | F12: =IFERROR(MAX(1+(E12-D12)/ABS(D12),0),) | G12: 0 | H12: 0 | I12: 0 | J12: 0 | K12: 0 | L12: 0 | M12: 0 | N12: 0 | O12: 0 | P12: 0 | Q12: 0 | R12: 0
A13: 业务指标 | B13: 6 | C13: 期末出租率/月均入住率 | D13: 0.69 | E13: =AVERAGE(G13:R13) | F13: =IFERROR(MAX(1+(E13-D13)/ABS(D13),0),) | G13: 0.6011 | H13: 0.5998 | I13: 0.6228 | J13: 0.6348
B14: 7 | C14: 回款率 | D14: 0.89 | E14: =AVERAGE(G14:R14) | F14: =IFERROR(MAX(1+(E14-D14)/ABS(D14),0),) | G14: 0.8345 | H14: 0.8097 | I14: 0.888 | J14: 0.8746
B15: 8 | C15: OTA网络评价 | D15: 0 | E15: =SUM(G15:R15) | F15: =IFERROR(MAX(1+(E15-D15)/ABS(D15),0),)
B16: 9 | C16: 规模保费 | D16: 0 | F16: =IFERROR(MAX(1+(E16-D16)/ABS(D16),0),)
B17: 10 | C17: 13月继续率 | D17: 0 | F17: =IFERROR(MAX(1+(E17-D17)/ABS(D17),0),)
B18: 11 | C18: 25月继续率 | D18: 0 | F18: =IFERROR(MAX(1+(E18-D18)/ABS(D18),0),)
C19: 2025年实际 | D19: 年度目标 | E19: 实际达成 | F19: 达成率 | G19: 1月 | H19: 2月 | I19: 3月 | J19: 4月 | K19: 5月 | L19: 6月 | M19: 7月 | N19: 8月 | O19: 9月 | P19: 10月 | Q19: 11月 | R19: 12月
C20: 营业收入 | D20: 1550.77 | E20: 1372.83 | F20: 0.885257 | G20: 111.6 | H20: 120.92 | I20: 113.45 | J20: 120.32 | K20: 111.4 | L20: 106.45 | M20: 110.76 | N20: 103.39 | O20: 119.5 | P20: 126.5 | Q20: 118.9 | R20: 109.64
C21: EBITDA | D21: 347.12 | E21: 263.42 | F21: 0.75887301 | G21: 52.31 | H21: 62.88 | I21: 59.23 | J21: 35.76 | K21: 4.15 | L21: 1.04 | M21: 33.89 | N21: 31.31 | O21: 43.66 | P21: 66.09 | Q21: 58.63 | R21: -185.53
C22: 经营活动净现金流 | D22: 260.94 | E22: 318.49 | F22: 1.2205488 | G22: -41.82 | H22: -56.94 | I22: 95.26 | J22: -11.52 | K22: -49.6 | L22: -25.25 | M22: -10.38 | N22: 10.98 | O22: -20.97 | P22: 50.7 | Q22: 241 | R22: 137.03
C23: 经营支出小计 | D23: 902.6 | E23: 778.03 | F23: 0.86198759 | G23: 30.18 | H23: 30.35 | I23: 26.69 | J23: 56.3 | K23: 79.9 | L23: 78.44 | M23: 48.95 | N23: 46.37 | O23: 48.86 | P23: 32.56 | Q23: 31.47 | R23: 267.96
C24: 固定费用 | D24: 759.86 | E24: 697.05 | F24: 0.91734004 | G24: 27.04 | H24: 27.64 | I24: 26.69 | J24: 19.6 | K24: 66.09 | L24: 77.8 | M24: 36.2 | N24: 45.87 | O24: 46.19 | P24: 30.64 | Q24: 28.25 | R24: 265.04
C25: 人力费用 | D25: 341.01 | E25: 311.08 | F25: 0.91223131 | G25: 26.34 | H25: 26.58 | I25: 26.2 | J25: 17.72 | K25: 29.73 | L25: 26.8 | M25: 26.48 | N25: 26.16 | O25: 26.13 | P25: 26.63 | Q25: 26.14 | R25: 26.17
C26: 日常费用 | D26: 418.85 | E26: 385.97 | F26: 0.92149934 | G26: 0.7 | H26: 1.06 | I26: 0.49 | J26: 1.88 | K26: 36.36 | L26: 51 | M26: 9.72 | N26: 19.71 | O26: 20.06 | P26: 4.01 | Q26: 2.11 | R26: 238.87
C27: 变动费用 | D27: 142.74 | E27: 80.98 | F27: 0.56732521 | G27: 3.14 | H27: 2.71 | I27: 0 | J27: 36.7 | K27: 13.81 | L27: 0.64 | M27: 12.75 | N27: 0.5 | O27: 2.67 | P27: 1.92 | Q27: 3.22 | R27: 2.92
C28: 经营变动费用 | D28: 142.74 | E28: 80.98 | F28: 0.56732521 | G28: 3.14 | H28: 2.71 | I28: 0 | J28: 36.7 | K28: 13.81 | L28: 0.64 | M28: 12.75 | N28: 0.5 | O28: 2.67 | P28: 1.92 | Q28: 3.22 | R28: 2.92
C29: 营业成本 | D29: 0 | E29: 0 | F29: 0 | G29: 0 | H29: 0 | I29: 0 | J29: 0 | K29: 0 | L29: 0 | M29: 0 | N29: 0 | O29: 0 | P29: 0 | Q29: 0 | R29: 0
C30: 资本性支出 | D30: 93.2 | E30: 2.21 | F30: 0.023712446 | G30: 0 | H30: 0 | I30: 0 | J30: 0 | K30: 0 | L30: 2.21 | M30: 0 | N30: 0 | O30: 0 | P30: 0 | Q30: 0 | R30: 0
C31: 期末出租率/月均入住率 | D31: 0.63 | E31: 0.57841667 | F31: 0.91812169 | G31: 0.508 | H31: 0.508 | I31: 0.5604 | J31: 0.6 | K31: 0.5986 | L31: 0.5916 | M31: 0.5859 | N31: 0.5892 | O31: 0.6013 | P31: 0.6026 | Q31: 0.5954 | R31: 0.6
C32: 回款率 | D32: 0.95 | E32: 0.81445 | F32: 0.85731579 | G32: 0.9427 | H32: 0.8111 | I32: 0.8419 | J32: 0.8812 | K32: 0.7439 | L32: 0.732 | M32: 0.7424 | N32: 0.724 | O32: 0.8011 | P32: 0.8871 | Q32: 0.8 | R32: 0.866
F33: 指标 | G33: 1月 | H33: 2月 | I33: 3月 | J33: 4月 | K33: 5月 | L33: 6月 | M33: 7月 | N33: 8月 | O33: 9月 | P33: 10月 | Q33: 11月 | R33: 12月
F34: 营业收入 | G34: {=IF(COLUMN(G2:R2)<=COLUMN(G2)+MATCH(填写页!$A$1,$G$1:$R$1,0)-1,G2:R2,NA())} | H34: 97.66 | I34: 97.81 | J34: 0 | K34: #N/A | L34: #N/A | M34: #N/A | N34: #N/A | O34: #N/A | P34: #N/A | Q34: #N/A | R34: #N/A
F35: 同期营收 | G35: =G20 | H35: =H20 | I35: =I20 | J35: =J20 | K35: =K20 | L35: =L20 | M35: =M20 | N35: =N20 | ... R35: =R20
F36: 营收分解计划 | G36: =VLOOKUP(填写页!$C$5,分解计划!$A:$N,COLUMN()-4,FALSE) | H36: =VLOOKUP(填写页!$C$5,分解计划!$A:$N,COLUMN()-4,FALSE) | I36: =VLOOKUP(填写页!$C$5,分解计划!$A:$N,COLUMN()-4,FALSE) | J36: =VLOOKUP(填写页!$C$5,分解计划!$A:$N,COLUMN()-4,FALSE) | K36: =VLOOKUP(填写页!$C$5,分解计划!$A:$N,COLUMN()-4,FALSE) | L36: =VLOOKUP(填写页!$C$5,分解计划!$A:$N,COLUMN()-4,FALSE) | M36: =VLOOKUP(填写页!$C$5,分解计划!$A:$N,COLUMN()-4,FALSE) | N36: =VLOOKUP(填写页!$C$5,分解计划!$A:$N,COLUMN()-4,FALSE) | ... R36: =VLOOKUP(填写页!$C$5,分解计划!$A:$N,COLUMN()-4,FALSE)
F39: 指标 | G39: 1月 | H39: 2月 | I39: 3月 | J39: 4月 | K39: 5月 | L39: 6月 | M39: 7月 | N39: 8月 | O39: 9月 | P39: 10月 | Q39: 11月 | R39: 12月
F40: 营业收入 | G40: {=IF(COLUMN(G2:R2)<=COLUMN(G2)+MATCH(填写页!$A$1,$G$1:$R$1,0)-1,G2:R2,NA())} | H40: 97.66 | I40: 97.81 | J40: 0 | K40: #N/A | L40: #N/A | M40: #N/A | N40: #N/A | O40: #N/A | P40: #N/A | Q40: #N/A | R40: #N/A
F41: EBITDA | G41: {=IF(COLUMN(G3:R3)<=COLUMN(G3)+MATCH(填写页!$A$1,$G$1:$R$1,0)-1,G3:R3,NA())} | H41: 47.55 | I41: 49.88 | J41: 0 | K41: #N/A | L41: #N/A | M41: #N/A | N41: #N/A | O41: #N/A | P41: #N/A | Q41: #N/A | R41: #N/A
F42: 经营活动净现金流 | G42: {=IF(COLUMN(G4:R4)<=COLUMN(G4)+MATCH(填写页!$A$1,$G$1:$R$1,0)-1,G4:R4,NA())} | H42: -8.45 | I42: 86.87 | J42: 0 | K42: #N/A | L42: #N/A | M42: #N/A | N42: #N/A | O42: #N/A | P42: #N/A | Q42: #N/A | R42: #N/A
F43: 经营支出小计 | G43: {=IF(COLUMN(G5:R5)<=COLUMN(G5)+MATCH(填写页!$A$1,$G$1:$R$1,0)-1,G5:R5,NA())} | H43: 25.42 | I43: 23.66 | J43: 0 | K43: #N/A | L43: #N/A | M43: #N/A | N43: #N/A | O43: #N/A | P43: #N/A | Q43: #N/A | R43: #N/A

Sheet 重庆宜新
A1: 类别 | B1: 序号 | C1: 指标 | D1: 年度目标 | E1: 实际达成 | F1: 年度目标达成率 | G1: 1月 | H1: 2月 | I1: 3月 | J1: 4月 | K1: 5月 | L1: 6月 | M1: 7月 | N1: 8月 | O1: 9月 | P1: 10月 | Q1: 11月 | R1: 12月
A2: 经营指标 | B2: 1 | C2: 营业收入 | D2: {=INDEX(年度计划!E2:M18,,MATCH(填写页!C6,年度计划!E1:M1,0))} | E2: =SUM(G2:R2) | F2: =IFERROR(MAX(1+(E2-D2)/ABS(D2),0),) | G2: 51.121052 | H2: 28.623522 | I2: 50.833071 | J2: 31.674646 | K2: 0 | L2: 0 | M2: 0 | N2: 0 | O2: 0 | P2: 0 | Q2: 0 | R2: 0
B3: 2 | C3: EBITDA | D3: 190.72038 | E3: =SUM(G3:R3) | F3: =IFERROR(MAX(1+(E3-D3)/ABS(D3),0),) | G3: 45.562446 | H3: 23.283589 | I3: 3.393221 | J3: -116.28951
B4: 3 | C4: 经营活动净现金流 | D4: 259.62622 | E4: =SUM(G4:R4) | F4: =IFERROR(MAX(1+(E4-D4)/ABS(D4),0),) | G4: 27.423488 | H4: 11.955679 | I4: 66.988168 | J4: -115.15762
A5: 财务指标 | B5: 4 | C5: 经营支出 | D5: 268.66369 | E5: =SUM(G5:R5) | F5: =IFERROR(MAX(1+(E5-D5)/ABS(D5),0),) | G5: 5.135138 | H5: 5.14162 | I5: 47.184892 | J5: 5.15811 | K5: 0 | L5: 0 | M5: 0 | N5: 0 | O5: 0 | P5: 0 | Q5: 0 | R5: 0
B6: 4.1 | C6: 固定费用 | D6: 89.223688 | E6: =SUM(G6:R6) | F6: =IFERROR(MAX(1+(E6-D6)/ABS(D6),0),) | G6: 5.135138 | H6: 5.133978 | I6: 5.119921 | J6: 5.15811 | K6: 0 | L6: 0 | M6: 0 | N6: 0 | O6: 0 | P6: 0 | Q6: 0 | R6: 0
B7: 4.1.1 | C7: 人力费用 | D7: 56.812 | E7: =SUM(G7:R7) | F7: =IFERROR(MAX(1+(E7-D7)/ABS(D7),0),) | G7: 4.15351 | H7: 4.15751 | I7: 4.16351 | J7: 4.18151 | K7: 0 | L7: 0 | M7: 0 | N7: 0 | O7: 0 | P7: 0 | Q7: 0 | R7: 0
B8: 4.1.2 | C8: 日常费用 | D8: 32.411688 | E8: =SUM(G8:R8) | F8: =IFERROR(MAX(1+(E8-D8)/ABS(D8),0),) | G8: 0.981628 | H8: 0.976468 | I8: 0.956411 | J8: 0.9766 | K8: 0 | L8: 0 | M8: 0 | N8: 0 | O8: 0 | P8: 0 | Q8: 0 | R8: 0
B9: 4.2 | C9: 变动费用 | D9: 179.44 | E9: =SUM(G9:R9) | F9: =IFERROR(MAX(1+(E9-D9)/ABS(D9),0),) | G9: 0 | H9: 0.007642 | I9: 42.064971 | J9: 0 | K9: 0 | L9: 0 | M9: 0 | N9: 0 | O9: 0 | P9: 0 | Q9: 0 | R9: 0
B10: 4.2.1 | C10: 经营变动费用 | D10: 179.44 | E10: =SUM(G10:R10) | F10: =IFERROR(MAX(1+(E10-D10)/ABS(D10),0),) | G10: 0 | H10: 0.007642 | I10: 42.064971 | J10: 0 | K10: 0 | L10: 0 | M10: 0 | N10: 0 | O10: 0 | P10: 0 | Q10: 0 | R10: 0
B11: 4.2.2 | C11: 营业成本 | D11: 0 | E11: =SUM(G11:R11) | F11: =IFERROR(MAX(1+(E11-D11)/ABS(D11),0),) | G11: 0 | H11: 0 | I11: 0 | J11: 0 | K11: 0 | L11: 0 | M11: 0 | N11: 0 | O11: 0 | P11: 0 | Q11: 0 | R11: 0
B12: 5 | C12: 资本性支出 | D12: 0 | E12: =SUM(G12:R12) | F12: =IFERROR(MAX(1+(E12-D12)/ABS(D12),0),) | G12: 0 | H12: 0 | I12: 0 | J12: 0 | K12: 0 | L12: 0 | M12: 0 | N12: 0 | O12: 0 | P12: 0 | Q12: 0 | R12: 0
A13: 业务指标 | B13: 6 | C13: 期末出租率/月均入住率 | D13: 0.5805 | E13: =AVERAGE(G13:R13) | F13: =IFERROR(MAX(1+(E13-D13)/ABS(D13),0),) | G13: 0.4458 | H13: 0.4458 | I13: 0.431 | J13: 0.43
B14: 7 | C14: 回款率 | D14: 0.95 | E14: =AVERAGE(G14:R14) | F14: =IFERROR(MAX(1+(E14-D14)/ABS(D14),0),) | G14: 0.55 | H14: 0.99 | I14: 7.94 | J14: 0.32
B15: 8 | C15: OTA网络评价 | D15: 0 | E15: =SUM(G15:R15) | F15: =IFERROR(MAX(1+(E15-D15)/ABS(D15),0),)
B16: 9 | C16: 规模保费 | D16: 0 | F16: =IFERROR(MAX(1+(E16-D16)/ABS(D16),0),)
B17: 10 | C17: 13月继续率 | D17: 0 | F17: =IFERROR(MAX(1+(E17-D17)/ABS(D17),0),)
B18: 11 | C18: 25月继续率 | D18: 0 | F18: =IFERROR(MAX(1+(E18-D18)/ABS(D18),0),)
C19: 2025年实际 | D19: 年度目标 | E19: 实际达成 | F19: 达成率 | G19: 1月 | H19: 2月 | I19: 3月 | J19: 4月 | K19: 5月 | L19: 6月 | M19: 7月 | N19: 8月 | O19: 9月 | P19: 10月 | Q19: 11月 | R19: 12月
C20: 营业收入 | D20: 946.75 | E20: 708.33923 | F20: 0.7481798 | G20: 60.893351 | H20: 61.44702 | I20: 62.937243 | J20: 58.140368 | K20: 54.59992 | L20: 57.112126 | M20: 57.107671 | N20: 57.864961 | O20: 58.017674 | P20: 58.010279 | Q20: 59.447189 | R20: 62.761423
C21: EBITDA | D21: 299.2 | E21: 178.61397 | F21: 0.59697181 | G21: 55.345344 | H21: 52.94616 | I21: 10.920281 | J21: -92.776627 | K21: 50.910904 | L21: 4.590861 | M21: 55.615657 | N21: 71.043053 | O21: 8.255389 | P21: -100.08482 | Q21: 50.585096 | R21: 11.262664
C22: 经营活动净现金流 | D22: 419.4 | E22: -135.22805 | F22: 0 | G22: -1.41261 | H22: 53.257678 | I22: 40.865669 | J22: -125.20206 | K22: 1.002805 | L22: 28.571851 | M22: -29.549682 | N22: 65.141702 | O22: -25.666086 | P22: -143.74181 | Q22: 27.289989 | R22: -25.785497
C23: 经营支出小计 | D23: 350.08 | E23: 251.96941 | F23: 0.71974808 | G23: 4.863251 | H23: 10.057306 | I23: 52.514199 | J23: 3.604859 | K23: 4.082708 | L23: 52.48927 | M23: 1.151065 | N23: 4.161439 | O23: 53.638572 | P23: 5.621372 | Q23: 8.176755 | R23: 51.608613
C24: 固定费用 | D24: 105.48 | E24: 70.468867 | F24: 0.668078 | G24: 4.236976 | H24: 4.209171 | I24: 7.354025 | J24: 3.596335 | K24: 4.020908 | L24: 10.315817 | M24: 4.178119 | N24: 4.161439 | O24: 7.432971 | P24: 5.521376 | Q24: 7.535327 | R24: 7.906403
C25: 人力费用 | D25: 73.96 | E25: 48.369547 | F25: 0.65399604 | G25: 4.212146 | H25: 4.1866 | I25: 4.1564 | J25: 2.393701 | K25: 4.137445 | L25: 4.139445 | M25: 4.154388 | N25: 4.139445 | O25: 4.239045 | P25: 4.308327 | Q25: 4.15351 | R25: 4.149095
C26: 日常费用 | D26: 31.52 | E26: 22.09932 | F26: 0.70112056 | G26: 0.02483 | H26: 0.022571 | I26: 3.197625 | J26: 1.202634 | K26: -0.116537 | L26: 6.176372 | M26: 0.023731 | N26: 0.021994 | O26: 3.193926 | P26: 1.213049 | Q26: 3.381817 | R26: 3.757308
C27: 变动费用 | D27: 244.6 | E27: 181.50054 | F27: 0.74203002 | G27: 0.626275 | H27: 5.848135 | I27: 45.160174 | J27: 0.008524 | K27: 0.0618 | L27: 42.173453 | M27: -3.027054 | N27: 0 | O27: 46.205601 | P27: 0.099996 | Q27: 0.641428 | R27: 43.70221
C28: 经营变动费用 | D28: 244.6 | E28: 181.50054 | F28: 0.74203002 | G28: 0.626275 | H28: 5.848135 | I28: 45.160174 | J28: 0.008524 | K28: 0.0618 | L28: 42.173453 | M28: -3.027054 | N28: 0 | O28: 46.205601 | P28: 0.099996 | Q28: 0.641428 | R28: 43.70221
C29: 营业成本 | D29: 0 | E29: 0 | F29: 0 | G29: 0 | H29: 0 | I29: 0 | J29: 0 | K29: 0 | L29: 0 | M29: 0 | N29: 0 | O29: 0 | P29: 0 | Q29: 0 | R29: 0
C30: 资本性支出 | D30: 61.2 | E30: 0 | F30: 0 | G30: 0 | H30: 0 | I30: 0 | J30: 0 | K30: 0 | L30: 0 | M30: 0 | N30: 0 | O30: 0 | P30: 0 | Q30: 0 | R30: 0
C31: 期末出租率/月均入住率 | D31: 0.7353088 | E31: 0.40698333 | F31: 0.55348628 | G31: 0.401 | H31: 0.423 | I31: 0.423 | J31: 0.423 | K31: 0.423 | L31: 0.3808 | M31: 0.3803 | N31: 0.3806 | O31: 0.3818 | P31: 0.3813 | Q31: 0.443 | R31: 0.443
C32: 回款率 | D32: 0.95 | E32: 1.939925 | F32: 2.0420263 | G32: 0.413 | H32: 0.77 | I32: 4.185 | J32: 0.275 | K32: 0.702 | L32: 8.05 | M32: 0.1741 | N32: 3.16 | O32: 1.99 | P32: 0.26 | Q32: 1.18 | R32: 2.12
F33: 指标 | G33: 1月 | H33: 2月 | I33: 3月 | J33: 4月 | K33: 5月 | L33: 6月 | M33: 7月 | N33: 8月 | O33: 9月 | P33: 10月 | Q33: 11月 | R33: 12月
F34: 营业收入 | G34: {=IF(COLUMN(G2:R2)<=COLUMN(G2)+MATCH(填写页!$A$1,$G$1:$R$1,0)-1,G2:R2,NA())} | H34: 28.623522 | I34: 50.833071 | J34: 0 | K34: #N/A | L34: #N/A | M34: #N/A | N34: #N/A | O34: #N/A | P34: #N/A | Q34: #N/A | R34: #N/A
F35: 同期营收 | G35: =G20 | H35: =H20 | I35: =I20 | J35: =J20 | K35: =K20 | L35: =L20 | M35: =M20 | N35: =N20 | ... R35: =R20
F36: 营收分解计划 | G36: =VLOOKUP(填写页!$C$6,分解计划!$A:$N,COLUMN()-4,FALSE) | H36: =VLOOKUP(填写页!$C$6,分解计划!$A:$N,COLUMN()-4,FALSE) | I36: =VLOOKUP(填写页!$C$6,分解计划!$A:$N,COLUMN()-4,FALSE) | J36: =VLOOKUP(填写页!$C$6,分解计划!$A:$N,COLUMN()-4,FALSE) | K36: =VLOOKUP(填写页!$C$6,分解计划!$A:$N,COLUMN()-4,FALSE) | L36: =VLOOKUP(填写页!$C$6,分解计划!$A:$N,COLUMN()-4,FALSE) | M36: =VLOOKUP(填写页!$C$6,分解计划!$A:$N,COLUMN()-4,FALSE) | N36: =VLOOKUP(填写页!$C$6,分解计划!$A:$N,COLUMN()-4,FALSE) | ... R36: =VLOOKUP(填写页!$C$6,分解计划!$A:$N,COLUMN()-4,FALSE)
F39: 指标 | G39: 1月 | H39: 2月 | I39: 3月 | J39: 4月 | K39: 5月 | L39: 6月 | M39: 7月 | N39: 8月 | O39: 9月 | P39: 10月 | Q39: 11月 | R39: 12月
F40: 营业收入 | G40: {=IF(COLUMN(G2:R2)<=COLUMN(G2)+MATCH(填写页!$A$1,$G$1:$R$1,0)-1,G2:R2,NA())} | H40: 28.623522 | I40: 50.833071 | J40: 0 | K40: #N/A | L40: #N/A | M40: #N/A | N40: #N/A | O40: #N/A | P40: #N/A | Q40: #N/A | R40: #N/A
F41: EBITDA | G41: {=IF(COLUMN(G3:R3)<=COLUMN(G3)+MATCH(填写页!$A$1,$G$1:$R$1,0)-1,G3:R3,NA())} | H41: 23.283589 | I41: 3.393221 | J41: 0 | K41: #N/A | L41: #N/A | M41: #N/A | N41: #N/A | O41: #N/A | P41: #N/A | Q41: #N/A | R41: #N/A
F42: 经营活动净现金流 | G42: {=IF(COLUMN(G4:R4)<=COLUMN(G4)+MATCH(填写页!$A$1,$G$1:$R$1,0)-1,G4:R4,NA())} | H42: 11.955679 | I42: 66.988168 | J42: 0 | K42: #N/A | L42: #N/A | M42: #N/A | N42: #N/A | O42: #N/A | P42: #N/A | Q42: #N/A | R42: #N/A
F43: 经营支出小计 | G43: {=IF(COLUMN(G5:R5)<=COLUMN(G5)+MATCH(填写页!$A$1,$G$1:$R$1,0)-1,G5:R5,NA())} | H43: 5.14162 | I43: 47.184892 | J43: 0 | K43: #N/A | L43: #N/A | M43: #N/A | N43: #N/A | O43: #N/A | P43: #N/A | Q43: #N/A | R43: #N/A

Sheet 伯豪瑞廷
A1: 类别 | B1: 序号 | C1: 指标 | D1: 年度目标 | E1: 实际达成 | F1: 年度目标达成率 | G1: 1月 | H1: 2月 | I1: 3月 | J1: 4月 | K1: 5月 | L1: 6月 | M1: 7月 | N1: 8月 | O1: 9月 | P1: 10月 | Q1: 11月 | R1: 12月
A2: 经营指标 | B2: 1 | C2: 营业收入 | D2: {=INDEX(年度计划!E2:M18,,MATCH(填写页!C7,年度计划!E1:M1,0))} | E2: =SUM(G2:R2) | F2: =IFERROR(MAX(1+(E2-D2)/ABS(D2),0),) | G2: 557.51 | H2: 405.76 | I2: 524.09 | J2: 614.99 | K2: 0 | L2: 0 | M2: 0 | N2: 0 | O2: 0 | P2: 0 | Q2: 0 | R2: 0
B3: 2 | C3: GOP | D3: 3208.89 | E3: =SUM(G3:R3) | F3: =IFERROR(MAX(1+(E3-D3)/ABS(D3),0),) | G3: 200.8924 | H3: 69.875 | I3: 196.984 | J3: 278.191 | K3: 0 | L3: 0 | M3: 0 | N3: 0 | O3: 0 | P3: 0 | Q3: 0 | R3: 0
B4: 3 | C4: 经营活动净现金流 | D4: 2140.79 | E4: =SUM(G4:R4) | F4: =IFERROR(MAX(1+(E4-D4)/ABS(D4),0),) | G4: 17.26 | H4: 25.62 | I4: 207.69 | J4: -186.61
A5: 财务指标 | B5: 4 | C5: 经营支出 | D5: 4751.02 | E5: =SUM(G5:R5) | F5: =IFERROR(MAX(1+(E5-D5)/ABS(D5),0),) | G5: 359.0376 | H5: 338.005 | I5: 331.676 | J5: 338.939 | K5: 0 | L5: 0 | M5: 0 | N5: 0 | O5: 0 | P5: 0 | Q5: 0 | R5: 0
B6: 4.1 | C6: 固定费用 | D6: 2813.65 | E6: =SUM(G6:R6) | F6: =IFERROR(MAX(1+(E6-D6)/ABS(D6),0),) | G6: 196.84 | H6: 206.46 | I6: 208.23 | J6: 203.97 | K6: 0 | L6: 0 | M6: 0 | N6: 0 | O6: 0 | P6: 0 | Q6: 0 | R6: 0
B7: 4.1.1 | C7: 人力费用 | D7: 2148.46 | E7: =SUM(G7:R7) | F7: =IFERROR(MAX(1+(E7-D7)/ABS(D7),0),) | G7: 167.97 | H7: 178.3 | I7: 163.82 | J7: 164.77 | K7: 0 | L7: 0 | M7: 0 | N7: 0 | O7: 0 | P7: 0 | Q7: 0 | R7: 0
B8: 4.1.2 | C8: 日常费用 | D8: 665.19 | E8: =SUM(G8:R8) | F8: =IFERROR(MAX(1+(E8-D8)/ABS(D8),0),) | G8: 28.87 | H8: 28.16 | I8: 44.41 | J8: 39.2 | K8: 0 | L8: 0 | M8: 0 | N8: 0 | O8: 0 | P8: 0 | Q8: 0 | R8: 0
B9: 4.2 | C9: 变动费用 | D9: 1937.37 | E9: =SUM(G9:R9) | F9: =IFERROR(MAX(1+(E9-D9)/ABS(D9),0),) | G9: 162.1976 | H9: 131.545 | I9: 123.446 | J9: 134.969 | K9: 0 | L9: 0 | M9: 0 | N9: 0 | O9: 0 | P9: 0 | Q9: 0 | R9: 0
B10: 4.2.1 | C10: 经营变动费用 | D10: 647.28 | E10: =SUM(G10:R10) | F10: =IFERROR(MAX(1+(E10-D10)/ABS(D10),0),) | G10: 51.0976 | H10: 43.375 | I10: 51.276 | J10: 55.939 | K10: 0 | L10: 0 | M10: 0 | N10: 0 | O10: 0 | P10: 0 | Q10: 0 | R10: 0
B11: 4.2.2 | C11: 营业成本 | D11: 1290.09 | E11: =SUM(G11:R11) | F11: =IFERROR(MAX(1+(E11-D11)/ABS(D11),0),) | G11: 111.1 | H11: 88.17 | I11: 72.17 | J11: 79.03 | K11: 0 | L11: 0 | M11: 0 | N11: 0 | O11: 0 | P11: 0 | Q11: 0 | R11: 0
B12: 5 | C12: 资本性支出 | D12: 294.498 | E12: =SUM(G12:R12) | F12: =IFERROR(MAX(1+(E12-D12)/ABS(D12),0),) | G12: 0 | H12: 0 | I12: 0 | J12: 0 | K12: 0 | L12: 0 | M12: 0 | N12: 0 | O12: 0 | P12: 0 | Q12: 0 | R12: 0
A13: 业务指标 | B13: 6 | C13: 期末出租率/月均入住率 | D13: 0.8203 | E13: =AVERAGE(G13:R13) | F13: =IFERROR(MAX(1+(E13-D13)/ABS(D13),0),) | G13: 0.6527 | H13: 0.5493 | I13: 0.7096 | J13: 0.877
B14: 7 | C14: 回款率 | D14: 0.842 | E14: =AVERAGE(G14:R14) | F14: =IFERROR(MAX(1+(E14-D14)/ABS(D14),0),) | G14: 0.7759 | H14: 0.7279 | I14: 0.7701 | J14: 0.9935
B15: 8 | C15: OTA网络评价 | D15: 4.7 | E15: =AVERAGE(G15:R15) | F15: =IFERROR(MAX(1+(E15-D15)/ABS(D15),0),) | G15: 4.68 | H15: 4.67 | I15: 4.69 | J15: 4.67
B16: 9 | C16: 规模保费 | D16: 0 | F16: =IFERROR(MAX(1+(E16-D16)/ABS(D16),0),)
B17: 10 | C17: 13月继续率 | D17: 0 | F17: =IFERROR(MAX(1+(E17-D17)/ABS(D17),0),)
B18: 11 | C18: 25月继续率 | D18: 0 | F18: =IFERROR(MAX(1+(E18-D18)/ABS(D18),0),)
C19: 2025年实际 | D19: 年度目标 | E19: 实际达成 | F19: 达成率 | G19: 1月 | H19: 2月 | I19: 3月 | J19: 4月 | K19: 5月 | L19: 6月 | M19: 7月 | N19: 8月 | O19: 9月 | P19: 10月 | Q19: 11月 | R19: 12月
C20: 营业收入 | D20: 8778.3 | E20: 7549.28 | F20: 0.85999339 | G20: 638.59 | H20: 508.88 | I20: 583.66 | J20: 632.44 | K20: 669.89 | L20: 654.76 | M20: 751.06 | N20: 672.56 | O20: 585.23 | P20: 673.95 | Q20: 623.86 | R20: 554.4
C21: GOP | D21: 3749.94 | E21: 2969.6251 | F21: 0.7919127 | G21: 206.54 | H21: 132.75 | I21: 222.6261 | J21: 273.82 | K21: 282.32 | L21: 278.26 | M21: 346.88 | N21: 275.043 | O21: 231.813 | P21: 291.005 | Q21: 258.948 | R21: 169.62
C22: 经营活动净现金流 | D22: 2297.88 | E22: 1105.78 | F22: 0.48121747 | G22: 37.57 | H22: 26.77 | I22: 149.98 | J22: -211.81 | K22: 229.59 | L22: 169.05 | M22: 281.06 | N22: 285.12 | O22: 254.51 | P22: -376.23 | Q22: 118.4 | R22: 141.77
C23: 经营支出小计 | D23: 5050.36 | E23: 4621.7049 | F23: 0.91512385 | G23: 431.87 | H23: 375.86 | I23: 363.5439 | J23: 358.34 | K23: 401.51 | L23: 381.88 | M23: 406.45 | N23: 399.797 | O23: 359.457 | P23: 385.285 | Q23: 367.262 | R23: 390.45
C24: 固定费用 | D24: 2620.81 | E24: 2558.95 | F24: 0.97639661 | G24: 241.55 | H24: 212.22 | I24: 208.383 | J24: 210.2 | K24: 219.812 | L24: 212.98 | M24: 211.755 | N24: 207.25 | O24: 210.79 | P24: 216.355 | Q24: 206.385 | R24: 201.27
C25: 人力费用 | D25: 2233.02 | E25: 2216.83 | F25: 0.99274973 | G25: 210.63 | H25: 183.02 | I25: 181.86 | J25: 185.99 | K25: 187.97 | L25: 185.91 | M25: 182.75 | N25: 176.48 | O25: 184.77 | P25: 190.98 | Q25: 177.12 | R25: 169.35
C26: 日常费用 | D26: 387.79 | E26: 342.12 | F26: 0.88223007 | G26: 30.92 | H26: 29.2 | I26: 26.523 | J26: 24.21 | K26: 31.842 | L26: 27.07 | M26: 29.005 | N26: 30.77 | O26: 26.02 | P26: 25.375 | Q26: 29.265 | R26: 31.92
C27: 变动费用 | D27: 2429.55 | E27: 2062.7549 | F27: 0.84902756 | G27: 190.32 | H27: 163.64 | I27: 155.1609 | J27: 148.14 | K27: 181.698 | L27: 168.9 | M27: 194.695 | N27: 192.547 | O27: 148.667 | P27: 168.93 | Q27: 160.877 | R27: 189.18
C28: 经营变动费用 | D28: 942.96 | E28: 891.0549 | F28: 0.94495514 | G28: 68.45 | H28: 70.04 | I28: 75.6709 | J28: 71.2 | K28: 80.108 | L28: 74.62 | M28: 82.975 | N28: 85.877 | O28: 65.857 | P28: 69.76 | Q28: 80.287 | R28: 66.21
C29: 营业成本 | D29: 1486.59 | E29: 1171.7 | F29: 0.78817966 | G29: 121.87 | H29: 93.6 | I29: 79.49 | J29: 76.94 | K29: 101.59 | L29: 94.28 | M29: 111.72 | N29: 106.67 | O29: 82.81 | P29: 99.17 | Q29: 80.59 | R29: 122.97
C30: 资本性支出 | D30: 231.78 | E30: 131.16 | F30: 0.56588144 | G30: 0 | H30: 0.98 | I30: 0 | J30: 5.13 | K30: 5.09 | L30: 5.42 | M30: 2.1 | N30: 1.86 | O30: 4.59 | P30: 0.52 | Q30: 9.33 | R30: 96.14
C31: 期末出租率/月均入住率 | D31: 0.844 | E31: 0.78608333 | F31: 0.93137836 | G31: 0.708 | H31: 0.627 | I31: 0.696 | J31: 0.786 | K31: 0.829 | L31: 0.86 | M31: 0.936 | N31: 0.89 | O31: 0.803 | P31: 0.823 | Q31: 0.801 | R31: 0.674
C32: 回款率 | D32: 0.95 | E32: 0.82283333 | F32: 0.86614035 | G32: 0.763 | H32: 0.799 | I32: 0.793 | J32: 0.922 | K32: 0.762 | L32: 0.665 | M32: 0.867 | N32: 0.962 | O32: 0.891 | P32: 0.795 | Q32: 0.784 | R32: 0.871
F33: 指标 | G33: 1月 | H33: 2月 | I33: 3月 | J33: 4月 | K33: 5月 | L33: 6月 | M33: 7月 | N33: 8月 | O33: 9月 | P33: 10月 | Q33: 11月 | R33: 12月
F34: 营业收入 | G34: {=IF(COLUMN(G2:R2)<=COLUMN(G2)+MATCH(填写页!$A$1,$G$1:$R$1,0)-1,G2:R2,NA())} | H34: 405.76 | I34: 524.09 | J34: 0 | K34: #N/A | L34: #N/A | M34: #N/A | N34: #N/A | O34: #N/A | P34: #N/A | Q34: #N/A | R34: #N/A
F35: 同期营收 | G35: =G20 | H35: =H20 | I35: =I20 | J35: =J20 | K35: =K20 | L35: =L20 | M35: =M20 | N35: =N20 | ... R35: =R20
D36: =D3/D2 | E36: =E3/E2 | F36: 营收分解计划 | G36: =VLOOKUP(填写页!$C$7,分解计划!$A:$N,COLUMN()-4,FALSE) | H36: =VLOOKUP(填写页!$C$7,分解计划!$A:$N,COLUMN()-4,FALSE) | I36: =VLOOKUP(填写页!$C$7,分解计划!$A:$N,COLUMN()-4,FALSE) | J36: =VLOOKUP(填写页!$C$7,分解计划!$A:$N,COLUMN()-4,FALSE) | K36: =VLOOKUP(填写页!$C$7,分解计划!$A:$N,COLUMN()-4,FALSE) | L36: =VLOOKUP(填写页!$C$7,分解计划!$A:$N,COLUMN()-4,FALSE) | M36: =VLOOKUP(填写页!$C$7,分解计划!$A:$N,COLUMN()-4,FALSE) | N36: =VLOOKUP(填写页!$C$7,分解计划!$A:$N,COLUMN()-4,FALSE) | ... R36: =VLOOKUP(填写页!$C$7,分解计划!$A:$N,COLUMN()-4,FALSE)
E37: =E5/E2
F39: 指标 | G39: 1月 | H39: 2月 | I39: 3月 | J39: 4月 | K39: 5月 | L39: 6月 | M39: 7月 | N39: 8月 | O39: 9月 | P39: 10月 | Q39: 11月 | R39: 12月
F40: 营业收入 | G40: {=IF(COLUMN(G2:R2)<=COLUMN(G2)+MATCH(填写页!$A$1,$G$1:$R$1,0)-1,G2:R2,NA())} | H40: 405.76 | I40: 524.09 | J40: 0 | K40: #N/A | L40: #N/A | M40: #N/A | N40: #N/A | O40: #N/A | P40: #N/A | Q40: #N/A | R40: #N/A
F41: GOP | G41: {=IF(COLUMN(G3:R3)<=COLUMN(G3)+MATCH(填写页!$A$1,$G$1:$R$1,0)-1,G3:R3,NA())} | H41: 69.875 | I41: 196.984 | J41: 0 | K41: #N/A | L41: #N/A | M41: #N/A | N41: #N/A | O41: #N/A | P41: #N/A | Q41: #N/A | R41: #N/A
F42: 经营活动净现金流 | G42: {=IF(COLUMN(G4:R4)<=COLUMN(G4)+MATCH(填写页!$A$1,$G$1:$R$1,0)-1,G4:R4,NA())} | H42: 25.62 | I42: 207.69 | J42: 0 | K42: #N/A | L42: #N/A | M42: #N/A | N42: #N/A | O42: #N/A | P42: #N/A | Q42: #N/A | R42: #N/A
F43: 经营支出小计 | G43: {=IF(COLUMN(G5:R5)<=COLUMN(G5)+MATCH(填写页!$A$1,$G$1:$R$1,0)-1,G5:R5,NA())} | H43: 338.005 | I43: 331.676 | J43: 0 | K43: #N/A | L43: #N/A | M43: #N/A | N43: #N/A | O43: #N/A | P43: #N/A | Q43: #N/A | R43: #N/A

Sheet 重庆瑞尔
A1: 类别 | B1: 序号 | C1: 指标 | D1: 年度目标 | E1: 实际达成 | F1: 年度目标达成率 | G1: 1月 | H1: 2月 | I1: 3月 | J1: 4月 | K1: 5月 | L1: 6月 | M1: 7月 | N1: 8月 | O1: 9月 | P1: 10月 | Q1: 11月 | R1: 12月
A2: 经营指标 | B2: 1 | C2: 营业收入 | D2: {=INDEX(年度计划!E2:M18,,MATCH(填写页!C8,年度计划!E1:M1,0))} | E2: =SUM(G2:R2) | F2: =IFERROR(MAX(1+(E2-D2)/ABS(D2),0),) | G2: 78.97726 | H2: 63.822824 | I2: 80.56083 | J2: 96.956248 | K2: 0 | L2: 0 | M2: 0 | N2: 0 | O2: 0 | P2: 0 | Q2: 0 | R2: 0
B3: 2 | C3: GOP | D3: -55.516737 | E3: =SUM(G3:R3) | F3: =IFERROR(MAX(1+(E3-D3)/ABS(D3),0),) | G3: -52.776259 | H3: -38.670642 | I3: -1.727057 | J3: -13.573026 | K3: 0 | L3: 0 | M3: 0 | N3: 0 | O3: 0 | P3: 0 | Q3: 0 | R3: 0
B4: 3 | C4: 经营活动净现金流 | D4: -178.55007 | E4: =SUM(G4:R4) | F4: =IFERROR(MAX(1+(E4-D4)/ABS(D4),0),) | G4: -59.297686 | H4: -47.233397 | I4: -17.259462 | J4: -90.647837
A5: 财务指标 | B5: 4 | C5: 经营支出 | D5: 1518.434 | E5: =SUM(G5:R5) | F5: =IFERROR(MAX(1+(E5-D5)/ABS(D5),0),) | G5: 131.62255 | H5: 102.38878 | I5: 82.703909 | J5: 110.36911 | K5: 0 | L5: 0 | M5: 0 | N5: 0 | O5: 0 | P5: 0 | Q5: 0 | R5: 0
B6: 4.1 | C6: 固定费用 | D6: 793.4447 | E6: =SUM(G6:R6) | F6: =IFERROR(MAX(1+(E6-D6)/ABS(D6),0),) | G6: 82.740795 | H6: 54.661567 | I6: 41.604384 | J6: 62.007687 | K6: 0 | L6: 0 | M6: 0 | N6: 0 | O6: 0 | P6: 0 | Q6: 0 | R6: 0
B7: 4.1.1 | C7: 人力费用 | D7: 700.56 | E7: =SUM(G7:R7) | F7: =IFERROR(MAX(1+(E7-D7)/ABS(D7),0),) | G7: 77.910641 | H7: 52.070162 | I7: 46.482044 | J7: 47.60297 | K7: 0 | L7: 0 | M7: 0 | N7: 0 | O7: 0 | P7: 0 | Q7: 0 | R7: 0
B8: 4.1.2 | C8: 日常费用 | D8: 92.8847 | E8: =SUM(G8:R8) | F8: =IFERROR(MAX(1+(E8-D8)/ABS(D8),0),) | G8: 4.830154 | H8: 2.591405 | I8: -4.87766 | J8: 14.404717 | K8: 0 | L8: 0 | M8: 0 | N8: 0 | O8: 0 | P8: 0 | Q8: 0 | R8: 0
B9: 4.2 | C9: 变动费用 | D9: 724.9893 | E9: =SUM(G9:R9) | F9: =IFERROR(MAX(1+(E9-D9)/ABS(D9),0),) | G9: 48.881752 | H9: 47.727211 | I9: 41.099525 | J9: 48.361423 | K9: 0 | L9: 0 | M9: 0 | N9: 0 | O9: 0 | P9: 0 | Q9: 0 | R9: 0
B10: 4.2.1 | C10: 经营变动费用 | D10: 225.42 | E10: =SUM(G10:R10) | F10: =IFERROR(MAX(1+(E10-D10)/ABS(D10),0),) | G10: 14.661237 | H10: 17.69237 | I10: 15.084433 | J10: 20.184048 | K10: 0 | L10: 0 | M10: 0 | N10: 0 | O10: 0 | P10: 0 | Q10: 0 | R10: 0
B11: 4.2.2 | C11: 营业成本 | D11: 499.5693 | E11: =SUM(G11:R11) | F11: =IFERROR(MAX(1+(E11-D11)/ABS(D11),0),) | G11: 34.220515 | H11: 30.034841 | I11: 26.015092 | J11: 28.177375 | K11: 0 | L11: 0 | M11: 0 | N11: 0 | O11: 0 | P11: 0 | Q11: 0 | R11: 0
B12: 5 | C12: 资本性支出 | D12: 153.94 | E12: =SUM(G12:R12) | F12: =IFERROR(MAX(1+(E12-D12)/ABS(D12),0),) | G12: 0 | H12: 0 | I12: 0 | J12: 0 | K12: 0 | L12: 0 | M12: 0 | N12: 0 | O12: 0 | P12: 0 | Q12: 0 | R12: 0
A13: 业务指标 | B13: 6 | C13: 期末出租率/月均入住率 | D13: 0.71 | E13: =AVERAGE(G13:R13) | F13: =IFERROR(MAX(1+(E13-D13)/ABS(D13),0),) | G13: 0.41286389 | H13: 0.31946864 | I13: 0.59343037 | J13: 0.74512195
B14: 7 | C14: 回款率 | D14: 0.98 | E14: =AVERAGE(G14:R14) | F14: =IFERROR(MAX(1+(E14-D14)/ABS(D14),0),) | G14: 0.97824235 | H14: 0.94651203 | I14: 0.89600247 | J14: 0.91666599
B15: 8 | C15: OTA网络评价 | D15: 4.7 | E15: =AVERAGE(G15:R15) | F15: =IFERROR(MAX(1+(E15-D15)/ABS(D15),0),) | G15: 4.7 | H15: 4.7 | I15: 4.7 | J15: 4.7
B16: 9 | C16: 规模保费 | D16: 0 | F16: =IFERROR(MAX(1+(E16-D16)/ABS(D16),0),)
B17: 10 | C17: 13月继续率 | D17: 0 | F17: =IFERROR(MAX(1+(E17-D17)/ABS(D17),0),)
B18: 11 | C18: 25月继续率 | D18: 0 | F18: =IFERROR(MAX(1+(E18-D18)/ABS(D18),0),)
C19: 2025年实际 | D19: 年度目标 | E19: 实际达成 | F19: 达成率 | G19: 1月 | H19: 2月 | I19: 3月 | J19: 4月 | K19: 5月 | L19: 6月 | M19: 7月 | N19: 8月 | O19: 9月 | P19: 10月 | Q19: 11月 | R19: 12月
C20: 营业收入 | D20: 1749.21 | E20: 1317.0211 | F20: 0.75292339 | G20: 122.07055 | H20: 81.181808 | I20: 97.998313 | J20: 102.57482 | K20: 114.97763 | L20: 96.161043 | M20: 113.34614 | N20: 129.57156 | O20: 113.18523 | P20: 138.98558 | Q20: 123.14268 | R20: 83.825761
C21: GOP | D21: 185.18 | E21: -62.410234 | F21: 0 | G21: -30.342026 | H21: -23.808526 | I21: -2.670252 | J21: 8.87845 | K21: -9.082622 | L21: -13.523187 | M21: -0.486976 | N21: 14.714839 | O21: 3.159387 | P21: 9.342381 | Q21: -1.889775 | R21: -16.701927
C22: 经营活动净现金流 | D22: 15.37 | E22: -334.31939 | F22: 0 | G22: -22.160819 | H22: -64.887175 | I22: -1.798001 | J22: -110.40968 | K22: 26.191044 | L22: -14.371964 | M22: -35.609103 | N22: -8.644165 | O22: 3.299494 | P22: -91.279589 | Q22: -13.699818 | R22: -0.949615
C23: 经营支出小计 | D23: 1573.61 | E23: 1383.951 | F23: 0.87947521 | G23: 152.26767 | H23: 106.34511 | I23: 100.97573 | J23: 93.525853 | K23: 123.81811 | L23: 110.31608 | M23: 113.6617 | N23: 119.3665 | O23: 109.92283 | P23: 129.46949 | Q23: 125.64226 | R23: 98.639651
C24: 固定费用 | D24: 741.27 | E24: 723.7531 | F24: 0.97636907 | G24: 66.421653 | H24: 58.459528 | I24: 54.903276 | J24: 46.604141 | K24: 71.358028 | L24: 55.95855 | M24: 57.568122 | N24: 55.12155 | O24: 54.711267 | P24: 70.248746 | Q24: 70.477954 | R24: 61.920285
C25: 人力费用 | D25: 645.31 | E25: 628.60191 | F25: 0.97410843 | G25: 60.679863 | H25: 52.981514 | I25: 52.264505 | J25: 35.619784 | K25: 64.600598 | L25: 49.420506 | M25: 54.495432 | N25: 51.821029 | O25: 49.744293 | P25: 56.277602 | Q25: 49.951766 | R25: 50.745022
C26: 日常费用 | D26: 95.96 | E26: 95.151186 | F26: 0.99157134 | G26: 5.74179 | H26: 5.478014 | I26: 2.638771 | J26: 10.984357 | K26: 6.75743 | L26: 6.538044 | M26: 3.07269 | N26: 3.300521 | O26: 4.966974 | P26: 13.971144 | Q26: 20.526188 | R26: 11.175263
C27: 变动费用 | D27: 832.35 | E27: 660.19788 | F27: 0.79317341 | G27: 85.84602 | H27: 47.885586 | I27: 46.072458 | J27: 46.921712 | K27: 52.46008 | L27: 54.357531 | M27: 56.09358 | N27: 64.244948 | O27: 55.211561 | P27: 59.22074 | Q27: 55.164302 | R27: 36.719366
C28: 经营变动费用 | D28: 238.03 | E28: 204.55631 | F28: 0.85937196 | G28: 21.862432 | H28: 15.525939 | I28: 18.129138 | J28: 17.697507 | K28: 17.47416 | L28: 22.092931 | M28: 13.202619 | N28: 16.035961 | O28: 20.631425 | P28: 15.199642 | Q28: 17.972665 | R28: 8.731888
C29: 营业成本 | D29: 594.31 | E29: 455.64158 | F29: 0.76667325 | G29: 63.983588 | H29: 32.359647 | I29: 27.94332 | J29: 29.224205 | K29: 34.98592 | L29: 32.2646 | M29: 42.890961 | N29: 48.208987 | O29: 34.580136 | P29: 44.021098 | Q29: 37.191637 | R29: 27.987478
C30: 资本性支出 | D30: 234.95 | E30: 14.644794 | F30: 0.062331534 | G30: 2.251681 | H30: 0 | I30: 0 | J30: 0 | K30: 1.752211 | L30: 0 | M30: 0 | N30: 0 | O30: 1.651361 | P30: 0 | Q30: 0 | R30: 8.989541
C31: 期末出租率/月均入住率 | D31: 0.73 | E31: 0.67602008 | F31: 0.92605491 | G31: 0.38099921 | H31: 0.54006969 | I31: 0.65558615 | J31: 0.70243902 | K31: 0.68784422 | L31: 0.62144309 | M31: 0.8782 | N31: 0.87372148 | O31: 0.53719512 | P31: 0.82218725 | Q31: 0.82581301 | R31: 0.58674272
C32: 回款率 | D32: 0.95 | E32: 0.97238902 | F32: 1.0235674 | G32: 0.86032117 | H32: 0.79777875 | I32: 1.2575653 | J32: 1.1169652 | K32: 1.2863519 | L32: 0.97034216 | M32: 0.93746444 | N32: 0.8722107 | O32: 0.74436843 | P32: 1.1978773 | Q32: 0.97594919 | R32: 0.65147365
F33: 指标 | G33: 1月 | H33: 2月 | I33: 3月 | J33: 4月 | K33: 5月 | L33: 6月 | M33: 7月 | N33: 8月 | O33: 9月 | P33: 10月 | Q33: 11月 | R33: 12月
F34: 营业收入 | G34: {=IF(COLUMN(G2:R2)<=COLUMN(G2)+MATCH(填写页!$A$1,$G$1:$R$1,0)-1,G2:R2,NA())} | H34: 63.822824 | I34: 80.56083 | J34: 0 | K34: #N/A | L34: #N/A | M34: #N/A | N34: #N/A | O34: #N/A | P34: #N/A | Q34: #N/A | R34: #N/A
F35: 同期营收 | G35: =G20 | H35: =H20 | I35: =I20 | J35: =J20 | K35: =K20 | L35: =L20 | M35: =M20 | N35: =N20 | ... R35: =R20
F36: 营收分解计划 | G36: =VLOOKUP(填写页!$C$8,分解计划!$A:$N,COLUMN()-4,FALSE) | H36: =VLOOKUP(填写页!$C$8,分解计划!$A:$N,COLUMN()-4,FALSE) | I36: =VLOOKUP(填写页!$C$8,分解计划!$A:$N,COLUMN()-4,FALSE) | J36: =VLOOKUP(填写页!$C$8,分解计划!$A:$N,COLUMN()-4,FALSE) | K36: =VLOOKUP(填写页!$C$8,分解计划!$A:$N,COLUMN()-4,FALSE) | L36: =VLOOKUP(填写页!$C$8,分解计划!$A:$N,COLUMN()-4,FALSE) | M36: =VLOOKUP(填写页!$C$8,分解计划!$A:$N,COLUMN()-4,FALSE) | N36: =VLOOKUP(填写页!$C$8,分解计划!$A:$N,COLUMN()-4,FALSE) | ... R36: =VLOOKUP(填写页!$C$8,分解计划!$A:$N,COLUMN()-4,FALSE)
F39: 指标 | G39: 1月 | H39: 2月 | I39: 3月 | J39: 4月 | K39: 5月 | L39: 6月 | M39: 7月 | N39: 8月 | O39: 9月 | P39: 10月 | Q39: 11月 | R39: 12月
F40: 营业收入 | G40: {=IF(COLUMN(G2:R2)<=COLUMN(G2)+MATCH(填写页!$A$1,$G$1:$R$1,0)-1,G2:R2,NA())} | H40: 63.822824 | I40: 80.56083 | J40: 0 | K40: #N/A | L40: #N/A | M40: #N/A | N40: #N/A | O40: #N/A | P40: #N/A | Q40: #N/A | R40: #N/A
F41: GOP | G41: {=IF(COLUMN(G3:R3)<=COLUMN(G3)+MATCH(填写页!$A$1,$G$1:$R$1,0)-1,G3:R3,NA())} | H41: -38.670642 | I41: -1.727057 | J41: 0 | K41: #N/A | L41: #N/A | M41: #N/A | N41: #N/A | O41: #N/A | P41: #N/A | Q41: #N/A | R41: #N/A
F42: 经营活动净现金流 | G42: {=IF(COLUMN(G4:R4)<=COLUMN(G4)+MATCH(填写页!$A$1,$G$1:$R$1,0)-1,G4:R4,NA())} | H42: -47.233397 | I42: -17.259462 | J42: 0 | K42: #N/A | L42: #N/A | M42: #N/A | N42: #N/A | O42: #N/A | P42: #N/A | Q42: #N/A | R42: #N/A
F43: 经营支出小计 | G43: {=IF(COLUMN(G5:R5)<=COLUMN(G5)+MATCH(填写页!$A$1,$G$1:$R$1,0)-1,G5:R5,NA())} | H43: 102.38878 | I43: 82.703909 | J43: 0 | K43: #N/A | L43: #N/A | M43: #N/A | N43: #N/A | O43: #N/A | P43: #N/A | Q43: #N/A | R43: #N/A

Sheet 盛唐融信
A1: 类别 | B1: 序号 | C1: 指标 | D1: 年度目标 | E1: 实际达成 | F1: 年度目标达成率 | G1: 1月 | H1: 2月 | I1: 3月 | J1: 4月 | K1: 5月 | L1: 6月 | M1: 7月 | N1: 8月 | O1: 9月 | P1: 10月 | Q1: 11月 | R1: 12月
A2: 经营指标 | B2: 1 | C2: 营业收入 | D2: {=INDEX(年度计划!E2:M18,,MATCH(填写页!C9,年度计划!E1:M1,0))} | E2: =SUM(G2:R2) | F2: =IFERROR(MAX(1+(E2-D2)/ABS(D2),0),) | G2: 32.620633 | H2: 19.682364 | I2: 31.674955 | J2: 23.451862
B3: 2 | C3: 扣非利润 | D3: 127.81801 | E3: =SUM(G3:R3) | F3: =IFERROR(MAX(1+(E3-D3)/ABS(D3),0),) | G3: 4.668735 | H3: -3.913125 | I3: 6.554692 | J3: 1.440771
B4: 3 | C4: 经营活动净现金流 | D4: 91.154908 | E4: =SUM(G4:R4) | F4: =IFERROR(MAX(1+(E4-D4)/ABS(D4),0),) | G4: -18.43919 | H4: 29.445458 | I4: 58.445817 | J4: 13.167888
A5: 财务指标 | B5: 4 | C5: 经营支出 | D5: 653.17324 | E5: =SUM(G5:R5) | F5: =IFERROR(MAX(1+(E5-D5)/ABS(D5),0),) | G5: 32.36311 | H5: 28.197865 | I5: 27.942634 | J5: 27.738821 | K5: 0 | L5: 0 | M5: 0 | N5: 0 | O5: 0 | P5: 0 | Q5: 0 | R5: 0
B6: 4.1 | C6: 固定费用 | D6: 268.70086 | E6: =SUM(G6:R6) | F6: =IFERROR(MAX(1+(E6-D6)/ABS(D6),0),) | G6: 21.927277 | H6: 19.824103 | I6: 19.711548 | J6: 19.787052 | K6: 0 | L6: 0 | M6: 0 | N6: 0 | O6: 0 | P6: 0 | Q6: 0 | R6: 0
B7: 4.1.1 | C7: 人力费用 | D7: 195.0858 | E7: =SUM(G7:R7) | F7: =IFERROR(MAX(1+(E7-D7)/ABS(D7),0),) | G7: 16.761363 | H7: 15.891363 | I7: 15.811363 | J7: 16.311363
B8: 4.1.2 | C8: 日常费用 | D8: 73.615064 | E8: =SUM(G8:R8) | F8: =IFERROR(MAX(1+(E8-D8)/ABS(D8),0),) | G8: 5.165914 | H8: 3.93274 | I8: 3.900185 | J8: 3.475689
B9: 4.2 | C9: 变动费用 | D9: 384.47237 | E9: =SUM(G9:R9) | F9: =IFERROR(MAX(1+(E9-D9)/ABS(D9),0),) | G9: 10.435833 | H9: 8.373762 | I9: 8.231086 | J9: 7.951769 | K9: 0 | L9: 0 | M9: 0 | N9: 0 | O9: 0 | P9: 0 | Q9: 0 | R9: 0
B10: 4.2.1 | C10: 经营变动费用 | D10: 81.588744 | E10: =SUM(G10:R10) | F10: =IFERROR(MAX(1+(E10-D10)/ABS(D10),0),) | G10: 6.921186 | H10: 6.621186 | I10: 6.621186 | J10: 6.781186
B11: 4.2.2 | C11: 营业成本 | D11: 302.88363 | E11: =SUM(G11:R11) | F11: =IFERROR(MAX(1+(E11-D11)/ABS(D11),0),) | G11: 3.514647 | H11: 1.752576 | I11: 1.6099 | J11: 1.170583
B12: 5 | C12: 资本性支出 | D12: 0 | E12: =SUM(G12:R12) | F12: =IFERROR(MAX(1+(E12-D12)/ABS(D12),0),)
A13: 业务指标 | B13: 6 | C13: 期末出租率/月均入住率 | D13: 0 | E13: =SUM(G13:R13) | F13: =IFERROR(MAX(1+(E13-D13)/ABS(D13),0),)
B14: 7 | C14: 回款率 | D14: 0 | E14: =SUM(G14:R14) | F14: =IFERROR(MAX(1+(E14-D14)/ABS(D14),0),)
B15: 8 | C15: OTA网络评价 | D15: 0 | E15: =SUM(G15:R15) | F15: =IFERROR(MAX(1+(E15-D15)/ABS(D15),0),)
B16: 9 | C16: 规模保费 | D16: 862 | E16: =SUM(G16:R16) | F16: =IFERROR(MAX(1+(E16-D16)/ABS(D16),0),) | G16: 7.1105 | H16: 0
B17: 10 | C17: 13月继续率 | D17: 0 | E17: =AVERAGE(G17:R17) | F17: =IFERROR(MAX(1+(E17-D17)/ABS(D17),0),) | G17: 0.9875 | H17: 0.9818 | I17: 0.9271 | J17: 0.9168
B18: 11 | C18: 25月继续率 | D18: 0 | F18: =IFERROR(MAX(1+(E18-D18)/ABS(D18),0),) | G18: 0.9512 | H18: 0.9667 | I18: 0.9749 | J18: 0.9774
C19: 2025年实际 | D19: 年度目标 | E19: 实际达成 | F19: 达成率 | G19: 1月 | H19: 2月 | I19: 3月 | J19: 4月 | K19: 5月 | L19: 6月 | M19: 7月 | N19: 8月 | O19: 9月 | P19: 10月 | Q19: 11月 | R19: 12月
C20: 营业收入 | D20: 654.52407 | E20: 585.65702 | F20: 0.89478301 | G20: 106.32089 | H20: 42.534918 | I20: 75.209191 | J20: 32.272233 | K20: 43.14 | L20: 47.282986 | M20: 52.31881 | N20: 40.126594 | O20: 41.531773 | P20: 32.941035 | Q20: 27.427461 | R20: 44.551139
C21: 扣非利润 | D21: 100.50955 | E21: 127.76386 | F21: 1.2711614 | G21: 33.950856 | H21: 9.153241 | I21: 9.384558 | J21: -3.248022 | K21: 13.541398 | L21: 16.918366 | M21: 24.363209 | N21: -1.192556 | O21: 15.58985 | P21: 7.94342 | Q21: -3.200815 | R21: 4.560352
C22: 经营活动净现金流 | D22: 101.74491 | E22: 189.9048 | F22: 1.8664795 | G22: 34.440909 | H22: -14.043867 | I22: 91.110914 | J22: -41.876819 | K22: 49.533206 | L22: -2.470594 | M22: 20.40532 | N22: 34.410863 | O22: 4.269568 | P22: -16.61999 | Q22: 33.075863 | R22: -2.330576
C23: 经营支出小计 | D23: 612.46818 | E23: 485.30363 | F23: 0.79237362 | G23: 80.387025 | H23: 35.797499 | I23: 54.469118 | J23: 39.964103 | K23: 34.50411 | L23: 36.96709 | M23: 32.896531 | N23: 45.733149 | O23: 24.802285 | P23: 29.297178 | Q23: 27.721059 | R23: 42.764483
C24: 固定费用 | D24: 295.66181 | E24: 289.24517 | F24: 0.97829736 | G24: 21.8829 | H24: 21.19739 | I24: 22.329717 | J24: 30.202661 | K24: 25.716073 | L24: 25.592248 | M24: 21.49094 | N24: 21.358005 | O24: 20.362721 | P24: 21.049006 | Q24: 22.444414 | R24: 35.619093
C25: 人力费用 | D25: 190.90912 | E25: 201.09572 | F25: 1.0533583 | G25: 16.893039 | H25: 15.411923 | I25: 16.092382 | J25: 24.227064 | K25: 16.907164 | L25: 15.707141 | M25: 15.782381 | N25: 15.791071 | O25: 16.811363 | P25: 15.851947 | Q25: 15.811363 | R25: 15.80888
C26: 日常费用 | D26: 104.75268 | E26: 88.14945 | F26: 0.84150063 | G26: 4.989861 | H26: 5.785467 | I26: 6.237335 | J26: 5.975597 | K26: 8.808909 | L26: 9.885107 | M26: 5.708559 | N26: 5.566934 | O26: 3.551358 | P26: 5.197059 | Q26: 6.633051 | R26: 19.810213
C27: 变动费用 | D27: 316.80637 | E27: 196.05846 | F27: 0.61885897 | G27: 58.504125 | H27: 14.600109 | I27: 32.139401 | J27: 9.761442 | K27: 8.788037 | L27: 11.374842 | M27: 11.405591 | N27: 24.375144 | O27: 4.439564 | P27: 8.248172 | Q27: 5.276645 | R27: 7.14539
C28: 经营变动费用 | D28: 77.798938 | E28: 81.579116 | F28: 1.0485891 | G28: 6.815 | H28: 6.495 | I28: 6.955 | J28: 7.6844 | K28: 6.9276 | L28: 6.655 | M28: 6.621186 | N28: 6.621186 | O28: 6.941186 | P28: 6.621186 | Q28: 6.621186 | R28: 6.621186
C29: 营业成本 | D29: 239.00743 | E29: 114.47935 | F29: 0.47897819 | G29: 51.689125 | H29: 8.105109 | I29: 25.184401 | J29: 2.077042 | K29: 1.860437 | L29: 4.719842 | M29: 4.784405 | N29: 17.753958 | O29: -2.501622 | P29: 1.626986 | Q29: -1.344541 | R29: 0.524204
C30: 资本性支出 | D30: 0.75 | E30: 0.354162 | F30: 0.472216 | G30: 0.20916 | H30: 0 | N30: 0.145002
F33: 指标 | G33: 1月 | H33: 2月 | I33: 3月 | J33: 4月 | K33: 5月 | L33: 6月 | M33: 7月 | N33: 8月 | O33: 9月 | P33: 10月 | Q33: 11月 | R33: 12月
F34: 营业收入 | G34: {=IF(COLUMN(G2:R2)<=COLUMN(G2)+MATCH(填写页!$A$1,$G$1:$R$1,0)-1,G2:R2,NA())} | H34: 19.682364 | I34: 31.674955 | J34: 0 | K34: #N/A | L34: #N/A | M34: #N/A | N34: #N/A | O34: #N/A | P34: #N/A | Q34: #N/A | R34: #N/A
F35: 同期营收 | G35: =G20 | H35: =H20 | I35: =I20 | J35: =J20 | K35: =K20 | L35: =L20 | M35: =M20 | N35: =N20 | ... R35: =R20
F36: 营收分解计划 | G36: =VLOOKUP(填写页!$C$9,分解计划!$A:$N,COLUMN()-4,FALSE) | H36: =VLOOKUP(填写页!$C$9,分解计划!$A:$N,COLUMN()-4,FALSE) | I36: =VLOOKUP(填写页!$C$9,分解计划!$A:$N,COLUMN()-4,FALSE) | J36: =VLOOKUP(填写页!$C$9,分解计划!$A:$N,COLUMN()-4,FALSE) | K36: =VLOOKUP(填写页!$C$9,分解计划!$A:$N,COLUMN()-4,FALSE) | L36: =VLOOKUP(填写页!$C$9,分解计划!$A:$N,COLUMN()-4,FALSE) | M36: =VLOOKUP(填写页!$C$9,分解计划!$A:$N,COLUMN()-4,FALSE) | N36: =VLOOKUP(填写页!$C$9,分解计划!$A:$N,COLUMN()-4,FALSE) | ... R36: =VLOOKUP(填写页!$C$9,分解计划!$A:$N,COLUMN()-4,FALSE)
F39: 指标 | G39: 1月 | H39: 2月 | I39: 3月 | J39: 4月 | K39: 5月 | L39: 6月 | M39: 7月 | N39: 8月 | O39: 9月 | P39: 10月 | Q39: 11月 | R39: 12月
F40: 营业收入 | G40: {=IF(COLUMN(G2:R2)<=COLUMN(G2)+MATCH(填写页!$A$1,$G$1:$R$1,0)-1,G2:R2,NA())} | H40: 19.682364 | I40: 31.674955 | J40: 0 | K40: #N/A | L40: #N/A | M40: #N/A | N40: #N/A | O40: #N/A | P40: #N/A | Q40: #N/A | R40: #N/A
F41: 扣非利润 | G41: {=IF(COLUMN(G3:R3)<=COLUMN(G3)+MATCH(填写页!$A$1,$G$1:$R$1,0)-1,G3:R3,NA())} | H41: -3.913125 | I41: 6.554692 | J41: 0 | K41: #N/A | L41: #N/A | M41: #N/A | N41: #N/A | O41: #N/A | P41: #N/A | Q41: #N/A | R41: #N/A
F42: 经营活动净现金流 | G42: {=IF(COLUMN(G4:R4)<=COLUMN(G4)+MATCH(填写页!$A$1,$G$1:$R$1,0)-1,G4:R4,NA())} | H42: 29.445458 | I42: 58.445817 | J42: 0 | K42: #N/A | L42: #N/A | M42: #N/A | N42: #N/A | O42: #N/A | P42: #N/A | Q42: #N/A | R42: #N/A
F43: 经营支出小计 | G43: {=IF(COLUMN(G5:R5)<=COLUMN(G5)+MATCH(填写页!$A$1,$G$1:$R$1,0)-1,G5:R5,NA())} | H43: 28.197865 | I43: 27.942634 | J43: 0 | K43: #N/A | L43: #N/A | M43: #N/A | N43: #N/A | O43: #N/A | P43: #N/A | Q43: #N/A | R43: #N/A

Sheet 君康经纪
A1: 类别 | B1: 序号 | C1: 指标 | D1: 年度目标 | E1: 实际达成 | F1: 年度目标达成率 | G1: 1月 | H1: 2月 | I1: 3月 | J1: 4月 | K1: 5月 | L1: 6月 | M1: 7月 | N1: 8月 | O1: 9月 | P1: 10月 | Q1: 11月 | R1: 12月
A2: 经营指标 | B2: 1 | C2: 营业收入 | D2: {=INDEX(年度计划!E2:M18,,MATCH(填写页!C10,年度计划!E1:M1,0))} | E2: =SUM(G2:R2) | F2: =IFERROR(MAX(1+(E2-D2)/ABS(D2),0),) | G2: 21.123507 | H2: 5.293431 | I2: 8.220388 | J2: 8.25769
B3: 2 | C3: 扣非利润 | D3: -19.043753 | E3: =SUM(G3:R3) | F3: =IFERROR(MAX(1+(E3-D3)/ABS(D3),0),) | G3: -32.5747 | H3: -39.343258 | I3: -9.372579 | J3: -26.324295
B4: 3 | C4: 经营活动净现金流 | D4: 178.18975 | E4: =SUM(G4:R4) | F4: =IFERROR(MAX(1+(E4-D4)/ABS(D4),0),) | G4: -24.505483 | H4: 0.032856 | I4: -56.605711 | J4: -21.829094
A5: 财务指标 | B5: 4 | C5: 经营支出 | D5: 591.07578 | E5: =SUM(G5:R5) | F5: =IFERROR(MAX(1+(E5-D5)/ABS(D5),0),) | G5: 45.380984 | H5: 36.885018 | I5: 32.425914 | J5: 34.207451 | K5: 0 | L5: 0 | M5: 0 | N5: 0 | O5: 0 | P5: 0 | Q5: 0 | R5: 0
B6: 4.1 | C6: 固定费用 | D6: 365.6486 | E6: =SUM(G6:R6) | F6: =IFERROR(MAX(1+(E6-D6)/ABS(D6),0),) | G6: 27.527153 | H6: 23.919152 | I6: 25.396004 | J6: 25.454185 | K6: 0 | L6: 0 | M6: 0 | N6: 0 | O6: 0 | P6: 0 | Q6: 0 | R6: 0
B7: 4.1.1 | C7: 人力费用 | D7: 202.52624 | E7: =SUM(G7:R7) | F7: =IFERROR(MAX(1+(E7-D7)/ABS(D7),0),) | G7: 16.043974 | H7: 16.218865 | I7: 16.063923 | J7: 16.102655
B8: 4.1.2 | C8: 日常费用 | D8: 163.12237 | E8: =SUM(G8:R8) | F8: =IFERROR(MAX(1+(E8-D8)/ABS(D8),0),) | G8: 11.483179 | H8: 7.700287 | I8: 9.332081 | J8: 9.35153
B9: 4.2 | C9: 变动费用 | D9: 225.42717 | E9: =SUM(G9:R9) | F9: =IFERROR(MAX(1+(E9-D9)/ABS(D9),0),) | G9: 17.853831 | H9: 12.965866 | I9: 7.02991 | J9: 8.753266 | K9: 0 | L9: 0 | M9: 0 | N9: 0 | O9: 0 | P9: 0 | Q9: 0 | R9: 0
B10: 4.2.1 | C10: 经营变动费用 | D10: 78.066998 | E10: =SUM(G10:R10) | F10: =IFERROR(MAX(1+(E10-D10)/ABS(D10),0),) | G10: 6.187104 | H10: 6.257674 | I10: 6.187104 | J10: 6.187104
B11: 4.2.2 | C11: 营业成本 | D11: 147.36017 | E11: =SUM(G11:R11) | F11: =IFERROR(MAX(1+(E11-D11)/ABS(D11),0),) | G11: 11.666727 | H11: 6.708192 | I11: 0.842806 | J11: 2.566162
B12: 5 | C12: 资本性支出 | D12: 0 | E12: =SUM(G12:R12) | F12: =IFERROR(MAX(1+(E12-D12)/ABS(D12),0),) | G12: 0 | H12: 0 | I12: 0 | J12: 0 | K12: 0 | L12: 0 | M12: 0 | N12: 0
A13: 业务指标 | B13: 6 | C13: 期末出租率/月均入住率 | D13: 0 | E13: =SUM(G13:R13) | F13: =IFERROR(MAX(1+(E13-D13)/ABS(D13),0),)
B14: 7 | C14: 回款率 | D14: 0 | E14: =SUM(G14:R14) | F14: =IFERROR(MAX(1+(E14-D14)/ABS(D14),0),)
B15: 8 | C15: OTA网络评价 | D15: 0 | E15: =SUM(G15:R15) | F15: =IFERROR(MAX(1+(E15-D15)/ABS(D15),0),)
B16: 9 | C16: 规模保费 | D16: 2790 | E16: =SUM(G16:R16) | F16: =IFERROR(MAX(1+(E16-D16)/ABS(D16),0),) | G16: 100 | H16: 0.51 | I16: 1.34 | J16: 0.2
B17: 10 | C17: 13月继续率 | D17: 0 | E17: =AVERAGE(G17:R17) | F17: =IFERROR(MAX(1+(E17-D17)/ABS(D17),0),) | G17: 1 | H17: 1 | I17: 1 | J17: 1
B18: 11 | C18: 25月继续率 | D18: 0 | E18: =AVERAGE(G18:R18) | F18: =IFERROR(MAX(1+(E18-D18)/ABS(D18),0),) | G18: 1 | H18: 1 | I18: 1 | J18: 1
C19: 2025年实际 | D19: 年度目标 | E19: 实际达成 | F19: 达成率 | G19: 1月 | H19: 2月 | I19: 3月 | J19: 4月 | K19: 5月 | L19: 6月 | M19: 7月 | N19: 8月 | O19: 9月 | P19: 10月 | Q19: 11月 | R19: 12月
C20: 营业收入 | D20: 344.09755 | E20: 208.41382 | F20: 0.60568237 | G20: 16.512047 | H20: 14.980842 | I20: 28.14216 | J20: 27.797814 | K20: 21.950714 | L20: 18.660004 | M20: 12.630675 | N20: 27.603272 | O20: 10.559486 | P20: 16.441937 | Q20: 7.291591 | R20: 5.843275
C21: 扣非利润 | D21: -405.84764 | E21: -376.40158 | F21: 1.0725545 | G21: -37.127919 | H21: -43.098125 | I21: -48.522369 | J21: -18.018945 | K21: -23.965343 | L21: -28.270824 | M21: -29.652354 | N21: -14.132058 | O21: -29.947352 | P21: -26.29058 | Q21: -27.488973 | R21: -49.88674
C22: 经营活动净现金流 | D22: -99.173959 | E22: -65.773094 | F22: 1.3367907 | G22: -20.902717 | H22: -33.64597 | I22: 9.820275 | J22: -12.917457 | K22: -12.778475 | L22: 23.84787 | M22: -7.150763 | N22: 9.189605 | O22: -11.551064 | P22: -26.842033 | Q22: 31.707455 | R22: -14.54982
C23: 经营支出小计 | D23: 664.30591 | E23: 509.25018 | F23: 0.76658987 | G23: 45.212057 | H23: 50.166473 | I23: 67.717151 | J23: 37.139526 | K23: 36.832164 | L23: 38.119566 | M23: 33.176338 | N23: 32.732474 | O23: 31.79779 | P23: 33.674261 | Q23: 52.334561 | R23: 50.347821
C24: 固定费用 | D24: 468.6804 | E24: 405.00117 | F24: 0.86413081 | G24: 33.898573 | H24: 38.60473 | I24: 59.35212 | J24: 26.005085 | K24: 29.318677 | L24: 31.288873 | M24: 26.204439 | N24: 25.108283 | O24: 25.072744 | P24: 26.338534 | Q24: 40.594361 | R24: 43.214754
C25: 人力费用 | D25: 208.94 | E25: 208.87649 | F25: 0.99969604 | G25: 16.306 | H25: 16.4468 | I25: 15.9156 | J25: 16.069 | K25: 16.0204 | L25: 15.412 | M25: 16.0062 | N25: 16.3364 | O25: 16.202975 | P25: 16.2186 | Q25: 31.954901 | R25: 15.987614
C26: 日常费用 | D26: 259.7404 | E26: 196.12468 | F26: 0.75507962 | G26: 17.592573 | H26: 22.15793 | I26: 43.43652 | J26: 9.936085 | K26: 13.298277 | L26: 15.876873 | M26: 10.198239 | N26: 8.771883 | O26: 8.869769 | P26: 10.119934 | Q26: 8.63946 | R26: 27.22714
C27: 变动费用 | D27: 195.62551 | E27: 104.24901 | F27: 0.5329009 | G27: 11.313484 | H27: 11.561743 | I27: 8.365031 | J27: 11.134441 | K27: 7.513487 | L27: 6.830693 | M27: 6.971899 | N27: 7.624191 | O27: 6.725046 | P27: 7.335727 | Q27: 11.7402 | R27: 7.133067
C28: 经营变动费用 | D28: 79.03 | E28: 83.44052 | F28: 1.0558082 | G28: 7.7246 | H28: 7.7951 | I28: 6.3206 | J28: 6.1486 | K28: 6.3912 | L28: 6.32 | M28: 6.3656 | N28: 6.4362 | O28: 6.365618 | P28: 6.443328 | Q28: 10.868677 | R28: 6.260997
C29: 营业成本 | D29: 116.59551 | E29: 20.808489 | F29: 0.17846733 | G29: 3.588884 | H29: 3.766643 | I29: 2.044431 | J29: 4.985841 | K29: 1.122287 | L29: 0.510693 | M29: 0.606299 | N29: 1.187991 | O29: 0.359428 | P29: 0.892399 | Q29: 0.871523 | R29: 0.87207
C30: 资本性支出 | D30: 0 | E30: 0 | F30: 0 | G30: 0 | H30: 0 | I30: 0 | J30: 0 | K30: 0 | L30: 0 | M30: 0 | N30: 0
F33: 指标 | G33: 1月 | H33: 2月 | I33: 3月 | J33: 4月 | K33: 5月 | L33: 6月 | M33: 7月 | N33: 8月 | O33: 9月 | P33: 10月 | Q33: 11月 | R33: 12月
F34: 营业收入 | G34: {=IF(COLUMN(G2:R2)<=COLUMN(G2)+MATCH(填写页!$A$1,$G$1:$R$1,0)-1,G2:R2,NA())} | H34: 5.293431 | I34: 8.220388 | J34: 0 | K34: #N/A | L34: #N/A | M34: #N/A | N34: #N/A | O34: #N/A | P34: #N/A | Q34: #N/A | R34: #N/A
F35: 同期营收 | G35: =G20 | H35: =H20 | I35: =I20 | J35: =J20 | K35: =K20 | L35: =L20 | M35: =M20 | N35: =N20 | ... R35: =R20
F36: 营收分解计划 | G36: =VLOOKUP(填写页!$C$10,分解计划!$A:$N,COLUMN()-4,FALSE) | H36: =VLOOKUP(填写页!$C$10,分解计划!$A:$N,COLUMN()-4,FALSE) | I36: =VLOOKUP(填写页!$C$10,分解计划!$A:$N,COLUMN()-4,FALSE) | J36: =VLOOKUP(填写页!$C$10,分解计划!$A:$N,COLUMN()-4,FALSE) | K36: =VLOOKUP(填写页!$C$10,分解计划!$A:$N,COLUMN()-4,FALSE) | L36: =VLOOKUP(填写页!$C$10,分解计划!$A:$N,COLUMN()-4,FALSE) | M36: =VLOOKUP(填写页!$C$10,分解计划!$A:$N,COLUMN()-4,FALSE) | N36: =VLOOKUP(填写页!$C$10,分解计划!$A:$N,COLUMN()-4,FALSE) | ... R36: =VLOOKUP(填写页!$C$10,分解计划!$A:$N,COLUMN()-4,FALSE)
F39: 指标 | G39: 1月 | H39: 2月 | I39: 3月 | J39: 4月 | K39: 5月 | L39: 6月 | M39: 7月 | N39: 8月 | O39: 9月 | P39: 10月 | Q39: 11月 | R39: 12月
F40: 营业收入 | G40: {=IF(COLUMN(G2:R2)<=COLUMN(G2)+MATCH(填写页!$A$1,$G$1:$R$1,0)-1,G2:R2,NA())} | H40: 5.293431 | I40: 8.220388 | J40: 0 | K40: #N/A | L40: #N/A | M40: #N/A | N40: #N/A | O40: #N/A | P40: #N/A | Q40: #N/A | R40: #N/A
F41: 扣非利润 | G41: {=IF(COLUMN(G3:R3)<=COLUMN(G3)+MATCH(填写页!$A$1,$G$1:$R$1,0)-1,G3:R3,NA())} | H41: -39.343258 | I41: -9.372579 | J41: 0 | K41: #N/A | L41: #N/A | M41: #N/A | N41: #N/A | O41: #N/A | P41: #N/A | Q41: #N/A | R41: #N/A
F42: 经营活动净现金流 | G42: {=IF(COLUMN(G4:R4)<=COLUMN(G4)+MATCH(填写页!$A$1,$G$1:$R$1,0)-1,G4:R4,NA())} | H42: 0.032856 | I42: -56.605711 | J42: 0 | K42: #N/A | L42: #N/A | M42: #N/A | N42: #N/A | O42: #N/A | P42: #N/A | Q42: #N/A | R42: #N/A
F43: 经营支出小计 | G43: {=IF(COLUMN(G5:R5)<=COLUMN(G5)+MATCH(填写页!$A$1,$G$1:$R$1,0)-1,G5:R5,NA())} | H43: 36.885018 | I43: 32.425914 | J43: 0 | K43: #N/A | L43: #N/A | M43: #N/A | N43: #N/A | O43: #N/A | P43: #N/A | Q43: #N/A | R43: #N/A

Sheet 北京联谊
A1: 项目 | B1: 项目 | C1: 年度目标 | D1: 实际达成 | E1: 达成率/执行率 | F1: 1月实际 | G1: 2月实际 | H1: 3月实际 | I1: 4月实际 | J1: 5月实际 | K1: 6月实际 | L1: 7月实际 | M1: 8月实际 | N1: 9月实际 | O1: 10月实际 | P1: 11月实际 | Q1: 12月实际 | S1: 项目(7月末) | T1: 期末余额 (万元) | U1: 期初余额 (万元)
A2: 经营指标 | B2: 营业收入 | D2: =SUM(F2:Q2) -> 0 | E2: =IFERROR(D2/C2,0) -> 0 | S2: 资产总额 | T2: 127728.63 | U2: 128213.48
B3: EBITDA | D3: =SUM(F3:Q3) -> 0 | E3: =IFERROR(D3/C3,0) -> 0 | S3: 负债总额 | T3: 2468.25 | U3: 2648.8802
B4: 经营活动净现金流 | D4: =SUM(F4:Q4) -> 0 | E4: =IFERROR(D4/C4,0) -> 0 | S4: 所有者权益 | T4: 125260.38 | U4: 125564.6
A5: 财务指标 | B5: 经营支出小计 | D5: =SUM(F5:Q5) -> 0 | E5: =IFERROR(D5/C5,0) -> 0 | S5: 资产负债率 | T5: =T3/T2 -> 0.019324171 | U5: =U3/U2 -> 0.02065992
B6: -固定费用 | D6: =SUM(F6:Q6) -> 0 | E6: =IFERROR(D6/C6,0) -> 0 | S6: 资金余额 | T6: 98.698916 | U6: 1041.9134
B7: --人力费用 | D7: =SUM(F7:Q7) -> 0 | E7: =IFERROR(D7/C7,0) -> 0
B8: --日常费用 | D8: =SUM(F8:Q8) -> 0 | E8: =IFERROR(D8/C8,0) -> 0
B9: -变动费用 | D9: =SUM(F9:Q9) -> 0 | E9: =IFERROR(D9/C9,0) -> 0
B10: --经营变动费用 | D10: =SUM(F10:Q10) -> 0 | E10: =IFERROR(D10/C10,0) -> 0
B11: --营业成本 | D11: =SUM(F11:Q11) -> 0 | E11: =IFERROR(D11/C11,0) -> 0
B12: 资本性支出 | D12: =SUM(F12:Q12) -> 0 | E12: =IFERROR(D12/C12,0) -> 0
B13: 折旧摊销 | D13: =SUM(F13:Q13) -> 0 | E13: =IFERROR(D13/C13,0) -> 0
B14: 财务费用 | D14: =SUM(F14:Q14) -> 0 | E14: =IFERROR(D14/C14,0) -> 0
B15: 税金及附加 | D15: =SUM(F15:Q15) -> 0 | E15: =IFERROR(D15/C15,0) -> 0
A18: 成本结构 | B18: 项目 | C18: 年度目标 | D18: 实际达成
B19: 人力费用 | C19: =C7 -> 0 | D19: =D7 -> 0
B20: 日常费用 | C20: =C8 -> 0 | D20: =D8 -> 0
B21: 经营变动费用 | C21: =C10 -> 0 | D21: =D10 -> 0
B22: 营业成本 | C22: =C11 -> 0 | D22: =D11 -> 0
B23: 变动费用率 | C23: =C9/C2 -> #DIV/0! | D23: =D9/D2 -> #DIV/0!
B24: 项目 | C24: 年度目标 | D24: 实际达成
B25: 人力费用占比 | C25: =C19/C$5 -> #DIV/0! | D25: =D19/D$5 -> #DIV/0!
B26: 日常费用占比 | C26: =C20/C$5 -> #DIV/0! | D26: =D20/D$5 -> #DIV/0!
B27: 经营变动费用占比 | C27: =C21/C$5 -> #DIV/0! | D27: =D21/D$5 -> #DIV/0!
B28: 营业成本占比 | C28: =C22/C$5 -> #DIV/0! | D28: =D22/D$5 -> #DIV/0!
B29: 利润率 | C29: =C3/C2 -> #DIV/0! | D29: =D3/D2 -> #DIV/0!

Sheet 上海联杰
A1: 项目 | B1: 项目 | C1: 年度目标 | D1: 实际达成 | E1: 达成率/执行率 | F1: 1月实际 | G1: 2月实际 | H1: 3月实际 | I1: 4月实际 | J1: 5月实际 | K1: 6月实际 | L1: 7月实际 | M1: 8月实际 | N1: 9月实际 | O1: 10月实际 | P1: 11月实际 | Q1: 12月实际 | S1: 项目(7月末) | T1: 期末余额 (万元) | U1: 期初余额 (万元)
A2: 经营指标 | B2: 营业收入 | D2: =SUM(F2:Q2) -> 0 | E2: =IFERROR(D2/C2,0) -> 0 | S2: 资产总额 | T2: 257265.03 | U2: 257332.65
B3: EBITDA | D3: =SUM(F3:Q3) -> 0 | E3: =IFERROR(D3/C3,0) -> 0 | S3: 负债总额 | T3: 303.51528 | U3: 332.03
B4: 经营活动净现金流 | D4: =SUM(F4:Q4) -> 0 | E4: =IFERROR(D4/C4,0) -> 0 | S4: 所有者权益 | T4: 256961.51 | U4: 257000.62
A5: 财务指标 | B5: 经营支出小计 | D5: =SUM(F5:Q5) -> 0 | E5: =IFERROR(D5/C5,0) -> 0 | S5: 资产负债率 | T5: =T3/T2 -> 0.0011797767 | U5: =U3/U2 -> 0.0012902754
B6: -固定费用 | D6: =SUM(F6:Q6) -> 0 | E6: =IFERROR(D6/C6,0) -> 0 | S6: 资金余额 | T6: 41.316679 | U6: 39.464616
B7: --人力费用 | D7: =SUM(F7:Q7) -> 0 | E7: =IFERROR(D7/C7,0) -> 0
B8: --日常费用 | D8: =SUM(F8:Q8) -> 0 | E8: =IFERROR(D8/C8,0) -> 0
B9: -变动费用 | D9: =SUM(F9:Q9) -> 0 | E9: =IFERROR(D9/C9,0) -> 0
B10: --经营变动费用 | D10: =SUM(F10:Q10) -> 0 | E10: =IFERROR(D10/C10,0) -> 0
B11: --营业成本 | D11: =SUM(F11:Q11) -> 0 | E11: =IFERROR(D11/C11,0) -> 0
B12: 资本性支出 | D12: =SUM(F12:Q12) -> 0 | E12: =IFERROR(D12/C12,0) -> 0
B13: 折旧摊销 | D13: =SUM(F13:Q13) -> 0 | E13: =IFERROR(D13/C13,0) -> 0
B14: 财务费用 | D14: =SUM(F14:Q14) -> 0 | E14: =IFERROR(D14/C14,0) -> 0
B15: 税金及附加 | D15: =SUM(F15:Q15) -> 0 | E15: =IFERROR(D15/C15,0) -> 0
A18: 成本结构 | B18: 项目 | C18: 年度目标 | D18: 实际达成
B19: 人力费用 | C19: =C7 -> 0 | D19: =D7 -> 0
B20: 日常费用 | C20: =C8 -> 0 | D20: =D8 -> 0
B21: 经营变动费用 | C21: =C10 -> 0 | D21: =D10 -> 0
B22: 营业成本 | C22: =C11 -> 0 | D22: =D11 -> 0
B23: 变动费用率 | C23: =C9/C2 -> #DIV/0! | D23: =D9/D2 -> #DIV/0!
B24: 项目 | C24: 年度目标 | D24: 实际达成
B25: 人力费用占比 | C25: =C19/C$5 -> #DIV/0! | D25: =D19/D$5 -> #DIV/0!
B26: 日常费用占比 | C26: =C20/C$5 -> #DIV/0! | D26: =D20/D$5 -> #DIV/0!
B27: 经营变动费用占比 | C27: =C21/C$5 -> #DIV/0! | D27: =D21/D$5 -> #DIV/0!
B28: 营业成本占比 | C28: =C22/C$5 -> #DIV/0! | D28: =D22/D$5 -> #DIV/0!
B29: 利润率 | C29: =C3/C2 -> #DIV/0! | D29: =D3/D2 -> #DIV/0!
