Workbook

Sheet 指标统计
A1: 福晟钱隆广场（福建）商业管理有限公司2026年经营指标统计表
A2: 指标 | B2: 项目 | C2: 2026年预算 | D2: 2026年执行情况 | P2: 2026年实际 | Q2: 执行率 | R2: 指标说明 | S2: 备注
D3: 1月 | E3: 2月 | F3: 3月 | G3: 4月 | H3: 5月 | I3: 6月 | J3: 7月 | K3: 8月 | L3: 9月 | M3: 10月 | N3: 11月 | O3: 12月
A4: 经营指标 | B4: 营业收入 | C4: =预算执行汇总!B4 -> 8453.02 | D4: {=预算执行汇总!C4:N4} -> 519.18593 | E4: 532.97154 | F4: 517.25193 | G4: 925.59221 | H4: 0 | I4: 0 | J4: 0 | K4: 0 | L4: 0 | M4: 0 | N4: 0 | O4: 0 | P4: =SUM(D4:O4) -> 2495.0016 | Q4: =IFERROR((P4-C4)/ABS(C4)+1,) -> 0.29516097
B5: EBITDA/GOP/扣非净利润 | C5: =预算执行汇总!B18 -> 4484.05 | D5: =预算执行汇总!C18 -> 390.20747 | E5: =预算执行汇总!D18 -> 411.25073 | F5: =预算执行汇总!E18 -> 392.54369 | G5: =预算执行汇总!F18 -> 544.20433 | H5: =预算执行汇总!G18 -> 0 | I5: =预算执行汇总!H18 -> 0 | J5: =预算执行汇总!I18 -> 0 | ... O5: =预算执行汇总!N18 -> 0 | P5: =SUM(D5:O5) -> 1738.2062 | Q5: =IFERROR(P5/C5,) -> 0.38764202 | R5: EBITDA（商写适用）/GOP（酒店适用）/扣非净利润（保险中介适用）
B6: 经营活动净现金流 | C6: 1168.95 | D6: 501.21573 | E6: 344.23802 | F6: 920.00434 | G6: 323.90208 | P6: =SUM(D6:O6) -> 2089.3602 | Q6: =IFERROR(P6/C6,) -> 1.787382 | S6: 其中专项法律诉讼费支出9万元、仲量物业监管账户结算收入50万元，应予以考核剔除。
A7: 财务指标 | B7: 经营支出小计 | C7: {=预算执行汇总!B5:B12} -> 2883.81 | D7: {=预算执行汇总!C5:N12} -> 36.843094 | E7: 30.590467 | F7: 37.133258 | G7: 293.51709 | H7: 0 | I7: 0 | J7: 0 | K7: 0 | L7: 0 | M7: 0 | N7: 0 | O7: 0 | P7: =SUM(D7:O7) -> 398.08391 | Q7: =IFERROR(P7/C7,) -> 0.13804096
B8: 固定费用 | C8: 2810.76 | D8: 35.522094 | E8: 26.958767 | F8: 27.930338 | G8: 293.04035 | H8: 0 | I8: 0 | J8: 0 | K8: 0 | L8: 0 | M8: 0 | N8: 0 | O8: 0 | P8: =SUM(D8:O8) -> 383.45155 | Q8: =IFERROR(P8/C8,) -> 0.13642273
B9: 人力费用 | C9: 295.69 | D9: 22.264558 | E9: 22.38943 | F9: 22.990727 | G9: 21.718834 | H9: 0 | I9: 0 | J9: 0 | K9: 0 | L9: 0 | M9: 0 | N9: 0 | O9: 0 | P9: =SUM(D9:O9) -> 89.363549 | Q9: =IFERROR(P9/C9,) -> 0.3022204
B10: 日常费用 | C10: 2515.07 | D10: 13.257536 | E10: 4.569337 | F10: 4.939611 | G10: 271.32152 | H10: 0 | I10: 0 | J10: 0 | K10: 0 | L10: 0 | M10: 0 | N10: 0 | O10: 0 | P10: =SUM(D10:O10) -> 294.088 | Q10: =IFERROR(P10/C10,) -> 0.11693034
B11: 变动费用 | C11: 73.05 | D11: 1.321 | E11: 3.6317 | F11: 9.20292 | G11: 0.47674 | H11: 0 | I11: 0 | J11: 0 | K11: 0 | L11: 0 | M11: 0 | N11: 0 | O11: 0 | P11: =SUM(D11:O11) -> 14.63236 | Q11: =IFERROR(P11/C11,) -> 0.20030609
B12: 经营变动费用 | C12: 73.05 | D12: 1.321 | E12: 3.6317 | F12: 9.20292 | G12: 0.47674 | H12: 0 | I12: 0 | J12: 0 | K12: 0 | L12: 0 | M12: 0 | N12: 0 | O12: 0 | P12: =SUM(D12:O12) -> 14.63236 | Q12: =IFERROR(P12/C12,) -> 0.20030609
B13: 营业成本 | C13: 0 | D13: 0 | E13: 0 | F13: 0 | G13: 0 | H13: 0 | I13: 0 | J13: 0 | K13: 0 | L13: 0 | M13: 0 | N13: 0 | O13: 0 | P13: =SUM(D13:O13) -> 0 | Q13: =IFERROR(P13/C13,) -> 0
B14: 资本性支出 | C14: 226.85 | D14: 0 | E14: 0 | F14: 0 | G14: 0 | H14: 0 | I14: 0 | J14: 0 | K14: 0 | L14: 0 | M14: 0 | N14: 0 | O14: 0 | P14: =SUM(D14:O14) -> 0 | Q14: =IFERROR(P14/C14,) -> 0
A15: 业务指标 | B15: 期末出租率/月均入住率 | C15: 0.5715 | D15: 0.55115714 | E15: 0.55115714 | F15: 0.56022555 | G15: 0.56950452 | P15: =IFERROR(AVERAGE(D15:O15),) -> 0.55801109 | Q15: =IFERROR(P15/C15,) -> 0.97639736 | R15: 期末出租率(商写适用)/月均入住率(酒店适用)
B16: 回款率 | C16: 0.95 | D16: 0.8144 | E16: 0.70045088 | F16: 0.95453013 | G16: 0.96088298 | P16: =IFERROR(AVERAGE(D16:O16),) -> 0.85756599 | Q16: =IFERROR(P16/C16,) -> 0.90270105 | R16: 商写及酒店适用
B17: OTA网络评价 | P17: {=IFERROR(INDEX(D17:O17,0,MATCH(9.99999999999999E+307,D17:O17)),)} -> 0 | Q17: =IFERROR(P17/C17,) -> 0 | R17: 酒店适用
B18: 期交规保 | P18: {=IFERROR(INDEX(D18:O18,0,MATCH(9.99999999999999E+307,D18:O18)),)} -> 0 | Q18: =IFERROR(P18/C18,) -> 0 | R18: 保险中介适用
B19: 13月继续率 | P19: {=IFERROR(INDEX(D19:O19,0,MATCH(9.99999999999999E+307,D19:O19)),)} -> 0 | Q19: =IFERROR(P19/C19,) -> 0 | R19: 保险中介适用
B20: 25月继续率 | P20: {=IFERROR(INDEX(D20:O20,0,MATCH(9.99999999999999E+307,D20:O20)),)} -> 0 | Q20: =IFERROR(P20/C20,) -> 0 | R20: 保险中介适用
A21: 备注 | B21: EBITDA=营业收入-固定费用-变动费用-税金及附加+利息收入
B22: GOP=营业收入-固定费用-变动费用-财务费用（不含利息费用）
B23: 需填列单元格

Sheet 预算执行汇总
A1: 福晟钱隆广场（福建）商业管理有限公司2026年预算执行情况汇总表
A2: 项目 | B2: 2026年预算 | C2: 2026年执行情况 | O2: 2026年实际 | P2: 执行率
C3: 1月 | D3: 2月 | E3: 3月 | F3: 4月 | G3: 5月 | H3: 6月 | I3: 7月 | J3: 8月 | K3: 9月 | L3: 10月 | M3: 11月 | N3: 12月
A4: 营业收入 | B4: 8453.02 | C4: 519.18593 | D4: 532.97154 | E4: 517.25193 | F4: 925.59221 | O4: =SUM(C4:N4) -> 2495.0016 | P4: =IFERROR(O4/B4,) -> 0.29516097
A5: 经营支出小计 | B5: =B6+B9 -> 2883.81 | C5: =C6+C9 -> 36.843094 | D5: =D6+D9 -> 30.590467 | E5: =E6+E9 -> 37.133258 | F5: =F6+F9 -> 293.51709 | G5: =G6+G9 -> 0 | H5: =H6+H9 -> 0 | I5: =I6+I9 -> 0 | ... N5: =N6+N9 -> 0 | O5: =SUM(C5:N5) -> 398.08391 | P5: =IFERROR(O5/B5,) -> 0.13804096
A6: 固定费用 | B6: =费用预算执行明细!B4 -> 2810.76 | C6: =费用预算执行明细!C4 -> 35.522094 | D6: =费用预算执行明细!D4 -> 26.958767 | E6: =费用预算执行明细!E4 -> 27.930338 | F6: =费用预算执行明细!F4 -> 293.04035 | G6: =费用预算执行明细!G4 -> 0 | H6: =费用预算执行明细!H4 -> 0 | I6: =费用预算执行明细!I4 -> 0 | ... N6: =费用预算执行明细!N4 -> 0 | O6: =SUM(C6:N6) -> 383.45155 | P6: =IFERROR(O6/B6,) -> 0.13642273
A7: 人力费用 | B7: =费用预算执行明细!B5 -> 295.69 | C7: =费用预算执行明细!C5 -> 22.264558 | D7: =费用预算执行明细!D5 -> 22.38943 | E7: =费用预算执行明细!E5 -> 22.990727 | F7: =费用预算执行明细!F5 -> 21.718834 | G7: =费用预算执行明细!G5 -> 0 | H7: =费用预算执行明细!H5 -> 0 | I7: =费用预算执行明细!I5 -> 0 | ... N7: =费用预算执行明细!N5 -> 0 | O7: =SUM(C7:N7) -> 89.363549 | P7: =IFERROR(O7/B7,) -> 0.3022204
A8: 日常费用 | B8: =费用预算执行明细!B15 -> 2515.07 | C8: =费用预算执行明细!C15 -> 13.257536 | D8: =费用预算执行明细!D15 -> 4.569337 | E8: =费用预算执行明细!E15 -> 4.939611 | F8: =费用预算执行明细!F15 -> 271.32152 | G8: =费用预算执行明细!G15 -> 0 | H8: =费用预算执行明细!H15 -> 0 | I8: =费用预算执行明细!I15 -> 0 | ... N8: =费用预算执行明细!N15 -> 0 | O8: =SUM(C8:N8) -> 294.088 | P8: =IFERROR(O8/B8,) -> 0.11693034
A9: 变动费用 | B9: =费用预算执行明细!B43 -> 73.05 | C9: =费用预算执行明细!C43 -> 1.321 | D9: =费用预算执行明细!D43 -> 3.6317 | E9: =费用预算执行明细!E43 -> 9.20292 | F9: =费用预算执行明细!F43 -> 0.47674 | G9: =费用预算执行明细!G43 -> 0 | H9: =费用预算执行明细!H43 -> 0 | I9: =费用预算执行明细!I43 -> 0 | ... N9: =费用预算执行明细!N43 -> 0 | O9: =SUM(C9:N9) -> 14.63236 | P9: =IFERROR(O9/B9,) -> 0.20030609
A10: 经营变动费用支出 | B10: =费用预算执行明细!B44 -> 73.05 | C10: =费用预算执行明细!C44 -> 1.321 | D10: =费用预算执行明细!D44 -> 3.6317 | E10: =费用预算执行明细!E44 -> 9.20292 | F10: =费用预算执行明细!F44 -> 0.47674 | G10: =费用预算执行明细!G44 -> 0 | H10: =费用预算执行明细!H44 -> 0 | I10: =费用预算执行明细!I44 -> 0 | ... N10: =费用预算执行明细!N44 -> 0 | O10: =SUM(C10:N10) -> 14.63236 | P10: =IFERROR(O10/B10,) -> 0.20030609
A11: 营业成本支出 | B11: =费用预算执行明细!B69 -> 0 | C11: =费用预算执行明细!C69 -> 0 | D11: =费用预算执行明细!D69 -> 0 | E11: =费用预算执行明细!E69 -> 0 | F11: =费用预算执行明细!F69 -> 0 | G11: =费用预算执行明细!G69 -> 0 | H11: =费用预算执行明细!H69 -> 0 | I11: =费用预算执行明细!I69 -> 0 | ... N11: =费用预算执行明细!N69 -> 0 | O11: =SUM(C11:N11) -> 0 | P11: =IFERROR(O11/B11,) -> 0
A12: 资本性支出 | B12: =资本性支出计划与执行!G15 -> 226.85 | O12: =SUM(C12:N12) -> 0 | P12: =IFERROR(O12/B12,) -> 0
A13: 折旧摊销 | B13: =费用预算执行明细!B84 -> 6418.29 | C13: =费用预算执行明细!C84 -> 525.3673 | D13: =费用预算执行明细!D84 -> 525.35623 | E13: =费用预算执行明细!E84 -> 525.35622 | F13: =费用预算执行明细!F84 -> 525.3346 | G13: =费用预算执行明细!G84 -> 0 | H13: =费用预算执行明细!H84 -> 0 | I13: =费用预算执行明细!I84 -> 0 | ... N13: =费用预算执行明细!N84 -> 0 | O13: =SUM(C13:N13) -> 2101.4143 | P13: =IFERROR(O13/B13,) -> 0.32741031
A14: 财务费用 | B14: =费用预算执行明细!B89 -> -48.8 | C14: =费用预算执行明细!C89 -> 0.074883 | D14: =费用预算执行明细!D89 -> 0.060006 | E14: =费用预算执行明细!E89 -> -5.619242 | F14: =费用预算执行明细!F89 -> -0.226914 | G14: =费用预算执行明细!G89 -> 0 | H14: =费用预算执行明细!H89 -> 0 | I14: =费用预算执行明细!I89 -> 0 | ... N14: =费用预算执行明细!N89 -> 0 | O14: =SUM(C14:N14) -> -5.711267 | P14: =IFERROR(O14/B14,) -> 0.11703416
A15: 税金及附加 | B15: 1135.16 | C15: 92.135372 | D15: 91.130343 | E15: 93.274217 | F15: 88.180801 | O15: =SUM(C15:N15) -> 364.72073 | P15: =IFERROR(O15/B15,) -> 0.32129456
A16: 变动费用率 | B16: =IFERROR(B9/B4,) -> 0.0086418818 | C16: =IFERROR(C9/C4,) -> 0.0025443679 | D16: =IFERROR(D9/D4,) -> 0.00681406 | E16: =IFERROR(E9/E4,) -> 0.017791949 | F16: =IFERROR(F9/F4,) -> 0.00051506483 | G16: =IFERROR(G9/G4,) -> 0 | H16: =IFERROR(H9/H4,) -> 0 | I16: =IFERROR(I9/I4,) -> 0 | ... O16: =IFERROR(O9/O4,) -> 0.0058646696
A18: EBITDA | B18: =B4-B6-B9-B15+费用预算执行明细!B91 -> 4484.05 | C18: =C4-C6-C9-C15+费用预算执行明细!C91 -> 390.20747 | D18: =D4-D6-D9-D15+费用预算执行明细!D91 -> 411.25073 | E18: =E4-E6-E9-E15+费用预算执行明细!E91 -> 392.54369 | F18: =F4-F6-F9-F15+费用预算执行明细!F91 -> 544.20433 | G18: =G4-G6-G9-G15+费用预算执行明细!G91 -> 0 | H18: =H4-H6-H9-H15+费用预算执行明细!H91 -> 0 | I18: =I4-I6-I9-I15+费用预算执行明细!I91 -> 0 | ... O18: =O4-O6-O9-O15+费用预算执行明细!O91 -> 1738.2062 | P18: =IFERROR(O18/B18,) -> 0.38764202
A19: GOP | P19: =IFERROR(O19/B19,) -> 0
A21: 备注 | B21: EBITDA=营业收入-固定费用-变动费用-税金及附加+利息收入
B22: GOP=营业收入-固定费用-变动费用-财务费用（不含利息费用）
B23: 需填列单元格

Sheet 费用预算执行明细
A1: 福晟钱隆广场（福建）商业管理有限公司2026年预算执行情况明细表
A2: 项目 | B2: 2026年预算 | C2: 2026年预算执行情况 | O2: 2026年实际 | P2: 执行率
C3: 1月 | D3: 2月 | E3: 3月 | F3: 4月 | G3: 5月 | H3: 6月 | I3: 7月 | J3: 8月 | K3: 9月 | L3: 10月 | M3: 11月 | N3: 12月
A4: 固定费用 | B4: =B5+B15 -> 2810.76 | C4: =C5+C15 -> 35.522094 | D4: =D5+D15 -> 26.958767 | E4: =E5+E15 -> 27.930338 | F4: =F5+F15 -> 293.04035 | G4: =G5+G15 -> 0 | H4: =H5+H15 -> 0 | I4: =I5+I15 -> 0 | ... N4: =N5+N15 -> 0 | O4: =SUM(C4:N4) -> 383.45155 | P4: =IFERROR(O4/B4,) -> 0.13642273
A5: 人力费用支出合计 | B5: =SUM(B6:B14) -> 295.69 | C5: =SUM(C6:C14) -> 22.264558 | D5: =SUM(D6:D14) -> 22.38943 | E5: =SUM(E6:E14) -> 22.990727 | F5: =SUM(F6:F14) -> 21.718834 | G5: =SUM(G6:G14) -> 0 | H5: =SUM(H6:H14) -> 0 | I5: =SUM(I6:I14) -> 0 | ... N5: =SUM(N6:N14) -> 0 | O5: =SUM(C5:N5) -> 89.363549 | P5: =IFERROR(O5/B5,) -> 0.3022204
A6: 固定工资 | B6: 206.99 | C6: 16.087636 | D6: 16.162368 | E6: 16.44499 | F6: 15.643336 | O6: =SUM(C6:N6) -> 64.33833 | P6: =IFERROR(O6/B6,) -> 0.3108282
A7: 奖金 | B7: 0 | C7: 0 | D7: 0 | E7: 0 | F7: 0 | G7: 0 | H7: 0 | I7: 0 | J7: 0 | K7: 0 | L7: 0 | M7: 0 | N7: 0 | O7: =SUM(C7:N7) -> 0 | P7: =IFERROR(O7/B7,) -> 0
A8: 福利费 | B8: 10.09 | C8: 0.30229 | D8: 0.35243 | E8: 0.7525 | F8: 0.282261 | O8: =SUM(C8:N8) -> 1.689481 | P8: =IFERROR(O8/B8,) -> 0.16744113
A9: 五险一金 | B9: 77.51 | C9: 5.874632 | D9: 5.874632 | E9: 5.793237 | F9: 5.793237 | O9: =SUM(C9:N9) -> 23.335738 | P9: =IFERROR(O9/B9,) -> 0.30106745
A10: 残疾人就业保障金 | B10: 0 | C10: 0 | D10: 0 | E10: 0 | F10: 0 | G10: 0 | H10: 0 | I10: 0 | J10: 0 | K10: 0 | L10: 0 | M10: 0 | N10: 0 | O10: =SUM(C10:N10) -> 0 | P10: =IFERROR(O10/B10,) -> 0
A11: 工会经费 | B11: 0 | C11: 0 | D11: 0 | E11: 0 | F11: 0 | G11: 0 | H11: 0 | I11: 0 | J11: 0 | K11: 0 | L11: 0 | M11: 0 | N11: 0 | O11: =SUM(C11:N11) -> 0 | P11: =IFERROR(O11/B11,) -> 0
A12: 辞退补偿 | B12: 0 | C12: 0 | D12: 0 | E12: 0 | F12: 0 | G12: 0 | H12: 0 | I12: 0 | J12: 0 | K12: 0 | L12: 0 | M12: 0 | N12: 0 | O12: =SUM(C12:N12) -> 0 | P12: =IFERROR(O12/B12,) -> 0
A13: 招聘费 | B13: 1.1 | C13: 0 | D13: 0 | E13: 0 | F13: 0 | G13: 0 | H13: 0 | I13: 0 | J13: 0 | K13: 0 | L13: 0 | M13: 0 | N13: 0 | O13: =SUM(C13:N13) -> 0 | P13: =IFERROR(O13/B13,) -> 0
A14: 其他人力费用 | B14: 0 | C14: 0 | D14: 0 | E14: 0 | F14: 0 | G14: 0 | H14: 0 | I14: 0 | J14: 0 | K14: 0 | L14: 0 | M14: 0 | N14: 0 | O14: =SUM(C14:N14) -> 0 | P14: =IFERROR(O14/B14,) -> 0
A15: 日常费用支出合计 | B15: =B16+B22 -> 2515.07 | C15: =C16+C22 -> 13.257536 | D15: =D16+D22 -> 4.569337 | E15: =E16+E22 -> 4.939611 | F15: =F16+F22 -> 271.32152 | G15: =G16+G22 -> 0 | H15: =H16+H22 -> 0 | I15: =I16+I22 -> 0 | ... N15: =N16+N22 -> 0 | O15: =SUM(C15:N15) -> 294.088 | P15: =IFERROR(O15/B15,) -> 0.11693034
A16: 职场费用合计 | B16: =SUM(B17:B21) -> 2177.17 | C16: =SUM(C17:C21) -> 4 | D16: =SUM(D17:D21) -> 4 | E16: =SUM(E17:E21) -> 4 | F16: =SUM(F17:F21) -> 268.04116 | G16: =SUM(G17:G21) -> 0 | H16: =SUM(H17:H21) -> 0 | I16: =SUM(I17:I21) -> 0 | ... N16: =SUM(N17:N21) -> 0 | O16: =SUM(C16:N16) -> 280.04116 | P16: =IFERROR(O16/B16,) -> 0.12862623
A17: 物业费 | B17: =48+2129.17 -> 2177.17 | C17: 4 | D17: 4 | E17: 4 | F17: =4+264.041162 -> 268.04116 | G17: 0 | H17: 0 | I17: 0 | J17: 0 | K17: 0 | L17: 0 | M17: 0 | N17: 0 | O17: =SUM(C17:N17) -> 280.04116 | P17: =IFERROR(O17/B17,) -> 0.12862623
A18: 取暖供冷费 | B18: 0 | C18: 0 | D18: 0 | E18: 0 | F18: 0 | G18: 0 | H18: 0 | I18: 0 | J18: 0 | K18: 0 | L18: 0 | M18: 0 | N18: 0 | O18: =SUM(C18:N18) -> 0 | P18: =IFERROR(O18/B18,) -> 0
A19: 房屋租赁费 | B19: 0 | C19: 0 | D19: 0 | E19: 0 | F19: 0 | G19: 0 | H19: 0 | I19: 0 | J19: 0 | K19: 0 | L19: 0 | M19: 0 | N19: 0 | O19: =SUM(C19:N19) -> 0 | P19: =IFERROR(O19/B19,) -> 0
A20: 水电费 | B20: 0 | C20: 0 | D20: 0 | E20: 0 | F20: 0 | G20: 0 | H20: 0 | I20: 0 | J20: 0 | K20: 0 | L20: 0 | M20: 0 | N20: 0 | O20: =SUM(C20:N20) -> 0 | P20: =IFERROR(O20/B20,) -> 0
A21: 财产保险费 | B21: 0 | C21: 0 | D21: 0 | E21: 0 | F21: 0 | G21: 0 | H21: 0 | I21: 0 | J21: 0 | K21: 0 | L21: 0 | M21: 0 | N21: 0 | O21: =SUM(C21:N21) -> 0 | P21: =IFERROR(O21/B21,) -> 0
A22: 办公费用合计 | B22: =SUM(B23:B42) -> 337.9 | C22: =SUM(C23:C42) -> 9.257536 | D22: =SUM(D23:D42) -> 0.569337 | E22: =SUM(E23:E42) -> 0.939611 | F22: =SUM(F23:F42) -> 3.280355 | G22: =SUM(G23:G42) -> 0 | H22: =SUM(H23:H42) -> 0 | I22: =SUM(I23:I42) -> 0 | ... N22: =SUM(N23:N42) -> 0 | O22: =SUM(C22:N22) -> 14.046839 | P22: =IFERROR(O22/B22,) -> 0.041570994
A23: 差旅费 | B23: 5 | C23: 0 | D23: 0.2637 | E23: 0 | F23: 0 | G23: 0 | H23: 0 | I23: 0 | J23: 0 | K23: 0 | L23: 0 | M23: 0 | N23: 0 | O23: =SUM(C23:N23) -> 0.2637 | P23: =IFERROR(O23/B23,) -> 0.05274
A24: 业务招待费 | B24: 8.2 | C24: 0.051196 | D24: 0.0823 | E24: 0.6817 | F24: 0.557 | G24: 0 | H24: 0 | I24: 0 | J24: 0 | K24: 0 | L24: 0 | M24: 0 | N24: 0 | O24: =SUM(C24:N24) -> 1.372196 | P24: =IFERROR(O24/B24,) -> 0.16734098
A25: 邮寄费 | B25: 0.6 | C25: 0.0402 | D25: 0.0322 | E25: 0.0198 | F25: 0.02 | G25: 0 | H25: 0 | I25: 0 | J25: 0 | K25: 0 | L25: 0 | M25: 0 | N25: 0 | O25: =SUM(C25:N25) -> 0.1122 | P25: =IFERROR(O25/B25,) -> 0.187
A26: 汽车费 | B26: 2 | C26: 0.04904 | D26: 0 | E26: 0.039261 | F26: 0.066235 | G26: 0 | H26: 0 | I26: 0 | J26: 0 | K26: 0 | L26: 0 | M26: 0 | N26: 0 | O26: =SUM(C26:N26) -> 0.154536 | P26: =IFERROR(O26/B26,) -> 0.077268
A27: 低值易耗品 | B27: 0 | C27: 0 | D27: 0 | E27: 0 | F27: 0 | G27: 0 | H27: 0 | I27: 0 | J27: 0 | K27: 0 | L27: 0 | M27: 0 | N27: 0 | O27: =SUM(C27:N27) -> 0 | P27: =IFERROR(O27/B27,) -> 0
A28: 设备修理费 | B28: 0 | C28: 0 | D28: 0 | E28: 0 | F28: 0 | G28: 0 | H28: 0 | I28: 0 | J28: 0 | K28: 0 | L28: 0 | M28: 0 | N28: 0 | O28: =SUM(C28:N28) -> 0 | P28: =IFERROR(O28/B28,) -> 0
A29: 通讯费 | B29: 0.6 | C29: 0.0371 | D29: 0.0371 | E29: 0.0371 | F29: 0.03712 | G29: 0 | H29: 0 | I29: 0 | J29: 0 | K29: 0 | L29: 0 | M29: 0 | N29: 0 | O29: =SUM(C29:N29) -> 0.14842 | P29: =IFERROR(O29/B29,) -> 0.24736667
A30: 市内交通费 | B30: 0.2 | C30: 0 | D30: 0 | E30: 0 | F30: 0 | G30: 0 | H30: 0 | I30: 0 | J30: 0 | K30: 0 | L30: 0 | M30: 0 | N30: 0 | O30: =SUM(C30:N30) -> 0 | P30: =IFERROR(O30/B30,) -> 0
A31: 办公杂费 | B31: 2.55 | C31: 0.08 | D31: 0.154037 | E31: 0.0118 | F31: 0.2 | G31: 0 | H31: 0 | I31: 0 | J31: 0 | K31: 0 | L31: 0 | M31: 0 | N31: 0 | O31: =SUM(C31:N31) -> 0.445837 | P31: =IFERROR(O31/B31,) -> 0.17483804
A32: 会议费 | B32: 1.15 | C32: 0 | D32: 0 | E32: 0.14995 | F32: 0 | G32: 0 | H32: 0 | I32: 0 | J32: 0 | K32: 0 | L32: 0 | M32: 0 | N32: 0 | O32: =SUM(C32:N32) -> 0.14995 | P32: =IFERROR(O32/B32,) -> 0.1303913
A33: 培训费 | B33: 0 | C33: 0 | D33: 0 | E33: 0 | F33: 0 | G33: 0 | H33: 0 | I33: 0 | J33: 0 | K33: 0 | L33: 0 | M33: 0 | N33: 0 | O33: =SUM(C33:N33) -> 0 | P33: =IFERROR(O33/B33,) -> 0
A34: 广告宣传费 | B34: 0 | C34: 0 | D34: 0 | E34: 0 | F34: 0 | G34: 0 | H34: 0 | I34: 0 | J34: 0 | K34: 0 | L34: 0 | M34: 0 | N34: 0 | O34: =SUM(C34:N34) -> 0 | P34: =IFERROR(O34/B34,) -> 0
... A42: 其他 | B42: 0 | C42: 0 | D42: 0 | E42: 0 | F42: 0 | G42: 0 | H42: 0 | I42: 0 | J42: 0 | K42: 0 | L42: 0 | M42: 0 | N42: 0 | O42: =SUM(C42:N42) -> 0 | P42: =IFERROR(O42/B42,) -> 0
A43: 变动费用 | B43: =B44+B69 -> 73.05 | C43: =C44+C69 -> 1.321 | D43: =D44+D69 -> 3.6317 | E43: =E44+E69 -> 9.20292 | F43: =F44+F69 -> 0.47674 | G43: =G44+G69 -> 0 | H43: =H44+H69 -> 0 | I43: =I44+I69 -> 0 | ... N43: =N44+N69 -> 0 | O43: =SUM(C43:N43) -> 14.63236 | P43: =IFERROR(O43/B43,) -> 0.20030609
A44: 经营变动费用支出合计 | B44: =B45+B66 -> 73.05 | C44: =C45+C66 -> 1.321 | D44: =D45+D66 -> 3.6317 | E44: =E45+E66 -> 9.20292 | F44: =F45+F66 -> 0.47674 | G44: =G45+G66 -> 0 | H44: =H45+H66 -> 0 | I44: =I45+I66 -> 0 | ... N44: =N45+N66 -> 0 | O44: =SUM(C44:N44) -> 14.63236 | P44: =IFERROR(O44/B44,) -> 0.20030609
A45: 业务费用合计 | B45: =SUM(B46:B65) -> 32.7 | C45: =SUM(C46:C65) -> 1.321 | D45: =SUM(D46:D65) -> 3.6317 | E45: =SUM(E46:E65) -> 0.5856 | F45: =SUM(F46:F65) -> 0.47674 | G45: =SUM(G46:G65) -> 0 | H45: =SUM(H46:H65) -> 0 | I45: =SUM(I46:I65) -> 0 | ... N45: =SUM(N46:N65) -> 0 | O45: =SUM(C45:N45) -> 6.01504 | P45: =IFERROR(O45/B45,) -> 0.18394618
A46: 差旅费 | B46: 0 | C46: 0 | D46: 0 | E46: 0 | F46: 0 | G46: 0 | H46: 0 | I46: 0 | J46: 0 | K46: 0 | L46: 0 | M46: 0 | N46: 0 | O46: =SUM(C46:N46) -> 0 | P46: =IFERROR(O46/B46,) -> 0
A47: 业务招待费 | B47: 5 | C47: 0.1354 | D47: 0.8653 | E47: 0.5856 | F47: 0.47674 | G47: 0 | H47: 0 | I47: 0 | J47: 0 | K47: 0 | L47: 0 | M47: 0 | N47: 0 | O47: =SUM(C47:N47) -> 2.06304 | P47: =IFERROR(O47/B47,) -> 0.412608
A48: 邮寄费 | B48: 0 | C48: 0 | D48: 0 | E48: 0 | F48: 0 | G48: 0 | H48: 0 | I48: 0 | J48: 0 | K48: 0 | L48: 0 | M48: 0 | N48: 0 | O48: =SUM(C48:N48) -> 0 | P48: =IFERROR(O48/B48,) -> 0
A49: 汽车费 | B49: 0 | C49: 0 | D49: 0 | E49: 0 | F49: 0 | G49: 0 | H49: 0 | I49: 0 | J49: 0 | K49: 0 | L49: 0 | M49: 0 | N49: 0 | O49: =SUM(C49:N49) -> 0 | P49: =IFERROR(O49/B49,) -> 0
A50: 通讯费 | B50: 0 | C50: 0 | D50: 0 | E50: 0 | F50: 0 | G50: 0 | H50: 0 | I50: 0 | J50: 0 | K50: 0 | L50: 0 | M50: 0 | N50: 0 | O50: =SUM(C50:N50) -> 0 | P50: =IFERROR(O50/B50,) -> 0
A51: 市内交通费 | B51: 0.2 | C51: 0 | D51: 0 | E51: 0 | F51: 0 | G51: 0 | H51: 0 | I51: 0 | J51: 0 | K51: 0 | L51: 0 | M51: 0 | N51: 0 | O51: =SUM(C51:N51) -> 0 | P51: =IFERROR(O51/B51,) -> 0
A52: 办公杂费 | B52: 0 | C52: 0 | D52: 0 | E52: 0 | F52: 0 | G52: 0 | H52: 0 | I52: 0 | J52: 0 | K52: 0 | L52: 0 | M52: 0 | N52: 0 | O52: =SUM(C52:N52) -> 0 | P52: =IFERROR(O52/B52,) -> 0
A53: 会议费 | B53: 0 | C53: 0 | D53: 0 | E53: 0 | F53: 0 | G53: 0 | H53: 0 | I53: 0 | J53: 0 | K53: 0 | L53: 0 | M53: 0 | N53: 0 | O53: =SUM(C53:N53) -> 0 | P53: =IFERROR(O53/B53,) -> 0
A54: 培训费 | B54: 0 | C54: 0 | D54: 0 | E54: 0 | F54: 0 | G54: 0 | H54: 0 | I54: 0 | J54: 0 | K54: 0 | L54: 0 | M54: 0 | N54: 0 | O54: =SUM(C54:N54) -> 0 | P54: =IFERROR(O54/B54,) -> 0
A55: 广告宣传费 | B55: 19.5 | C55: 1.1856 | D55: 2.7664 | E55: 0 | F55: 0 | G55: 0 | H55: 0 | I55: 0 | J55: 0 | K55: 0 | L55: 0 | M55: 0 | N55: 0 | O55: =SUM(C55:N55) -> 3.952 | P55: =IFERROR(O55/B55,) -> 0.20266667
A56: 咨询服务费 | B56: 0 | C56: 0 | D56: 0 | E56: 0 | F56: 0 | G56: 0 | H56: 0 | I56: 0 | J56: 0 | K56: 0 | L56: 0 | M56: 0 | N56: 0 | O56: =SUM(C56:N56) -> 0 | P56: =IFERROR(O56/B56,) -> 0
A57: 法律诉讼费 | B57: 8 | C57: 0 | D57: 0 | E57: 0 | F57: 0 | G57: 0 | H57: 0 | I57: 0 | J57: 0 | K57: 0 | L57: 0 | M57: 0 | N57: 0 | O57: =SUM(C57:N57) -> 0 | P57: =IFERROR(O57/B57,) -> 0
... A65: 其他 | B65: 0 | C65: 0 | D65: 0 | E65: 0 | F65: 0 | G65: 0 | H65: 0 | I65: 0 | J65: 0 | K65: 0 | L65: 0 | M65: 0 | N65: 0 | O65: =SUM(C65:N65) -> 0 | P65: =IFERROR(O65/B65,) -> 0
A66: 佣金及代理费合计 | B66: =SUM(B67:B68) -> 40.35 | C66: =SUM(C67:C68) -> 0 | D66: =SUM(D67:D68) -> 0 | E66: =SUM(E67:E68) -> 8.61732 | F66: =SUM(F67:F68) -> 0 | G66: =SUM(G67:G68) -> 0 | H66: =SUM(H67:H68) -> 0 | I66: =SUM(I67:I68) -> 0 | ... N66: =SUM(N67:N68) -> 0 | O66: =SUM(C66:N66) -> 8.61732 | P66: =IFERROR(O66/B66,) -> 0.21356431
A67: 销售代理费 | B67: 40.35 | C67: 0 | D67: 0 | E67: 8.61732 | F67: 0 | G67: 0 | H67: 0 | I67: 0 | J67: 0 | K67: 0 | L67: 0 | M67: 0 | N67: 0 | O67: =SUM(C67:N67) -> 8.61732 | P67: =IFERROR(O67/B67,) -> 0.21356431
A68: 销售佣金 | B68: 0 | C68: 0 | D68: 0 | E68: 0 | F68: 0 | G68: 0 | H68: 0 | I68: 0 | J68: 0 | K68: 0 | L68: 0 | M68: 0 | N68: 0 | O68: =SUM(C68:N68) -> 0 | P68: =IFERROR(O68/B68,) -> 0
A69: 营业成本支出合计 | B69: =B70+B76+B81 -> 0 | C69: =C70+C76+C81 -> 0 | D69: =D70+D76+D81 -> 0 | E69: =E70+E76+E81 -> 0 | F69: =F70+F76+F81 -> 0 | G69: =G70+G76+G81 -> 0 | H69: =H70+H76+H81 -> 0 | I69: =I70+I76+I81 -> 0 | ... N69: =N70+N76+N81 -> 0 | O69: =SUM(C69:N69) -> 0 | P69: =IFERROR(O69/B69,) -> 0
A70: 客房成本合计 | B70: =SUM(B71:B75) -> 0 | C70: =SUM(C71:C75) -> 0 | D70: =SUM(D71:D75) -> 0 | E70: =SUM(E71:E75) -> 0 | F70: =SUM(F71:F75) -> 0 | G70: =SUM(G71:G75) -> 0 | H70: =SUM(H71:H75) -> 0 | I70: =SUM(I71:I75) -> 0 | ... N70: =SUM(N71:N75) -> 0 | O70: =SUM(C70:N70) -> 0 | P70: =IFERROR(O70/B70,) -> 0
A71: 客房用品损耗支出 | B71: 0 | C71: 0 | D71: 0 | E71: 0 | F71: 0 | G71: 0 | H71: 0 | I71: 0 | J71: 0 | K71: 0 | L71: 0 | M71: 0 | N71: 0 | O71: =SUM(C71:N71) -> 0 | P71: =IFERROR(O71/B71,) -> 0
A72: 客房水电能源支出 | B72: 0 | C72: 0 | D72: 0 | E72: 0 | F72: 0 | G72: 0 | H72: 0 | I72: 0 | J72: 0 | K72: 0 | L72: 0 | M72: 0 | N72: 0 | O72: =SUM(C72:N72) -> 0 | P72: =IFERROR(O72/B72,) -> 0
A73: 客房布草等物品清洁支出 | B73: 0 | C73: 0 | D73: 0 | E73: 0 | F73: 0 | G73: 0 | H73: 0 | I73: 0 | J73: 0 | K73: 0 | L73: 0 | M73: 0 | N73: 0 | O73: =SUM(C73:N73) -> 0 | P73: =IFERROR(O73/B73,) -> 0
A74: 客房设备维修支出 | B74: 0 | C74: 0 | D74: 0 | E74: 0 | F74: 0 | G74: 0 | H74: 0 | I74: 0 | J74: 0 | K74: 0 | L74: 0 | M74: 0 | N74: 0 | O74: =SUM(C74:N74) -> 0 | P74: =IFERROR(O74/B74,) -> 0
A75: 其他与客房直接相关的支出 | B75: 0 | C75: 0 | D75: 0 | E75: 0 | F75: 0 | G75: 0 | H75: 0 | I75: 0 | J75: 0 | K75: 0 | L75: 0 | M75: 0 | N75: 0 | O75: =SUM(C75:N75) -> 0 | P75: =IFERROR(O75/B75,) -> 0
A76: 餐饮成本合计 | B76: =SUM(B77:B80) -> 0 | C76: =SUM(C77:C80) -> 0 | D76: =SUM(D77:D80) -> 0 | E76: =SUM(E77:E80) -> 0 | F76: =SUM(F77:F80) -> 0 | G76: =SUM(G77:G80) -> 0 | H76: =SUM(H77:H80) -> 0 | I76: =SUM(I77:I80) -> 0 | ... N76: =SUM(N77:N80) -> 0 | O76: =SUM(C76:N76) -> 0 | P76: =IFERROR(O76/B76,) -> 0
A77: 餐饮食材支出 | B77: =SUM(C77:F77) -> 0 | C77: 0 | D77: 0 | E77: 0 | F77: 0 | G77: 0 | H77: 0 | I77: 0 | J77: 0 | K77: 0 | L77: 0 | M77: 0 | N77: 0 | O77: =SUM(C77:N77) -> 0 | P77: =IFERROR(O77/B77,) -> 0
A78: 餐饮水电燃气支出 | B78: =SUM(C78:F78) -> 0 | C78: 0 | D78: 0 | E78: 0 | F78: 0 | G78: 0 | H78: 0 | I78: 0 | J78: 0 | K78: 0 | L78: 0 | M78: 0 | N78: 0 | O78: =SUM(C78:N78) -> 0 | P78: =IFERROR(O78/B78,) -> 0
A79: 餐饮设备维修支出 | B79: =SUM(C79:F79) -> 0 | C79: 0 | D79: 0 | E79: 0 | F79: 0 | G79: 0 | H79: 0 | I79: 0 | J79: 0 | K79: 0 | L79: 0 | M79: 0 | N79: 0 | O79: =SUM(C79:N79) -> 0 | P79: =IFERROR(O79/B79,) -> 0
A80: 其他与餐饮直接相关的支出 | B80: =SUM(C80:F80) -> 0 | C80: 0 | D80: 0 | E80: 0 | F80: 0 | G80: 0 | H80: 0 | I80: 0 | J80: 0 | K80: 0 | L80: 0 | M80: 0 | N80: 0 | O80: =SUM(C80:N80) -> 0 | P80: =IFERROR(O80/B80,) -> 0
A81: 会议成本合计 | B81: =SUM(B82:B83) -> 0 | C81: =SUM(C82:C83) -> 0 | D81: =SUM(D82:D83) -> 0 | E81: =SUM(E82:E83) -> 0 | F81: =SUM(F82:F83) -> 0 | G81: =SUM(G82:G83) -> 0 | H81: =SUM(H82:H83) -> 0 | I81: =SUM(I82:I83) -> 0 | ... N81: =SUM(N82:N83) -> 0 | O81: =SUM(C81:N81) -> 0 | P81: =IFERROR(O81/B81,) -> 0
A82: 会议设备支出 | B82: =SUM(C82:F82) -> 0 | C82: 0 | D82: 0 | E82: 0 | F82: 0 | G82: 0 | H82: 0 | I82: 0 | J82: 0 | K82: 0 | L82: 0 | M82: 0 | N82: 0 | O82: =SUM(C82:N82) -> 0 | P82: =IFERROR(O82/B82,) -> 0
A83: 其他与会议直接相关的支出 | B83: =SUM(C83:F83) -> 0 | C83: 0 | D83: 0 | E83: 0 | F83: 0 | G83: 0 | H83: 0 | I83: 0 | J83: 0 | K83: 0 | L83: 0 | M83: 0 | N83: 0 | O83: =SUM(C83:N83) -> 0 | P83: =IFERROR(O83/B83,) -> 0
A84: 折旧摊销小计 | B84: =SUM(B85:B88) -> 6418.29 | C84: =SUM(C85:C88) -> 525.3673 | D84: =SUM(D85:D88) -> 525.35623 | E84: =SUM(E85:E88) -> 525.35622 | F84: =SUM(F85:F88) -> 525.3346 | G84: =SUM(G85:G88) -> 0 | H84: =SUM(H85:H88) -> 0 | I84: =SUM(I85:I88) -> 0 | ... N84: =SUM(N85:N88) -> 0 | O84: =SUM(C84:N84) -> 2101.4143 | P84: =IFERROR(O84/B84,) -> 0.32741031
A85: 固定资产折旧 | B85: 14.27 | C85: 1.250093 | D85: 1.239023 | E85: 1.239009 | F85: 1.217389 | G85: 0 | H85: 0 | I85: 0 | J85: 0 | K85: 0 | L85: 0 | M85: 0 | N85: 0 | O85: =SUM(C85:N85) -> 4.945514 | P85: =IFERROR(O85/B85,) -> 0.3465672
A86: 无形资产摊销 | B86: 0 | C86: 0 | D86: 0 | E86: 0 | F86: 0 | G86: 0 | H86: 0 | I86: 0 | J86: 0 | K86: 0 | L86: 0 | M86: 0 | N86: 0 | O86: =SUM(C86:N86) -> 0 | P86: =IFERROR(O86/B86,) -> 0
A87: 投资性房地产折旧 | B87: 6382.44 | C87: 524.11721 | D87: 524.11721 | E87: 524.11721 | F87: 524.11721 | G87: 0 | H87: 0 | I87: 0 | J87: 0 | K87: 0 | L87: 0 | M87: 0 | N87: 0 | O87: =SUM(C87:N87) -> 2096.4688 | P87: =IFERROR(O87/B87,) -> 0.32847451
A88: 长期待摊费用摊销 | B88: 21.58 | C88: 0 | D88: 0 | E88: 0 | F88: 0 | G88: 0 | H88: 0 | I88: 0 | J88: 0 | K88: 0 | L88: 0 | M88: 0 | N88: 0 | O88: =SUM(C88:N88) -> 0 | P88: =IFERROR(O88/B88,) -> 0
A89: 财务费用小计 | B89: =B90-B91+B92+B93+B94 -> -48.8 | C89: =C90-C91+C92+C93+C94 -> 0.074883 | D89: =D90-D91+D92+D93+D94 -> 0.060006 | E89: =E90-E91+E92+E93+E94 -> -5.619242 | F89: =F90-F91+F92+F93+F94 -> -0.226914 | G89: =G90-G91+G92+G93+G94 -> 0 | H89: =H90-H91+H92+H93+H94 -> 0 | I89: =I90-I91+I92+I93+I94 -> 0 | ... N89: =N90-N91+N92+N93+N94 -> 0 | O89: =SUM(C89:N89) -> -5.711267 | P89: =IFERROR(O89/B89,) -> 0.11703416
A90: 利息支出 | B90: 0 | C90: 0 | D90: 0 | E90: 0 | F90: 0 | G90: 0 | H90: 0 | I90: 0 | J90: 0 | K90: 0 | L90: 0 | M90: 0 | N90: 0 | O90: =SUM(C90:N90) -> 0 | P90: =IFERROR(O90/B90,) -> 0
A91: 利息收入 | B91: 50 | C91: 0 | D91: 0 | E91: 5.699242 | F91: 0.310009 | G91: 0 | H91: 0 | I91: 0 | J91: 0 | K91: 0 | L91: 0 | M91: 0 | N91: 0 | O91: =SUM(C91:N91) -> 6.009251 | P91: =IFERROR(O91/B91,) -> 0.12018502
A92: 银行手续费 | B92: 1.2 | C92: 0.074883 | D92: 0.060006 | E92: 0.08 | F92: 0.083095 | G92: 0 | H92: 0 | I92: 0 | J92: 0 | K92: 0 | L92: 0 | M92: 0 | N92: 0 | O92: =SUM(C92:N92) -> 0.297984 | P92: =IFERROR(O92/B92,) -> 0.24832
A93: 其他财务费用 | B93: 0 | C93: 0 | D93: 0 | E93: 0 | F93: 0 | G93: 0 | H93: 0 | I93: 0 | J93: 0 | K93: 0 | L93: 0 | M93: 0 | N93: 0 | O93: =SUM(C93:N93) -> 0 | P93: =IFERROR(O93/B93,) -> 0
A94: 担保费 | B94: 0 | C94: 0 | D94: 0 | E94: 0 | F94: 0 | G94: 0 | H94: 0 | I94: 0 | J94: 0 | K94: 0 | L94: 0 | M94: 0 | N94: 0 | O94: =SUM(C94:N94) -> 0 | P94: =IFERROR(O94/B94,) -> 0

Sheet 资本性支出计划与执行
A1: 福晟钱隆广场（福建）商业管理有限公司2026年资本性支出执行情况明细表
A2: 资产类别 | B2: 资产类型 | C2: 资产名称 | D2: 数量 | E2: 单价 | F2: 金额 | G2: 2026年预算 | H2: 2026年实际
A3: 固定资产 | B3: 电器设备 | C3: 空气净化器 | D3: 1 | E3: 0.2 | G3: 0.2 | H3: =F3 -> 0
H4: =F4 -> 0
H5: =F5 -> 0
H6: =F6 -> 0
H7: =F7 -> 0
H8: =F8 -> 0
A9: 其他长期支出 | B9: 长期待摊费用 | C9: 小户型装修改造 | G9: 120 | H9: =F9 -> 0
C10: 2楼装修 | G10: 106.65 | H10: =F10 -> 0
H11: =F11 -> 0
H12: =F12 -> 0
A15: 资本性支出合计 | G15: =SUM(G3:G14) -> 226.85 | H15: =SUM(H3:H14) -> 0
A17: 需填列
