Workbook

Sheet 指标统计
A1: 瑞尔酒店公司2026年经营指标统计表
A2: 指标 | B2: 项目 | C2: 2026年预算 | D2: 2026年执行情况 | P2: 2026年实际 | Q2: 执行率 | R2: 指标说明
D3: 1月 | E3: 2月 | F3: 3月 | G3: 4月 | H3: 5月 | I3: 6月 | J3: 7月 | K3: 8月 | L3: 9月 | M3: 10月 | N3: 11月 | O3: 12月
A4: 经营指标 | B4: 营业收入 | C4: =预算执行汇总!B4 -> 1454.9973 | D4: {=预算执行汇总!C4:N4} -> 78.97726 | E4: 63.822824 | F4: 80.56083 | G4: 96.956248 | H4: 0 | I4: 0 | J4: 0 | K4: 0 | L4: 0 | M4: 0 | N4: 0 | O4: 0 | P4: =SUM(D4:O4) -> 320.31716 | Q4: =IFERROR((P4-C4)/ABS(C4)+1,) -> 0.22014967
B5: EBITDA/GOP/扣非净利润 | C5: =预算执行汇总!B19 -> -55.516737 | D5: =预算执行汇总!C19 -> -52.776259 | E5: =预算执行汇总!D19 -> -38.670642 | F5: =预算执行汇总!E19 -> -1.727057 | G5: =预算执行汇总!F19 -> -13.573026 | H5: =预算执行汇总!G19 -> 0 | I5: =预算执行汇总!H19 -> 0 | J5: =预算执行汇总!I19 -> 0 | ... O5: =预算执行汇总!N19 -> 0 | P5: =SUM(D5:O5) -> -106.74698 | Q5: =IFERROR(P5/C5,) -> 1.9227892 | R5: EBITDA（商写适用）/GOP（酒店适用）/扣非净利润（保险中介适用）
B6: 经营活动净现金流 | C6: -178.55007 | D6: -59.297686 | E6: -47.233397 | F6: -17.259462 | G6: -90.647837 | P6: =SUM(D6:O6) -> -214.43838 | Q6: =IFERROR(P6/C6,) -> 1.2009986
A7: 财务指标 | B7: 经营支出小计 | C7: {=预算执行汇总!B5:B12} -> 1518.434 | D7: {=预算执行汇总!C5:N12} -> 131.62255 | E7: 102.38878 | F7: 82.703909 | G7: 110.36911 | H7: 0 | I7: 0 | J7: 0 | K7: 0 | L7: 0 | M7: 0 | N7: 0 | O7: 0 | P7: =SUM(D7:O7) -> 427.08434 | Q7: =IFERROR(P7/C7,) -> 0.28126632
B8: 固定费用 | C8: 793.4447 | D8: 82.740795 | E8: 54.661567 | F8: 41.604384 | G8: 62.007687 | H8: 0 | I8: 0 | J8: 0 | K8: 0 | L8: 0 | M8: 0 | N8: 0 | O8: 0 | P8: =SUM(D8:O8) -> 241.01443 | Q8: =IFERROR(P8/C8,) -> 0.30375706
B9: 人力费用 | C9: 693.56 | D9: 77.910641 | E9: 52.070162 | F9: 46.482044 | G9: 47.60297 | H9: 0 | I9: 0 | J9: 0 | K9: 0 | L9: 0 | M9: 0 | N9: 0 | O9: 0 | P9: =SUM(D9:O9) -> 224.06582 | Q9: =IFERROR(P9/C9,) -> 0.32306623
B10: 日常费用 | C10: 99.8847 | D10: 4.830154 | E10: 2.591405 | F10: -4.87766 | G10: 14.404717 | H10: 0 | I10: 0 | J10: 0 | K10: 0 | L10: 0 | M10: 0 | N10: 0 | O10: 0 | P10: =SUM(D10:O10) -> 16.948616 | Q10: =IFERROR(P10/C10,) -> 0.1696818
B11: 变动费用 | C11: 724.9893 | D11: 48.881752 | E11: 47.727211 | F11: 41.099525 | G11: 48.361423 | H11: 0 | I11: 0 | J11: 0 | K11: 0 | L11: 0 | M11: 0 | N11: 0 | O11: 0 | P11: =SUM(D11:O11) -> 186.06991 | Q11: =IFERROR(P11/C11,) -> 0.25665194
B12: 经营变动费用 | C12: 225.42 | D12: 14.661237 | E12: 17.69237 | F12: 15.084433 | G12: 20.184048 | H12: 0 | I12: 0 | J12: 0 | K12: 0 | L12: 0 | M12: 0 | N12: 0 | O12: 0 | P12: =SUM(D12:O12) -> 67.622088 | Q12: =IFERROR(P12/C12,) -> 0.29998265
B13: 营业成本 | C13: 499.5693 | D13: 34.220515 | E13: 30.034841 | F13: 26.015092 | G13: 28.177375 | H13: 0 | I13: 0 | J13: 0 | K13: 0 | L13: 0 | M13: 0 | N13: 0 | O13: 0 | P13: =SUM(D13:O13) -> 118.44782 | Q13: =IFERROR(P13/C13,) -> 0.23709988
B14: 资本性支出 | C14: 153.94 | D14: 0 | E14: 0 | F14: 0 | G14: 0 | H14: 0 | I14: 0 | J14: 0 | K14: 0 | L14: 0 | M14: 0 | N14: 0 | O14: 0 | P14: =SUM(D14:O14) -> 0 | Q14: =IFERROR(P14/C14,) -> 0
A15: 业务指标 | B15: 期末出租率/月均入住率 | C15: 0.71 | D15: 0.41286389 | E15: 0.31946864 | F15: 0.59343037 | G15: 0.74512195 | P15: =IFERROR(AVERAGE(D15:O15),) -> 0.51772121 | Q15: =IFERROR(P15/C15,) -> 0.72918481 | R15: 期末出租率(商写适用)/月均入住率(酒店适用)
B16: 回款率 | C16: 0.98 | D16: 0.97824235 | E16: 0.94651203 | F16: 0.89600247 | G16: 0.91666599 | P16: =IFERROR(AVERAGE(D16:O16),) -> 0.93435571 | Q16: =IFERROR(P16/C16,) -> 0.95342419 | R16: 商写及酒店适用
B17: OTA网络评价 | C17: 4.7 | D17: 4.7 | E17: 4.7 | F17: 4.7 | G17: 4.7 | P17: {=IFERROR(INDEX(D17:O17,0,MATCH(9.99999999999999E+307,D17:O17)),)} -> 4.7 | Q17: =IFERROR(P17/C17,) -> 1 | R17: 酒店适用
B18: 期交规保 | P18: {=IFERROR(INDEX(D18:O18,0,MATCH(9.99999999999999E+307,D18:O18)),)} -> 0 | Q18: =IFERROR(P18/C18,) -> 0 | R18: 保险中介适用
B19: 13月继续率 | P19: {=IFERROR(INDEX(D19:O19,0,MATCH(9.99999999999999E+307,D19:O19)),)} -> 0 | Q19: =IFERROR(P19/C19,) -> 0 | R19: 保险中介适用
B20: 25月继续率 | P20: {=IFERROR(INDEX(D20:O20,0,MATCH(9.99999999999999E+307,D20:O20)),)} -> 0 | Q20: =IFERROR(P20/C20,) -> 0 | R20: 保险中介适用
A21: 备注 | B21: EBITDA=营业收入-固定费用-变动费用-税金及附加
B22: GOP=营业收入-固定费用-变动费用-财务费用（不含利息费用）
B23: 需填列单元格

Sheet 预算执行汇总
A1: 瑞尔酒店公司2026年预算执行情况汇总表
A2: 项目 | B2: 2026年预算 | C2: 2026年执行情况 | O2: 2026年实际 | P2: 执行率
C3: 1月 | D3: 2月 | E3: 3月 | F3: 4月 | G3: 5月 | H3: 6月 | I3: 7月 | J3: 8月 | K3: 9月 | L3: 10月 | M3: 11月 | N3: 12月
A4: 营业收入 | B4: 1454.9973 | C4: 78.97726 | D4: 63.822824 | E4: 80.56083 | F4: 96.956248 | O4: =SUM(C4:N4) -> 320.31716 | P4: =IFERROR(O4/B4,) -> 0.22014967
A5: 经营支出小计 | B5: =B6+B9 -> 1518.434 | C5: =C6+C9 -> 131.62255 | D5: =D6+D9 -> 102.38878 | E5: =E6+E9 -> 82.703909 | F5: =F6+F9 -> 110.36911 | G5: =G6+G9 -> 0 | H5: =H6+H9 -> 0 | I5: =I6+I9 -> 0 | ... N5: =N6+N9 -> 0 | O5: =SUM(C5:N5) -> 427.08434 | P5: =IFERROR(O5/B5,) -> 0.28126632
A6: 固定费用 | B6: =费用预算执行明细!B4 -> 793.4447 | C6: =费用预算执行明细!C4 -> 82.740795 | D6: =费用预算执行明细!D4 -> 54.661567 | E6: =费用预算执行明细!E4 -> 41.604384 | F6: =费用预算执行明细!F4 -> 62.007687 | G6: =费用预算执行明细!G4 -> 0 | H6: =费用预算执行明细!H4 -> 0 | I6: =费用预算执行明细!I4 -> 0 | ... N6: =费用预算执行明细!N4 -> 0 | O6: =SUM(C6:N6) -> 241.01443 | P6: =IFERROR(O6/B6,) -> 0.30375706
A7: 人力费用 | B7: =费用预算执行明细!B5 -> 693.56 | C7: =费用预算执行明细!C5 -> 77.910641 | D7: =费用预算执行明细!D5 -> 52.070162 | E7: =费用预算执行明细!E5 -> 46.482044 | F7: =费用预算执行明细!F5 -> 47.60297 | G7: =费用预算执行明细!G5 -> 0 | H7: =费用预算执行明细!H5 -> 0 | I7: =费用预算执行明细!I5 -> 0 | ... N7: =费用预算执行明细!N5 -> 0 | O7: =SUM(C7:N7) -> 224.06582 | P7: =IFERROR(O7/B7,) -> 0.32306623
A8: 日常费用 | B8: =费用预算执行明细!B13 -> 99.8847 | C8: =费用预算执行明细!C13 -> 4.830154 | D8: =费用预算执行明细!D13 -> 2.591405 | E8: =费用预算执行明细!E13 -> -4.87766 | F8: =费用预算执行明细!F13 -> 14.404717 | G8: =费用预算执行明细!G13 -> 0 | H8: =费用预算执行明细!H13 -> 0 | I8: =费用预算执行明细!I13 -> 0 | ... N8: =费用预算执行明细!N13 -> 0 | O8: =SUM(C8:N8) -> 16.948616 | P8: =IFERROR(O8/B8,) -> 0.1696818
A9: 变动费用 | B9: =费用预算执行明细!B46 -> 724.9893 | C9: =费用预算执行明细!C46 -> 48.881752 | D9: =费用预算执行明细!D46 -> 47.727211 | E9: =费用预算执行明细!E46 -> 41.099525 | F9: =费用预算执行明细!F46 -> 48.361423 | G9: =费用预算执行明细!G46 -> 0 | H9: =费用预算执行明细!H46 -> 0 | I9: =费用预算执行明细!I46 -> 0 | ... N9: =费用预算执行明细!N46 -> 0 | O9: =SUM(C9:N9) -> 186.06991 | P9: =IFERROR(O9/B9,) -> 0.25665194
A10: 经营变动费用支出 | B10: =费用预算执行明细!B47 -> 225.42 | C10: =费用预算执行明细!C47 -> 14.661237 | D10: =费用预算执行明细!D47 -> 17.69237 | E10: =费用预算执行明细!E47 -> 15.084433 | F10: =费用预算执行明细!F47 -> 20.184048 | G10: =费用预算执行明细!G47 -> 0 | H10: =费用预算执行明细!H47 -> 0 | I10: =费用预算执行明细!I47 -> 0 | ... N10: =费用预算执行明细!N47 -> 0 | O10: =SUM(C10:N10) -> 67.622088 | P10: =IFERROR(O10/B10,) -> 0.29998265
A11: 营业成本支出 | B11: =费用预算执行明细!B82 -> 499.5693 | C11: =费用预算执行明细!C82 -> 34.220515 | D11: =费用预算执行明细!D82 -> 30.034841 | E11: =费用预算执行明细!E82 -> 26.015092 | F11: =费用预算执行明细!F82 -> 28.177375 | G11: =费用预算执行明细!G82 -> 0 | H11: =费用预算执行明细!H82 -> 0 | I11: =费用预算执行明细!I82 -> 0 | ... N11: =费用预算执行明细!N82 -> 0 | O11: =SUM(C11:N11) -> 118.44782 | P11: =IFERROR(O11/B11,) -> 0.23709988
A12: 资本性支出 | B12: 153.94 | C12: 0 | D12: 0 | E12: 0 | F12: 0 | O12: =SUM(C12:N12) -> 0 | P12: =IFERROR(O12/B12,) -> 0
A13: 折旧摊销 | B13: 774.79 | C13: 64.720281 | D13: 64.716896 | E13: 64.716896 | F13: 64.716896 | O13: =SUM(C13:N13) -> 258.87097 | P13: =IFERROR(O13/B13,) -> 0.33411759
A14: 财务费用 | B14: -0.92 | C14: 0.130972 | D14: 0.104688 | E14: -0.416022 | F14: 0.160164 | O14: =SUM(C14:N14) -> -0.020198 | P14: =IFERROR(O14/B14,) -> 0.021954348
A15: 税金及附加 | B15: 179.7629 | C15: 0.10334 | D15: 0 | E15: 0.27608 | F15: 87.951979 | O15: =SUM(C15:N15) -> 88.331399 | P15: =IFERROR(O15/B15,) -> 0.49137726
A16: 变动费用率 | B16: =IFERROR(B9/B4,) -> 0.49827537 | C16: =IFERROR(C9/C4,) -> 0.61893451 | D16: =IFERROR(D9/D4,) -> 0.74780788 | E16: =IFERROR(E9/E4,) -> 0.5101676 | F16: =IFERROR(F9/F4,) -> 0.49879635 | G16: =IFERROR(G9/G4,) -> 0 | H16: =IFERROR(H9/H4,) -> 0 | I16: =IFERROR(I9/I4,) -> 0 | ... O16: =IFERROR(O9/O4,) -> 0.58089273
A18: EBITDA | B18: =B4-B6-B9-B15+3.6+7 -> -232.59963 | C18: =C4-C6-C9-C15 -> -52.748627 | D18: =D4-D6-D9-D15 -> -38.565954 | E18: =E4-E6-E9-E15 -> -2.419159 | F18: =F4-F6-F9-F15 -> -101.36484 | G18: =G4-G6-G9-G15 -> 0 | H18: =H4-H6-H9-H15 -> 0 | I18: =I4-I6-I9-I15 -> 0 | J18: =J4-J6-J9-J15 -> 0 | ... O18: =O4-O6-O9-O15 -> -195.09858 | P18: =IFERROR(O18/B18,) -> 0.83877424
A19: GOP | B19: =B4-B6-B9-B14+7 -> -55.516737 | C19: =C4-C6-C9-C14 -> -52.776259 | D19: =D4-D6-D9-D14 -> -38.670642 | E19: =E4-E6-E9-E14 -> -1.727057 | F19: =F4-F6-F9-F14 -> -13.573026 | G19: =G4-G6-G9-G14 -> 0 | H19: =H4-H6-H9-H14 -> 0 | I19: =I4-I6-I9-I14 -> 0 | J19: =J4-J6-J9-J14 -> 0 | ... O19: =O4-O6-O9-O14 -> -106.74698 | P19: =IFERROR(O19/B19,) -> 1.9227892
A21: 备注 | B21: EBITDA=营业收入-固定费用-变动费用-税金及附加
B22: GOP=营业收入-固定费用-变动费用-财务费用（不含利息费用）
B23: 需填列单元格

Sheet 费用预算执行明细
A1: 瑞尔酒店公司2026年预算执行情况明细表
A2: 项目 | B2: 2026年预算 | C2: 2026年预算执行情况 | O2: 2026年实际 | P2: 执行率
C3: 1月 | D3: 2月 | E3: 3月 | F3: 4月 | G3: 5月 | H3: 6月 | I3: 7月 | J3: 8月 | K3: 9月 | L3: 10月 | M3: 11月 | N3: 12月
A4: 固定费用 | B4: =B5+B13 -> 793.4447 | C4: =C5+C13 -> 82.740795 | D4: =D5+D13 -> 54.661567 | E4: =E5+E13 -> 41.604384 | F4: =F5+F13 -> 62.007687 | G4: =G5+G13 -> 0 | H4: =H5+H13 -> 0 | I4: =I5+I13 -> 0 | ... N4: =N5+N13 -> 0 | O4: =SUM(C4:N4) -> 241.01443 | P4: =IFERROR(O4/B4,) -> 0.30375706
A5: 人力费用合计 | B5: =SUM(B6:B12) -> 693.56 | C5: =SUM(C6:C12) -> 77.910641 | D5: =SUM(D6:D12) -> 52.070162 | E5: =SUM(E6:E12) -> 46.482044 | F5: =SUM(F6:F12) -> 47.60297 | G5: =SUM(G6:G12) -> 0 | H5: =SUM(H6:H12) -> 0 | I5: =SUM(I6:I12) -> 0 | ... N5: =SUM(N6:N12) -> 0 | O5: =SUM(C5:N5) -> 224.06582 | P5: =IFERROR(O5/B5,) -> 0.32306623
A6: 固定工资 | B6: 465.96 | C6: =66.785925-0.89-1.4448 -> 64.451125 | D6: =40.420825-0.806632-1.4468 -> 38.167393 | E6: =36.487796-1.6156-1.4468 -> 33.425396 | F6: =36.251258-1.273628-1.4858 -> 33.49183 | O6: =SUM(C6:N6) -> 169.53574 | P6: =IFERROR(O6/B6,) -> 0.36384184
A7: 绩效工资 | O7: =SUM(C7:N7) -> 0 | P7: =IFERROR(O7/B7,) -> 0
A8: 奖金 | O8: =SUM(C8:N8) -> 0 | P8: =IFERROR(O8/B8,) -> 0
A9: 福利费 | B9: 29.24 | C9: =0.121742+1.4448 -> 1.566542 | D9: =0.451528+1.4468+0.52432 -> 2.422648 | E9: =0.18266+1.4468 -> 1.62946 | F9: =0.143183+1.4858+1.52211 -> 3.151093 | O9: =SUM(C9:N9) -> 8.769743 | P9: =IFERROR(O9/B9,) -> 0.29992281
A10: 五险一金 | B10: 154.52 | C10: =8.664917+0.6186 -> 9.283517 | D10: =8.386482+0.5686 -> 8.955082 | E10: =8.275993+0.5686 -> 8.844593 | F10: =8.281991+0.5786 -> 8.860591 | O10: =SUM(C10:N10) -> 35.943783 | P10: =IFERROR(O10/B10,) -> 0.23261573
A11: 招聘费 | B11: 0.4 | O11: =SUM(C11:N11) -> 0 | P11: =IFERROR(O11/B11,) -> 0
A12: 其他人力费用 | B12: 43.44 | C12: =0.110609+2.498848 -> 2.609457 | D12: =0.111046+2.413993 -> 2.525039 | E12: =0.086346+2.496249 -> 2.582595 | F12: =0.093912+2.005544 -> 2.099456 | O12: =SUM(C12:N12) -> 9.816547 | P12: =IFERROR(O12/B12,) -> 0.22597944
A13: 固定费用支出合计 | B13: =SUM(B14:B45) -> 99.8847 | C13: =SUM(C14:C45) -> 4.830154 | D13: =SUM(D14:D45) -> 2.591405 | E13: =SUM(E14:E45) -> -4.87766 | F13: =SUM(F14:F45) -> 14.404717 | G13: =SUM(G14:G45) -> 0 | H13: =SUM(H14:H45) -> 0 | I13: =SUM(I14:I45) -> 0 | ... N13: =SUM(N14:N45) -> 0 | O13: =SUM(C13:N13) -> 16.948616 | P13: =IFERROR(O13/B13,) -> 0.1696818
A14: 邮寄费 | B14: 0.12 | D14: 0.0056 | O14: =SUM(C14:N14) -> 0.0056 | P14: =IFERROR(O14/B14,) -> 0.046666667
A15: 差旅费 | B15: 5.6 | O15: =SUM(C15:N15) -> 0 | P15: =IFERROR(O15/B15,) -> 0
A16: 业务招待费 | B16: 3.4 | E16: 0.0478 | O16: =SUM(C16:N16) -> 0.0478 | P16: =IFERROR(O16/B16,) -> 0.014058824
A17: 汽车费 | O17: =SUM(C17:N17) -> 0 | P17: =IFERROR(O17/B17,) -> 0
A18: 低值易耗品 | B18: 7.54 | C18: 0.7254 | D18: -0.083453 | O18: =SUM(C18:N18) -> 0.641947 | P18: =IFERROR(O18/B18,) -> 0.085138859
A19: 设备修理费 | B19: 20.5487 | C19: =1.554545-0.078322 -> 1.476223 | D19: 0.030165 | E19: =0.754717-7.749436 -> -6.994719 | F19: =9.639696-0.1265-0.038208 -> 9.474988 | O19: =SUM(C19:N19) -> 3.986657 | P19: =IFERROR(O19/B19,) -> 0.19401018
A20: 信息系统费 | B20: 1.256 | D20: 0.703517 | F20: 0.18 | O20: =SUM(C20:N20) -> 0.883517 | P20: =IFERROR(O20/B20,) -> 0.7034371
A21: 通讯费 | B21: 15.6 | C21: 1.213084 | D21: 1.3 | E21: 1.1933 | F21: 2.387377 | O21: =SUM(C21:N21) -> 6.093761 | P21: =IFERROR(O21/B21,) -> 0.39062571
A22: 交通费 | B22: 0.05 | D22: 0.003937 | F22: 0.008292 | O22: =SUM(C22:N22) -> 0.012229 | P22: =IFERROR(O22/B22,) -> 0.24458
A23: 办公费 | B23: 4.5 | C23: =0.049505+0.288968 -> 0.338473 | D23: 0.028843 | E23: =0.012583+0.112866 -> 0.125449 | F23: =0.099822+0.038069 -> 0.137891 | O23: =SUM(C23:N23) -> 0.630656 | P23: =IFERROR(O23/B23,) -> 0.14014578
A24: 会议费 | O24: =SUM(C24:N24) -> 0 | P24: =IFERROR(O24/B24,) -> 0
A25: 水电费 | O25: =SUM(C25:N25) -> 0 | P25: =IFERROR(O25/B25,) -> 0
A26: 展览费 | O26: =SUM(C26:N26) -> 0 | P26: =IFERROR(O26/B26,) -> 0
A27: 广告宣传费 | B27: 1 | O27: =SUM(C27:N27) -> 0 | P27: =IFERROR(O27/B27,) -> 0
A28: 咨询服务费 | B28: 7 | C28: 0.315313 | O28: =SUM(C28:N28) -> 0.315313 | P28: =IFERROR(O28/B28,) -> 0.045044714
A29: 法律诉讼费 | B29: 1 | O29: =SUM(C29:N29) -> 0 | P29: =IFERROR(O29/B29,) -> 0
A30: 工作餐费 | O30: =SUM(C30:N30) -> 0 | P30: =IFERROR(O30/B30,) -> 0
A31: 报关及代理费 | O31: =SUM(C31:N31) -> 0 | P31: =IFERROR(O31/B31,) -> 0
A32: 研究开发费 | O32: =SUM(C32:N32) -> 0 | P32: =IFERROR(O32/B32,) -> 0
A33: 质检认证费 | B33: 7.63 | F33: 1.521887 | O33: =SUM(C33:N33) -> 1.521887 | P33: =IFERROR(O33/B33,) -> 0.19946094
A34: 排污费 | O34: =SUM(C34:N34) -> 0 | P34: =IFERROR(O34/B34,) -> 0
A35: 社保服务费 | O35: =SUM(C35:N35) -> 0 | P35: =IFERROR(O35/B35,) -> 0
A36: 劳动保护费 | O36: =SUM(C36:N36) -> 0 | P36: =IFERROR(O36/B36,) -> 0
A37: 残疾人就业保障金 | B37: 7 | O37: =SUM(C37:N37) -> 0 | P37: =IFERROR(O37/B37,) -> 0
A38: 财产保险费 | B38: 6.55 | O38: =SUM(C38:N38) -> 0 | P38: =IFERROR(O38/B38,) -> 0
A39: 房租及物业费 | O39: =SUM(C39:N39) -> 0 | P39: =IFERROR(O39/B39,) -> 0
A40: 开办费 | O40: =SUM(C40:N40) -> 0 | P40: =IFERROR(O40/B40,) -> 0
A41: 存货盘存 | O41: =SUM(C41:N41) -> 0 | P41: =IFERROR(O41/B41,) -> 0
A42: 销售代理费 | O42: =SUM(C42:N42) -> 0 | P42: =IFERROR(O42/B42,) -> 0
A43: 销售佣金 | O43: =SUM(C43:N43) -> 0 | P43: =IFERROR(O43/B43,) -> 0
A44: 培训费 | B44: 1 | O44: =SUM(C44:N44) -> 0 | P44: =IFERROR(O44/B44,) -> 0
A45: 其他 | B45: 10.09 | C45: =0.738534+0.021929+0.001198 -> 0.761661 | D45: =0.568639+0.034157 -> 0.602796 | E45: =0.549404+0.020509+0.001197+0.1794 -> 0.75051 | F45: =0.582768+0.0317+0.000719+0.079095 -> 0.694282 | O45: =SUM(C45:N45) -> 2.809249 | P45: =IFERROR(O45/B45,) -> 0.27841913
A46: 变动费用 | B46: =B47+B82 -> 724.9893 | C46: =C47+C82 -> 48.881752 | D46: =D47+D82 -> 47.727211 | E46: =E47+E82 -> 41.099525 | F46: =F47+F82 -> 48.361423 | G46: =G47+G82 -> 0 | H46: =H47+H82 -> 0 | I46: =I47+I82 -> 0 | ... N46: =N47+N82 -> 0 | O46: =SUM(C46:N46) -> 186.06991 | P46: =IFERROR(O46/B46,) -> 0.25665194
A47: 变动费用支出合计 | B47: =SUM(B48:B81) -> 225.42 | C47: =SUM(C48:C81) -> 14.661237 | D47: =SUM(D48:D81) -> 17.69237 | E47: =SUM(E48:E81) -> 15.084433 | F47: =SUM(F48:F81) -> 20.184048 | G47: =SUM(G48:G81) -> 0 | H47: =SUM(H48:H81) -> 0 | I47: =SUM(I48:I81) -> 0 | ... N47: =SUM(N48:N81) -> 0 | O47: =SUM(C47:N47) -> 67.622088 | P47: =IFERROR(O47/B47,) -> 0.29998265
A48: 邮寄费 | B48: 0.18 | C48: 0.018773 | E48: 0.0034 | O48: =SUM(C48:N48) -> 0.022173 | P48: =IFERROR(O48/B48,) -> 0.12318333
A49: 差旅费 | B49: 0.6 | O49: =SUM(C49:N49) -> 0 | P49: =IFERROR(O49/B49,) -> 0
A50: 业务招待费 | B50: 5.3 | C50: 0.165 | D50: 0.5788 | E50: 0.0597 | F50: 0.3401 | O50: =SUM(C50:N50) -> 1.1436 | P50: =IFERROR(O50/B50,) -> 0.21577358
A51: 汽车费 | O51: =SUM(C51:N51) -> 0 | P51: =IFERROR(O51/B51,) -> 0
A52: 低值易耗品及修理费 | O52: =SUM(C52:N52) -> 0 | P52: =IFERROR(O52/B52,) -> 0
A53: 信息系统费 | O53: =SUM(C53:N53) -> 0 | P53: =IFERROR(O53/B53,) -> 0
A54: 通讯费 | O54: =SUM(C54:N54) -> 0 | P54: =IFERROR(O54/B54,) -> 0
A55: 交通费 | O55: =SUM(C55:N55) -> 0 | P55: =IFERROR(O55/B55,) -> 0
A56: 办公费 | B56: 3.4 | C56: 0.321597 | D56: =0.085465+0.040958 -> 0.126423 | E56: 0.112389 | F56: 0.121877 | O56: =SUM(C56:N56) -> 0.682286 | P56: =IFERROR(O56/B56,) -> 0.20067235
A57: 会议费 | O57: =SUM(C57:N57) -> 0 | P57: =IFERROR(O57/B57,) -> 0
A58: 水电费 | O58: =SUM(C58:N58) -> 0 | P58: =IFERROR(O58/B58,) -> 0
A59: 招聘费 | O59: =SUM(C59:N59) -> 0 | P59: =IFERROR(O59/B59,) -> 0
A60: 展览费 | O60: =SUM(C60:N60) -> 0 | P60: =IFERROR(O60/B60,) -> 0
A61: 广告宣传费 | B61: 3.6 | C61: 0.028 | E61: 0.1605 | O61: =SUM(C61:N61) -> 0.1885 | P61: =IFERROR(O61/B61,) -> 0.052361111
A62: 咨询服务费 | O62: =SUM(C62:N62) -> 0 | P62: =IFERROR(O62/B62,) -> 0
A63: 法律诉讼费 | F63: 5.3692 | O63: =SUM(C63:N63) -> 5.3692 | P63: =IFERROR(O63/B63,) -> 0
A64: 工作餐费 | O64: =SUM(C64:N64) -> 0 | P64: =IFERROR(O64/B64,) -> 0
A65: 报关及代理费 | O65: =SUM(C65:N65) -> 0 | P65: =IFERROR(O65/B65,) -> 0
A66: 研究开发费 | O66: =SUM(C66:N66) -> 0 | P66: =IFERROR(O66/B66,) -> 0
A67: 质检认证费 | O67: =SUM(C67:N67) -> 0 | P67: =IFERROR(O67/B67,) -> 0
A68: 福利费 | O68: =SUM(C68:N68) -> 0 | P68: =IFERROR(O68/B68,) -> 0
A69: 排污费 | O69: =SUM(C69:N69) -> 0 | P69: =IFERROR(O69/B69,) -> 0
A70: 社保服务费 | O70: =SUM(C70:N70) -> 0 | P70: =IFERROR(O70/B70,) -> 0
A71: 劳动保护费 | O71: =SUM(C71:N71) -> 0 | P71: =IFERROR(O71/B71,) -> 0
A72: 残疾人就业保障金 | O72: =SUM(C72:N72) -> 0 | P72: =IFERROR(O72/B72,) -> 0
A73: 财产保险费 | O73: =SUM(C73:N73) -> 0 | P73: =IFERROR(O73/B73,) -> 0
A74: 房租及物业费 | O74: =SUM(C74:N74) -> 0 | P74: =IFERROR(O74/B74,) -> 0
A75: 开办费 | O75: =SUM(C75:N75) -> 0 | P75: =IFERROR(O75/B75,) -> 0
... A77: 销售代理费 | O77: =SUM(C77:N77) -> 0 | P77: =IFERROR(O77/B77,) -> 0
A78: 销售佣金 | B78: 32.4 | C78: =0.240509+0.89 -> 1.130509 | D78: =2.285998+0.806632 -> 3.09263 | E78: =0.084915+1.6156 -> 1.700515 | F78: =0.12192+1.273628 -> 1.395548 | O78: =SUM(C78:N78) -> 7.319202 | P78: =IFERROR(O78/B78,) -> 0.2259013
A79: 临时工及劳务外包 | B79: 164.36 | C79: =10.091715+1.287129+1.534653 -> 12.913497 | D79: =10.089962+1.287129+1.534653 -> 12.911744 | E79: =10.089163+1.287129+0.125038+1.534653 -> 13.035983 | F79: =10.088385+1.287129+1.534653 -> 12.910167 | O79: =SUM(C79:N79) -> 51.771391 | P79: =IFERROR(O79/B79,) -> 0.31498778
A80: 宿舍租赁费 | B80: 12.48 | O80: =SUM(C80:N80) -> 0 | P80: =IFERROR(O80/B80,) -> 0
A81: 其他 | B81: 3.1 | C81: 0.083861 | D81: =0.416+0.536+0.030773 -> 0.982773 | E81: 0.011946 | F81: 0.047156 | O81: =SUM(C81:N81) -> 1.125736 | P81: =IFERROR(O81/B81,) -> 0.36314065
A82: 营业成本支出合计 | B82: =B83+B84+B90+B95+B98 -> 499.5693 | C82: =C83+C84+C90+C95+C98 -> 34.220515 | D82: =D83+D84+D90+D95+D98 -> 30.034841 | E82: =E83+E84+E90+E95+E98 -> 26.015092 | F82: =F83+F84+F90+F95+F98 -> 28.177375 | G82: =G83+G84+G90+G95+G98 -> 0 | H82: =H83+H84+H90+H95+H98 -> 0 | I82: =I83+I84+I90+I95+I98 -> 0 | ... N82: =N83+N84+N90+N95+N98 -> 0 | O82: =SUM(C82:N82) -> 118.44782 | P82: =IFERROR(O82/B82,) -> 0.23709988
A83: 空置房物业费 | O83: =SUM(C83:N83) -> 0 | P83: =IFERROR(O83/B83,) -> 0
A84: 客房成本合计 | B84: =SUM(B85:B89) -> 156.63762 | C84: =SUM(C85:C89) -> 11.270965 | D84: =SUM(D85:D89) -> 7.181822 | E84: =SUM(E85:E89) -> 8.9015641 | F84: =SUM(F85:F89) -> 8.7966956 | G84: =SUM(G85:G89) -> 0 | H84: =SUM(H85:H89) -> 0 | I84: =SUM(I85:I89) -> 0 | ... N84: =SUM(N85:N89) -> 0 | O84: =SUM(C84:N84) -> 36.151047 | P84: =IFERROR(O84/B84,) -> 0.23079416
A85: 客房用品损耗支出 | B85: 23.093615 | C85: 0.59457 | D85: 0.772455 | E85: 1.282029 | F85: 1.702963 | O85: =SUM(C85:N85) -> 4.352017 | P85: =IFERROR(O85/B85,) -> 0.18845109
A86: 客房水电能源支出 | B86: 112.32 | C86: 8.839934 | D86: 6.04189 | E86: 6.9550631 | F86: 6.3899416 | O86: =SUM(C86:N86) -> 28.226829 | P86: =IFERROR(O86/B86,) -> 0.25130724
A87: 客房布草等物品清洁支出 | B87: 6.96 | C87: =0.092132+0.192217 -> 0.284349 | D87: =0.152741+0.208007 -> 0.360748 | E87: =0.20684+0.303715 -> 0.510555 | F87: =0.371572+0.169458 -> 0.54103 | O87: =SUM(C87:N87) -> 1.696682 | P87: =IFERROR(O87/B87,) -> 0.24377615
A88: 客房设备维修支出 | B88: 2.52 | C88: 0.09 | D88: 0 | E88: 0 | F88: 0.098 | O88: =SUM(C88:N88) -> 0.188 | P88: =IFERROR(O88/B88,) -> 0.074603175
A89: 其他与客房直接相关的支出 | B89: 11.744 | C89: =0.272105+1.182428+0.007579 -> 1.462112 | D89: =0.0056+0.001129 -> 0.006729 | E89: =0.146035+0.007882 -> 0.153917 | F89: =0.051771+0.01299 -> 0.064761 | O89: =SUM(C89:N89) -> 1.687519 | P89: =IFERROR(O89/B89,) -> 0.14369201
A90: 餐饮成本合计 | B90: =SUM(B91:B94) -> 339.85508 | C90: =SUM(C91:C94) -> 22.896382 | D90: =SUM(D91:D94) -> 22.774167 | E90: =SUM(E91:E94) -> 17.043152 | F90: =SUM(F91:F94) -> 19.158832 | G90: =SUM(G91:G94) -> 0 | H90: =SUM(H91:H94) -> 0 | I90: =SUM(I91:I94) -> 0 | ... N90: =SUM(N91:N94) -> 0 | O90: =SUM(C90:N90) -> 81.872533 | P90: =IFERROR(O90/B90,) -> 0.24090425
A91: 餐饮食材支出 | B91: 230.71066 | C91: 15.461741 | D91: 16.29828 | E91: 11.372569 | F91: 13.792438 | O91: =SUM(C91:N91) -> 56.925028 | P91: =IFERROR(O91/B91,) -> 0.24673775
A92: 餐饮水电燃气支出 | B92: 87.6 | C92: 6.889486 | D92: 4.728012 | E92: 5.3383599 | F92: 5.0616924 | O92: =SUM(C92:N92) -> 22.01755 | P92: =IFERROR(O92/B92,) -> 0.2513419
A93: 餐饮设备维修支出 | B93: 2.4 | C93: 0 | D93: 0 | E93: 0 | F93: 0.004 | O93: =SUM(C93:N93) -> 0.004 | P93: =IFERROR(O93/B93,) -> 0.0016666667
A94: 其他与餐饮直接相关的支出 | B94: 19.144425 | C94: =0.317824+0.069531+0.1578 -> 0.545155 | D94: =0.42837+0.119505+1.2 -> 1.747875 | E94: =0.23697+0.095253 -> 0.332223 | F94: =0.212908+0.087794 -> 0.300702 | O94: =SUM(C94:N94) -> 2.925955 | P94: =IFERROR(O94/B94,) -> 0.15283588
A95: 会议成本合计 | B95: =B96+B97 -> 3.0766038 | C95: =C96+C97 -> 0.053168 | D95: =D96+D97 -> 0.078852 | E95: =E96+E97 -> 0.070376 | F95: =F96+F97 -> 0.221847 | G95: =G96+G97 -> 0 | H95: =H96+H97 -> 0 | I95: =I96+I97 -> 0 | ... N95: =N96+N97 -> 0 | O95: =SUM(C95:N95) -> 0.424243 | P95: =IFERROR(O95/B95,) -> 0.13789328
A96: 会议设备支出 | B96: 0.5 | O96: =SUM(C96:N96) -> 0 | P96: =IFERROR(O96/B96,) -> 0
A97: 其他与会议直接相关的支出 | B97: 2.5766038 | C97: 0.053168 | D97: 0.078852 | E97: 0.070376 | F97: 0.221847 | O97: =SUM(C97:N97) -> 0.424243 | P97: =IFERROR(O97/B97,) -> 0.16465201
O98: =SUM(C98:N98) -> 0 | P98: =IFERROR(O98/B98,) -> 0
A100: 需填列

Sheet 资本性支出计划与执行
A1: 瑞尔酒店公司2026年资本性支出执行情况明细表
A2: 资产类别 | B2: 资产类型 | C2: 资产名称 | D2: 数量 | E2: 单价 | F2: 金额 | G2: 2026年预算 | H2: 2026年实际
A3: 固定资产 | B3: 家具用具 | C3: 包房点歌系统（含音响、话筒） | D3: 2 | E3: 0.8 | F3: =D3*E3 -> 1.6 | G3: 1.6
C4: 包房岩板茶台（含椅子） | D4: 2 | E4: 0.25 | F4: =D4*E4 -> 0.5 | G4: 0.5
C5: 厨房制冷设备（冰柜） | D5: 6 | E5: 0.25 | F5: =D5*E5 -> 1.5 | G5: 1.5
C6: 吸尘器 | D6: 3 | E6: 0.15 | F6: =D6*E6 -> 0.45 | G6: 0.45
C7: 惠普打印机 | D7: 2 | E7: 0.25 | F7: =D7*E7 -> 0.5 | G7: 0.25
C8: 电脑 | D8: 1 | E8: 0.2 | F8: =D8*E8 -> 0.2 | G8: 0.2
A9: 其他长期支出 | B9: 长期待摊费用 | C9: 客房6-7楼部份翻新整改 | D9: 31间 | E9: 2.8 | F9: 95 | G9: 95
C10: 两江厅 | D10: 530平米 | E10: 0.0755 | F10: 40 | G10: 40
C11: 3楼护墙板 | D11: 110平米 | E11: 0.028 | F11: 3 | G11: 3
C12: 电梯钢绳 | D12: 2200米 | E12: 0.0011 | F12: 3.2 | G12: 3.2
C13: 电梯维修 | D13: 1台 | E13: 3.74 | F13: 3.74 | G13: 3.74
C14: 草坪婚礼场地 | D14: 1 | E14: 4.5 | F14: 4.5 | G14: 4.5
A15: 资本性支出合计 | G15: =SUM(G3:G14) -> 153.94 | H15: =SUM(H3:H8) -> 0
A17: 需填列
