Workbook

Sheet 指标统计
A1: 哈尔滨君康春夏秋冬置业有限公司2026年经营指标统计表
A2: 指标 | B2: 项目 | C2: 2026年预算 | D2: 2026年执行情况 | P2: 2026年实际 | Q2: 执行率 | R2: 指标说明
D3: 1月 | E3: 2月 | F3: 3月 | G3: 4月 | H3: 5月 | I3: 6月 | J3: 7月 | K3: 8月 | L3: 9月 | M3: 10月 | N3: 11月 | O3: 12月
A4: 经营指标 | B4: 营业收入 | C4: =预算执行汇总!B4 -> 1494.88 | D4: {=预算执行汇总!C4:N4} -> 115.23 | E4: 97.66 | F4: 97.81 | G4: 102.53 | H4: 0 | I4: 0 | J4: 0 | K4: 0 | L4: 0 | M4: 0 | N4: 0 | O4: 0 | P4: =SUM(D4:O4) -> 413.23 | Q4: =IFERROR((P4-C4)/ABS(C4)+1,) -> 0.27643022
B5: EBITDA/GOP/扣非净利润 | C5: 399 | D5: 64.96 | E5: 47.55 | F5: 49.88 | G5: 46.19 | P5: =SUM(D5:O5) -> 208.58 | Q5: =IFERROR(P5/C5,) -> 0.52275689 | R5: EBITDA（商写适用）/GOP（酒店适用）/扣非净利润（保险中介适用）
B6: 经营活动净现金流 | C6: 124 | D6: -11.16 | E6: -8.45 | F6: 86.87 | G6: 21.83 | P6: =SUM(D6:O6) -> 89.09 | Q6: =IFERROR(P6/C6,) -> 0.71846774
A7: 财务指标 | B7: 经营支出小计 | C7: {=预算执行汇总!B5:B12} -> 775.1 | D7: {=预算执行汇总!C5:N12} -> 25.4393 | E7: 25.42 | F7: 23.66 | G7: 30.88 | H7: 0 | I7: 0 | J7: 0 | K7: 0 | L7: 0 | M7: 0 | N7: 0 | O7: 0 | P7: =SUM(D7:O7) -> 105.3993 | Q7: =IFERROR(P7/C7,) -> 0.13598155
B8: 固定费用 | C8: 735.9 | D8: 24.8893 | E8: 23.58 | F8: 23.66 | G8: 25.24 | H8: 0 | I8: 0 | J8: 0 | K8: 0 | L8: 0 | M8: 0 | N8: 0 | O8: 0 | P8: =SUM(D8:O8) -> 97.3693 | Q8: =IFERROR(P8/C8,) -> 0.13231322
B9: 人力费用 | C9: 298.77 | D9: 24.89 | E9: 23.48 | F9: 23.55 | G9: 23.68 | H9: 0 | I9: 0 | J9: 0 | K9: 0 | L9: 0 | M9: 0 | N9: 0 | O9: 0 | P9: =SUM(D9:O9) -> 95.6 | Q9: =IFERROR(P9/C9,) -> 0.31997858
B10: 日常费用 | C10: 437.13 | D10: -0.0007 | E10: 0.1 | F10: 0.11 | G10: 1.56 | H10: 0 | I10: 0 | J10: 0 | K10: 0 | L10: 0 | M10: 0 | N10: 0 | O10: 0 | P10: =SUM(D10:O10) -> 1.7693 | Q10: =IFERROR(P10/C10,) -> 0.0040475373
B11: 变动费用 | C11: 39.2 | D11: 0.55 | E11: 1.84 | F11: 0 | G11: 5.64 | H11: 0 | I11: 0 | J11: 0 | K11: 0 | L11: 0 | M11: 0 | N11: 0 | O11: 0 | P11: =SUM(D11:O11) -> 8.03 | Q11: =IFERROR(P11/C11,) -> 0.20484694
B12: 经营变动费用 | C12: 39.2 | D12: 0.55 | E12: 1.84 | F12: 0 | G12: 5.64 | H12: 0 | I12: 0 | J12: 0 | K12: 0 | L12: 0 | M12: 0 | N12: 0 | O12: 0 | P12: =SUM(D12:O12) -> 8.03 | Q12: =IFERROR(P12/C12,) -> 0.20484694
B13: 营业成本 | C13: 0 | D13: 0 | E13: 0 | F13: 0 | G13: 0 | H13: 0 | I13: 0 | J13: 0 | K13: 0 | L13: 0 | M13: 0 | N13: 0 | O13: 0 | P13: =SUM(D13:O13) -> 0 | Q13: =IFERROR(P13/C13,) -> 0
B14: 资本性支出 | C14: 52 | D14: 0 | E14: 0 | F14: 0 | G14: 0 | H14: 0 | I14: 0 | J14: 0 | K14: 0 | L14: 0 | M14: 0 | N14: 0 | O14: 0 | P14: =SUM(D14:O14) -> 0 | Q14: =IFERROR(P14/C14,) -> 0
A15: 业务指标 | B15: 期末出租率/月均入住率 | C15: 0.69 | D15: 0.6011 | E15: 0.5998 | F15: 0.6228 | G15: 0.6348 | P15: =IFERROR(AVERAGE(D15:O15),) -> 0.614625 | Q15: =IFERROR(P15/C15,) -> 0.89076087 | R15: 期末出租率(商写适用)/月均入住率(酒店适用)
B16: 回款率 | C16: 0.89 | D16: 0.8345 | E16: 0.8097 | F16: 0.888 | G16: 0.8746 | P16: =IFERROR(AVERAGE(D16:O16),) -> 0.8517 | Q16: =IFERROR(P16/C16,) -> 0.95696629 | R16: 商写及酒店适用
B17: OTA网络评价 | P17: {=IFERROR(INDEX(D17:O17,0,MATCH(9.99999999999999E+307,D17:O17)),)} -> 0 | Q17: =IFERROR(P17/C17,) -> 0 | R17: 酒店适用
B18: 期交规保 | P18: {=IFERROR(INDEX(D18:O18,0,MATCH(9.99999999999999E+307,D18:O18)),)} -> 0 | Q18: =IFERROR(P18/C18,) -> 0 | R18: 保险中介适用
B19: 13月继续率 | P19: {=IFERROR(INDEX(D19:O19,0,MATCH(9.99999999999999E+307,D19:O19)),)} -> 0 | Q19: =IFERROR(P19/C19,) -> 0 | R19: 保险中介适用
B20: 25月继续率 | P20: {=IFERROR(INDEX(D20:O20,0,MATCH(9.99999999999999E+307,D20:O20)),)} -> 0 | Q20: =IFERROR(P20/C20,) -> 0 | R20: 保险中介适用
A21: 备注 | B21: EBITDA=营业收入-固定费用-变动费用-税金及附加
B22: GOP=营业收入-固定费用-变动费用-财务费用（不含利息费用）
B23: 需填列单元格

Sheet 预算执行汇总
A1: 哈尔滨君康春夏秋冬置业有限公司2026年预算执行情况汇总表
A2: 项目 | B2: 2026年预算 | C2: 2026年执行情况 | O2: 2026年实际 | P2: 执行率
C3: 1月 | D3: 2月 | E3: 3月 | F3: 4月 | G3: 5月 | H3: 6月 | I3: 7月 | J3: 8月 | K3: 9月 | L3: 10月 | M3: 11月 | N3: 12月
A4: 营业收入 | B4: 1494.88 | C4: 115.23 | D4: 97.66 | E4: 97.81 | F4: 102.53 | O4: =SUM(C4:N4) -> 413.23 | P4: =IFERROR(O4/B4,) -> 0.27643022
A5: 经营支出小计 | B5: =B6+B9 -> 775.1 | C5: =C6+C9 -> 25.4393 | D5: =D6+D9 -> 25.42 | E5: =E6+E9 -> 23.66 | F5: =F6+F9 -> 30.88 | G5: =G6+G9 -> 0 | H5: =H6+H9 -> 0 | I5: =I6+I9 -> 0 | ... N5: =N6+N9 -> 0 | O5: =SUM(C5:N5) -> 105.3993 | P5: =IFERROR(O5/B5,) -> 0.13598155
A6: 固定费用 | B6: =B7+B8 -> 735.9 | C6: =费用预算执行明细!C4 -> 24.8893 | D6: =费用预算执行明细!D4 -> 23.58 | E6: =费用预算执行明细!E4 -> 23.66 | F6: =费用预算执行明细!F4 -> 25.24 | G6: =费用预算执行明细!G4 -> 0 | H6: =费用预算执行明细!H4 -> 0 | I6: =费用预算执行明细!I4 -> 0 | J6: =费用预算执行明细!J4 -> 0 | ... N6: =费用预算执行明细!N4 -> 0 | O6: =SUM(C6:N6) -> 97.3693 | P6: =IFERROR(O6/B6,) -> 0.13231322
A7: 人力费用 | B7: =费用预算执行明细!B5 -> 298.77 | C7: =费用预算执行明细!C5 -> 24.89 | D7: =费用预算执行明细!D5 -> 23.48 | E7: =费用预算执行明细!E5 -> 23.55 | F7: =费用预算执行明细!F5 -> 23.68 | G7: =费用预算执行明细!G5 -> 0 | H7: =费用预算执行明细!H5 -> 0 | I7: =费用预算执行明细!I5 -> 0 | ... N7: =费用预算执行明细!N5 -> 0 | O7: =SUM(C7:N7) -> 95.6 | P7: =IFERROR(O7/B7,) -> 0.31997858
A8: 日常费用 | B8: =费用预算执行明细!B14 -> 437.13 | C8: =费用预算执行明细!C14 -> -0.0007 | D8: =费用预算执行明细!D14 -> 0.1 | E8: =费用预算执行明细!E14 -> 0.11 | F8: =费用预算执行明细!F14 -> 1.56 | G8: =费用预算执行明细!G14 -> 0 | H8: =费用预算执行明细!H14 -> 0 | I8: =费用预算执行明细!I14 -> 0 | ... N8: =费用预算执行明细!N14 -> 0 | O8: =SUM(C8:N8) -> 1.7693 | P8: =IFERROR(O8/B8,) -> 0.0040475373
A9: 变动费用 | B9: =B10 -> 39.2 | C9: =费用预算执行明细!C46 -> 0.55 | D9: =费用预算执行明细!D46 -> 1.84 | E9: =费用预算执行明细!E46 -> 0 | F9: =费用预算执行明细!F46 -> 5.64 | G9: =费用预算执行明细!G46 -> 0 | H9: =费用预算执行明细!H46 -> 0 | I9: =费用预算执行明细!I46 -> 0 | J9: =费用预算执行明细!J46 -> 0 | ... N9: =费用预算执行明细!N46 -> 0 | O9: =SUM(C9:N9) -> 8.03 | P9: =IFERROR(O9/B9,) -> 0.20484694
A10: 经营变动费用支出 | B10: 39.2 | C10: =费用预算执行明细!C47 -> 0.55 | D10: =费用预算执行明细!D47 -> 1.84 | E10: =费用预算执行明细!E47 -> 0 | F10: =费用预算执行明细!F47 -> 5.64 | G10: =费用预算执行明细!G47 -> 0 | H10: =费用预算执行明细!H47 -> 0 | I10: =费用预算执行明细!I47 -> 0 | J10: =费用预算执行明细!J47 -> 0 | ... N10: =费用预算执行明细!N47 -> 0 | O10: =SUM(C10:N10) -> 8.03 | P10: =IFERROR(O10/B10,) -> 0.20484694
A11: 营业成本支出 | B11: 0 | C11: =费用预算执行明细!C80 -> 0 | D11: =费用预算执行明细!D80 -> 0 | E11: =费用预算执行明细!E80 -> 0 | F11: =费用预算执行明细!F80 -> 0 | G11: =费用预算执行明细!G80 -> 0 | H11: =费用预算执行明细!H80 -> 0 | I11: =费用预算执行明细!I80 -> 0 | J11: =费用预算执行明细!J80 -> 0 | ... N11: =费用预算执行明细!N80 -> 0 | O11: =SUM(C11:N11) -> 0 | P11: =IFERROR(O11/B11,) -> 0
A12: 资本性支出 | B12: 52 | C12: 0 | D12: 0 | E12: 0 | F12: 0 | O12: =SUM(C12:N12) -> 0 | P12: =IFERROR(O12/B12,) -> 0
A13: 折旧摊销 | B13: 1108.99 | C13: 91 | D13: 91 | E13: 176.32 | F13: 119.39 | O13: =SUM(C13:N13) -> 477.71 | P13: =IFERROR(O13/B13,) -> 0.43076132
A14: 财务费用 | B14: -14.95 | C14: -2.455 | D14: -1.08 | E14: 2 | F14: 0.07 | O14: =SUM(C14:N14) -> -1.465 | P14: =IFERROR(O14/B14,) -> 0.097993311
A15: 税金及附加 | B15: 336.94 | C15: 24.83 | D15: 24.69 | E15: 24.27 | F15: 25.46 | O15: =SUM(C15:N15) -> 99.25 | P15: =IFERROR(O15/B15,) -> 0.29456283
A16: 变动费用率 | B16: 0.092044315 | C16: =IFERROR(C9/C4,) -> 0.0047730626 | D16: =IFERROR(D9/D4,) -> 0.018840877 | E16: =IFERROR(E9/E4,) -> 0 | F16: =IFERROR(F9/F4,) -> 0.05500829 | G16: =IFERROR(G9/G4,) -> 0 | H16: =IFERROR(H9/H4,) -> 0 | I16: =IFERROR(I9/I4,) -> 0 | J16: =IFERROR(J9/J4,) -> 0 | ... O16: =IFERROR(O9/O4,) -> 0.019432277
A18: EBITDA | B18: 398.58 | C18: =C4-C6-C9-C15 -> 64.9607 | D18: =D4-D6-D9-D15 -> 47.55 | E18: =E4-E6-E9-E15 -> 49.88 | F18: =F4-F6-F9-F15 -> 46.19 | G18: =G4-G6-G9-G15 -> 0 | H18: =H4-H6-H9-H15 -> 0 | I18: =I4-I6-I9-I15 -> 0 | J18: =J4-J6-J9-J15 -> 0 | ... O18: =O4-O6-O9-O15 -> 208.5807 | P18: =IFERROR(O18/B18,) -> 0.5233095
A19: GOP | P19: =IFERROR(O19/B19,) -> 0
A21: 备注 | B21: EBITDA=营业收入-固定费用-变动费用-税金及附加
B22: GOP=营业收入-固定费用-变动费用-财务费用（不含利息费用）
B23: 需填列单元格

Sheet 费用预算执行明细
A1: 哈尔滨君康春夏秋冬置业有限公司2026年预算执行情况明细表
A2: 项目 | B2: 2026年预算 | C2: 2026年预算执行情况 | O2: 2026年实际 | P2: 执行率 | Q2: 单位：万元
C3: 1月 | D3: 2月 | E3: 3月 | F3: 4月 | G3: 5月 | H3: 6月 | I3: 7月 | J3: 8月 | K3: 9月 | L3: 10月 | M3: 11月 | N3: 12月
A4: 固定费用 | B4: =B14+B5 -> 735.9 | C4: =C14+C5 -> 24.8893 | D4: =D14+D5 -> 23.58 | E4: =E14+E5 -> 23.66 | F4: =F14+F5 -> 25.24 | G4: =G14+G5 -> 0 | H4: =H14+H5 -> 0 | I4: =I14+I5 -> 0 | ... N4: =N14+N5 -> 0 | O4: =SUM(C4:N4) -> 97.3693 | P4: =IFERROR(O4/B4,) -> 0.13231322
A5: 人力费用合计 | B5: =SUM(B6:B13) -> 298.77 | C5: =SUM(C6:C13) -> 24.89 | D5: =SUM(D6:D13) -> 23.48 | E5: =SUM(E6:E13) -> 23.55 | F5: =SUM(F6:F13) -> 23.68 | G5: =SUM(G6:G13) -> 0 | H5: =SUM(H6:H13) -> 0 | I5: =SUM(I6:I13) -> 0 | ... N5: =SUM(N6:N13) -> 0 | O5: =SUM(C5:N5) -> 95.6 | P5: =IFERROR(O5/B5,) -> 0.31997858
A6: 固定工资 | B6: 225.63 | C6: 19.6 | D6: 18.55 | E6: 18.21 | F6: 18.33 | O6: =SUM(C6:N6) -> 74.69 | P6: =IFERROR(O6/B6,) -> 0.33102868
A7: 绩效工资 | B7: 0 | O7: =SUM(C7:N7) -> 0 | P7: =IFERROR(O7/B7,) -> 0
A8: 奖金 | B8: 0 | O8: =SUM(C8:N8) -> 0 | P8: =IFERROR(O8/B8,) -> 0
A9: 福利费 | B9: 4.28 | O9: =SUM(C9:N9) -> 0 | P9: =IFERROR(O9/B9,) -> 0
A10: 工会经费 | B10: 5.66 | C10: 0.57 | D10: 0.21 | E10: 0.36 | F10: 0.37 | O10: =SUM(C10:N10) -> 1.51 | P10: =IFERROR(O10/B10,) -> 0.26678445
A11: 招聘费 | B11: 0 | O11: =SUM(C11:N11) -> 0 | P11: =IFERROR(O11/B11,) -> 0
A12: 社会保险费 | B12: 45.2 | C12: 3.17 | D12: 3.17 | E12: 3.35 | F12: 3.35 | O12: =SUM(C12:N12) -> 13.04 | P12: =IFERROR(O12/B12,) -> 0.28849558
A13: 住房公积金 | B13: 18 | C13: 1.55 | D13: 1.55 | E13: 1.63 | F13: 1.63 | O13: =SUM(C13:N13) -> 6.36 | P13: =IFERROR(O13/B13,) -> 0.35333333
A14: 固定费用支出合计 | B14: =SUM(B15:B45) -> 437.13 | C14: =SUM(C15:C45) -> -0.0007 | D14: =SUM(D15:D45) -> 0.1 | E14: =SUM(E15:E45) -> 0.11 | F14: =SUM(F15:F45) -> 1.56 | G14: =SUM(G15:G45) -> 0 | H14: =SUM(H15:H45) -> 0 | I14: =SUM(I15:I45) -> 0 | ... N14: =SUM(N15:N45) -> 0 | O14: =SUM(C14:N14) -> 1.7693 | P14: =IFERROR(O14/B14,) -> 0.0040475373
A15: 邮寄费 | B15: 0.6 | F15: 0.12 | O15: =SUM(C15:N15) -> 0.12 | P15: =IFERROR(O15/B15,) -> 0.2
A16: 差旅费 | B16: 2 | F16: 1.26 | O16: =SUM(C16:N16) -> 1.26 | P16: =IFERROR(O16/B16,) -> 0.63
A17: 业务招待费 | B17: 0 | O17: =SUM(C17:N17) -> 0 | P17: =IFERROR(O17/B17,) -> 0
A18: 汽车费 | B18: 0 | O18: =SUM(C18:N18) -> 0 | P18: =IFERROR(O18/B18,) -> 0
A19: 低值易耗品及修理费 | B19: 0.2 | O19: =SUM(C19:N19) -> 0 | P19: =IFERROR(O19/B19,) -> 0
A20: 信息系统费 | B20: 0.75 | O20: =SUM(C20:N20) -> 0 | P20: =IFERROR(O20/B20,) -> 0
A21: 通讯费 | B21: 0.32 | D21: 0.07 | O21: =SUM(C21:N21) -> 0.07 | P21: =IFERROR(O21/B21,) -> 0.21875
A22: 交通费 | B22: 0.2 | F22: 0 | O22: =SUM(C22:N22) -> 0 | P22: =IFERROR(O22/B22,) -> 0
A23: 办公费 | B23: 2 | D23: 0.03 | E23: 0.02 | F23: 0.18 | O23: =SUM(C23:N23) -> 0.23 | P23: =IFERROR(O23/B23,) -> 0.115
A24: 会议费 | B24: 0 | O24: =SUM(C24:N24) -> 0 | P24: =IFERROR(O24/B24,) -> 0
A25: 水电费 | B25: 8 | O25: =SUM(C25:N25) -> 0 | P25: =IFERROR(O25/B25,) -> 0
A26: 培训费 | B26: 0 | O26: =SUM(C26:N26) -> 0 | P26: =IFERROR(O26/B26,) -> 0
A27: 展览费 | B27: 0 | O27: =SUM(C27:N27) -> 0 | P27: =IFERROR(O27/B27,) -> 0
A28: 广告宣传费 | B28: 0 | O28: =SUM(C28:N28) -> 0 | P28: =IFERROR(O28/B28,) -> 0
A29: 咨询服务费 | B29: =93-60 -> 33 | O29: =SUM(C29:N29) -> 0 | P29: =IFERROR(O29/B29,) -> 0
A30: 法律诉讼费 | B30: 13.5 | O30: =SUM(C30:N30) -> 0 | P30: =IFERROR(O30/B30,) -> 0
A31: 工作餐费 | B31: 0 | O31: =SUM(C31:N31) -> 0 | P31: =IFERROR(O31/B31,) -> 0
A32: 报关及代理费 | B32: 0 | O32: =SUM(C32:N32) -> 0 | P32: =IFERROR(O32/B32,) -> 0
A33: 研究开发费 | B33: 0 | O33: =SUM(C33:N33) -> 0 | P33: =IFERROR(O33/B33,) -> 0
A34: 质检认证费 | B34: 0 | O34: =SUM(C34:N34) -> 0 | P34: =IFERROR(O34/B34,) -> 0
A35: 排污费 | B35: 0 | O35: =SUM(C35:N35) -> 0 | P35: =IFERROR(O35/B35,) -> 0
A36: 社保服务费 | B36: 0 | O36: =SUM(C36:N36) -> 0 | P36: =IFERROR(O36/B36,) -> 0
A37: 劳动保护费 | B37: 0 | O37: =SUM(C37:N37) -> 0 | P37: =IFERROR(O37/B37,) -> 0
A38: 残疾人就业保障金 | B38: 0 | O38: =SUM(C38:N38) -> 0 | P38: =IFERROR(O38/B38,) -> 0
A39: 财产保险费 | B39: 10 | C39: -0.0007 | O39: =SUM(C39:N39) -> -0.0007 | P39: =IFERROR(O39/B39,) -> -7e-05
A40: 房租及物业费 | B40: 226.56 | E40: 0.09 | O40: =SUM(C40:N40) -> 0.09 | P40: =IFERROR(O40/B40,) -> 0.00039724576
A41: 取暖费 | B41: 130 | O41: =SUM(C41:N41) -> 0 | P41: =IFERROR(O41/B41,) -> 0
A42: 存货盘存 | B42: 0 | O42: =SUM(C42:N42) -> 0 | P42: =IFERROR(O42/B42,) -> 0
A43: 销售代理费 | B43: 0 | O43: =SUM(C43:N43) -> 0 | P43: =IFERROR(O43/B43,) -> 0
A44: 销售佣金 | B44: 0 | O44: =SUM(C44:N44) -> 0 | P44: =IFERROR(O44/B44,) -> 0
A45: 其他 | B45: 10 | E45: 0 | O45: =SUM(C45:N45) -> 0 | P45: =IFERROR(O45/B45,) -> 0
A46: 变动费用 | B46: =B47+B80 -> 39.2 | C46: =C47+C80 -> 0.55 | D46: =D47+D80 -> 1.84 | E46: =E47+E80 -> 0 | F46: =F47+F80 -> 5.64 | G46: =G47+G80 -> 0 | H46: =H47+H80 -> 0 | I46: =I47+I80 -> 0 | ... N46: =N47+N80 -> 0 | O46: =SUM(C46:N46) -> 8.03 | P46: =IFERROR(O46/B46,) -> 0.20484694
A47: 变动费用支出合计 | B47: =SUM(B48:B79) -> 39.2 | C47: =SUM(C48:C79) -> 0.55 | D47: =SUM(D48:D79) -> 1.84 | E47: =SUM(E48:E79) -> 0 | F47: =SUM(F48:F79) -> 5.64 | G47: =SUM(G48:G79) -> 0 | H47: =SUM(H48:H79) -> 0 | I47: =SUM(I48:I79) -> 0 | ... N47: =SUM(N48:N79) -> 0 | O47: =SUM(C47:N47) -> 8.03 | P47: =IFERROR(O47/B47,) -> 0.20484694
A48: 邮寄费 | B48: 0 | O48: =SUM(C48:N48) -> 0 | P48: =IFERROR(O48/B48,) -> 0
A49: 差旅费 | B49: 0 | O49: =SUM(C49:N49) -> 0 | P49: =IFERROR(O49/B49,) -> 0
A50: 业务招待费 | B50: 10 | D50: 0.35 | F50: 0.36 | O50: =SUM(C50:N50) -> 0.71 | P50: =IFERROR(O50/B50,) -> 0.071
A51: 汽车费 | B51: 0 | O51: =SUM(C51:N51) -> 0 | P51: =IFERROR(O51/B51,) -> 0
A52: 低值易耗品及修理费 | B52: 0 | O52: =SUM(C52:N52) -> 0 | P52: =IFERROR(O52/B52,) -> 0
A53: 信息系统费 | B53: 0 | O53: =SUM(C53:N53) -> 0 | P53: =IFERROR(O53/B53,) -> 0
A54: 通讯费 | B54: 0 | O54: =SUM(C54:N54) -> 0 | P54: =IFERROR(O54/B54,) -> 0
A55: 交通费 | B55: 0 | O55: =SUM(C55:N55) -> 0 | P55: =IFERROR(O55/B55,) -> 0
A56: 办公费 | B56: 0 | O56: =SUM(C56:N56) -> 0 | P56: =IFERROR(O56/B56,) -> 0
A57: 会议费 | B57: 0 | O57: =SUM(C57:N57) -> 0 | P57: =IFERROR(O57/B57,) -> 0
A58: 水电费 | B58: 0 | O58: =SUM(C58:N58) -> 0 | P58: =IFERROR(O58/B58,) -> 0
A59: 招聘费 | B59: 0 | O59: =SUM(C59:N59) -> 0 | P59: =IFERROR(O59/B59,) -> 0
A60: 展览费 | B60: 0 | O60: =SUM(C60:N60) -> 0 | P60: =IFERROR(O60/B60,) -> 0
A61: 广告宣传费 | B61: 5 | O61: =SUM(C61:N61) -> 0 | P61: =IFERROR(O61/B61,) -> 0
A62: 咨询服务费 | B62: 0 | O62: =SUM(C62:N62) -> 0 | P62: =IFERROR(O62/B62,) -> 0
A63: 法律诉讼费 | B63: 7.5 | C63: -0.29 | D63: 0.3 | O63: =SUM(C63:N63) -> 0.01 | P63: =IFERROR(O63/B63,) -> 0.0013333333
A64: 工作餐费 | B64: 0 | O64: =SUM(C64:N64) -> 0 | P64: =IFERROR(O64/B64,) -> 0
A65: 报关及代理费 | B65: 0 | O65: =SUM(C65:N65) -> 0 | P65: =IFERROR(O65/B65,) -> 0
A66: 研究开发费 | B66: 0 | O66: =SUM(C66:N66) -> 0 | P66: =IFERROR(O66/B66,) -> 0
A67: 质检认证费 | B67: 0 | O67: =SUM(C67:N67) -> 0 | P67: =IFERROR(O67/B67,) -> 0
A68: 福利费 | B68: 0 | O68: =SUM(C68:N68) -> 0 | P68: =IFERROR(O68/B68,) -> 0
A69: 排污费 | B69: 0 | O69: =SUM(C69:N69) -> 0 | P69: =IFERROR(O69/B69,) -> 0
A70: 社保服务费 | B70: 0 | O70: =SUM(C70:N70) -> 0 | P70: =IFERROR(O70/B70,) -> 0
A71: 劳动保护费 | B71: 0 | O71: =SUM(C71:N71) -> 0 | P71: =IFERROR(O71/B71,) -> 0
A72: 残疾人就业保障金 | B72: 0 | O72: =SUM(C72:N72) -> 0 | P72: =IFERROR(O72/B72,) -> 0
A73: 财产保险费 | B73: 0 | O73: =SUM(C73:N73) -> 0 | P73: =IFERROR(O73/B73,) -> 0
A74: 房租及物业费 | B74: 0 | O74: =SUM(C74:N74) -> 0 | P74: =IFERROR(O74/B74,) -> 0
A75: 开办费 | B75: 0 | O75: =SUM(C75:N75) -> 0 | P75: =IFERROR(O75/B75,) -> 0
A76: 存货盘存 | B76: 0 | O76: =SUM(C76:N76) -> 0 | P76: =IFERROR(O76/B76,) -> 0
A77: 销售代理费 | B77: 10 | D77: 1.19 | F77: 5.28 | O77: =SUM(C77:N77) -> 6.47 | P77: =IFERROR(O77/B77,) -> 0.647
A78: 销售佣金 | B78: 6.7 | C78: 0.84 | O78: =SUM(C78:N78) -> 0.84 | P78: =IFERROR(O78/B78,) -> 0.12537313
A79: 其他 | B79: 0 | O79: =SUM(C79:N79) -> 0 | P79: =IFERROR(O79/B79,) -> 0
A80: 营业成本支出合计 | B80: =SUM(B81:B85) -> 0 | C80: =SUM(C81:C85) -> 0 | D80: =SUM(D81:D85) -> 0 | E80: =SUM(E81:E85) -> 0 | F80: =SUM(F81:F85) -> 0 | G80: =SUM(G81:G85) -> 0 | H80: =SUM(H81:H85) -> 0 | I80: =SUM(I81:I85) -> 0 | ... N80: =SUM(N81:N85) -> 0 | O80: =SUM(C80:N80) -> 0 | P80: =IFERROR(O80/B80,) -> 0
A81: 空置房物业费 | B81: 0 | O81: =SUM(C81:N81) -> 0
A82: 客房成本 | B82: 0 | O82: =SUM(C82:N82) -> 0 | P82: =IFERROR(O82/B82,) -> 0
A83: 餐饮成本 | B83: 0 | O83: =SUM(C83:N83) -> 0 | P83: =IFERROR(O83/B83,) -> 0
A84: 会务成本 | B84: 0 | O84: =SUM(C84:N84) -> 0 | P84: =IFERROR(O84/B84,) -> 0
A85: 中厨房外包人力成本 | B85: 0 | O85: =SUM(C85:N85) -> 0 | P85: =IFERROR(O85/B85,) -> 0
A86: 折旧费 | C86: 0.08 | D86: 0.08 | E86: 0.08 | F86: 0.08
A87: 需填列

Sheet 资本性支出计划与执行
A1: 哈尔滨君康春夏秋冬置业有限公司2026年资本性支出执行情况明细表
A2: 资产类别 | B2: 资产类型 | C2: 资产名称 | D2: 数量 | E2: 单价 | F2: 金额 | G2: 2026年预算 | H2: 2026年实际
A3: 固定资产 | B3: 办公通讯设备 | C3: 电脑
C4: 彩色打印机
C5: 笔记本电脑
A6: 无形资产 | B6: 业务系统 | C6: 线上推广与在线选房平台小程序
A7: 长期待摊费用 | B7: 长期待摊费用 | C7: 项目公司自持房源空调维护、维修 | G7: 7
C8: 更换“君康大厦”标识 | G8: 45
A9: 资本性支出合计 | G9: =SUM(G3:G8) -> 52 | H9: =SUM(H3:H5) -> 0
A11: 需填列
